Workbook

Sheet Read_Me
A1: Workbook owner | B1: Dana Morales, Advertising Sales Desk Supervisor
A2: Lifecycle state | B2: Approved executable record
A3: Approved objective | B3: Rank the July escalated renewal portfolio and convert approved accounts into compliant recovery actions.
A4: Source refresh | B4: CRM 2026-07-13; ad-ops 2026-07-13; orders 2026Q3; contacts 2026-07-10; activity through 2026-07-14; approval 2026-07-15.
A5: Navigation | B5: Use Dashboard first, then Scoring, Decisions, Checks, and Raw_Data sheets for lineage.

Sheet Metric_Definitions
A1: Metric | B1: Definition | C1: Unit
A2: Renewal exposure | B2: Renewal opportunity amount from order history | C2: USD
A3: Forecast variance | B3: Current Q3 forecast minus Q3 2025 baseline | C3: USD
A4: Issue burden score | B4: Open case count, severity, and issue age | C4: 0-100
A5: Operational recovery risk | B5: Weighted health, issue burden, and activity aging risk | C5: 0-100
A6: Priority score | B6: Exposure, risk, urgency, contact readiness, and forecast variance weighted for recovery order | C6: 0-100
A7: Offer compliance | B7: Recommended offer stays within local authority or remains a controlled exception | C7: Status

Sheet Assumptions
A1: Assumption | B1: Value
A2: Exposure weight | B2: 0.3
A3: Recovery risk weight | B3: 0.35
A4: Urgency weight | B4: 0.2
A5: Contact readiness weight | B5: 0.1
A6: Forecast variance weight | B6: 0.05
A7: Exposure score denominator | B7: 400000
A8: As of date | B8: 46218
D11: PriorityTierList | E11: DecisionStatusList | F11: DecisionActionList | G11: ExceptionRouteList
D12: Tier 1 | E12: Approved execution | F12: Confirm makegood inventory and delivery recovery plan | G12: Decision-maker outreach permission pending
D13: Tier 2 | E13: Controlled exception | F13: Deliver reconciled reporting package and executive summary | G13: Requested credit is above supervisor authority
D14: Tier 3 | E14: Excluded - no action | F14: Confirm verified billing credit and renewal rate hold | G14: Ad-ops blocker not cleared
D15: Controlled exception/hold | F15: Offer equivalent package swap after trafficking confirmation | G15: Closed renewal
F16: Swap misaligned audience package and reset delivery proof | G16: Contract terms outside local authority
F17: Confirm verified invoice credit and corrected bill date | G17: Customer requested September review
F18: Confirm makegood placement and revised delivery dates | G18: Ready to schedule
F19: Send reconciled district reach report and renewal summary | G19: Controlled exception
F20: Confirm package swap and creative approval timeline | G20: No sprint outreach
F21: Offer 60-day rate hold without additional credit
F22: Send corrected lift summary and renewal confidence note
F23: Confirm makegood placement and invoice correction route
F24: Hold customer-facing offer until decision-maker route is approved
F25: Route credit request to manager; do not promise local credit
F26: Wait for product feed fix before customer offer
F27: No sprint action; keep closure note
F28: Escalate to manager and legal owner; no rep commitment
F29: Hold for September agency review

Sheet Raw_CRM
A1: Account ID | B1: Account Name | C1: Segment | D1: Account Tier | E1: Owner Rep | F1: Renewal Date | G1: Health Score | H1: Lifecycle State | I1: Forecast Category | J1: Requested Recovery Value | K1: Escalation Reason | L1: Approved Action Note
A2: A-1001 | B2: Meridian Health Partners | C2: Healthcare | D2: Key Growth | E2: Maya Chen | F2: 46227 | G2: 48 | H2: Approved execution | I2: Commit at risk | J2: 21000 | K2: Delivery underpacing and reporting trust | L2: Confirm makegood inventory and delivery recovery plan
A3: A-1002 | B3: Larkspur Credit Union | C3: Financial Services | D3: Core | E3: Jordan Patel | F3: 46234 | G3: 52 | H3: Approved execution | I3: Best case | J3: 0 | K3: Reporting discrepancy | L3: Deliver reconciled reporting package and executive summary
A4: A-1003 | B4: Cobalt Cloud Systems | C4: Technology | D4: Key Growth | E4: Priya Nair | F4: 46239 | G4: 56 | H4: Approved execution | I4: Commit at risk | J4: 9500 | K4: Invoice credit and rate hold request | L4: Confirm verified billing credit and renewal rate hold
A5: A-1004 | B5: Harborview Furnishings | C5: Retail | D5: Core | E5: Luis Romero | F5: 46231 | G5: 61 | H5: Approved execution | I5: Best case | J5: 12000 | K5: Creative trafficking delay | L5: Offer equivalent package swap after trafficking confirmation
A6: A-1005 | B6: Axion Robotics | C6: Industrial | D6: Key Growth | E6: Devon Brooks | F6: 46246 | G6: 44 | H6: Approved execution | I6: Commit at risk | J6: 18000 | K6: Audience mismatch and delivery quality | L6: Swap misaligned audience package and reset delivery proof
A7: A-1006 | B7: Greenway Kitchens | C7: Retail | D7: Emerging | E7: Maya Chen | F7: 46229 | G7: 68 | H7: Approved execution | I7: Pipeline | J7: 4800 | K7: Billing error | L7: Confirm verified invoice credit and corrected bill date
A8: A-1007 | B8: Northline Insurance | C8: Financial Services | D8: Core | E8: Jordan Patel | F8: 46237 | G8: 50 | H8: Approved execution | I8: Commit at risk | J8: 22000 | K8: Delivery underpacing | L8: Confirm makegood placement and revised delivery dates
A9: A-1008 | B9: Veridian Charter Schools | C9: Education | D9: Emerging | E9: Priya Nair | F9: 46249 | G9: 63 | H9: Approved execution | I9: Pipeline | J9: 0 | K9: Reporting trust | L9: Send reconciled district reach report and renewal summary
A10: A-1009 | B10: Copper Trail Hospitality | C10: Travel | D10: Core | E10: Luis Romero | F10: 46232 | G10: 58 | H10: Approved execution | I10: Best case | J10: 15000 | K10: Creative approval blocker | L10: Confirm package swap and creative approval timeline
A11: A-1010 | B11: Finch Legal Group | C11: Professional Services | D11: Emerging | E11: Devon Brooks | F11: 46254 | G11: 70 | H11: Approved execution | I11: Pipeline | J11: 0 | K11: Renewal rate objection | L11: Offer 60-day rate hold without additional credit
A12: A-1011 | B12: Solstice Energy Co-op | C12: Energy | D12: Core | E12: Maya Chen | F12: 46243 | G12: 55 | H12: Approved execution | I12: Best case | J12: 0 | K12: Reporting discrepancy | L12: Send corrected lift summary and renewal confidence note
A13: A-1012 | B13: Vesta Apparel Collective | C13: Retail | D13: Key Growth | E13: Jordan Patel | F13: 46235 | G13: 47 | H13: Approved execution | I13: Commit at risk | J13: 24000 | K13: Delivery underpacing and invoice dispute | L13: Confirm makegood placement and invoice correction route
... A19: A-1018 | B19: Pinyon Outdoor Media Buyers | C19: Agency | D19: Core | E19: Priya Nair | F19: 46283 | G19: 66 | H19: Excluded - September review | I19: Pipeline | J19: 0 | K19: Customer requested pause until agency consolidation | L19: Hold for September agency review

Sheet Raw_Cases
A1: Case ID | B1: Account ID | C1: Order ID | D1: Issue Type | E1: Severity | F1: Severity Score | G1: Opened Date | H1: Issue Age Days | I1: Sla Target Date | J1: Last Update Date | K1: Expected Resolution Date | L1: Current Owner | M1: Issue Status | N1: Resolution Confidence | O1: Root Cause | P1: Customer Impact | Q1: Open Dependency
A2: CASE-7201 | B2: A-1001 | C2: ORD-73101 | D2: Delivery Underpacing | E2: High | F2: 4 | G2: 46193 | H2: 25 | I2: 46211 | J2: 46216 | K2: 46219 | L2: Ad Ops - Lena Ortiz | M2: Waiting on Ad Ops | N2: Medium | O2: Inventory pacing lag | P2: Renewal confidence and delivery promise | Q2: Traffic pacing confirmation
A3: CASE-7202 | B3: A-1001 | C3: ORD-73101 | D3: Reporting Discrepancy | E3: Medium | F3: 3 | G3: 46205 | H3: 13 | I3: 46215 | J3: 46216 | K3: 46220 | L3: Reporting - Eli Park | M3: Open | N3: Medium | O3: UTM match mismatch | P3: Trust in delivery report | Q3: Reach report reconciliation
A4: CASE-7203 | B4: A-1002 | C4: ORD-73102 | D4: Reporting Discrepancy | E4: High | F4: 4 | G4: 46201 | H4: 17 | I4: 46212 | J4: 46216 | K4: 46220 | L4: Reporting - Eli Park | M4: Open | N4: High | O4: Audience reach export defect | P4: Renewal proof stalled | Q4: Corrected report
A5: CASE-7204 | B5: A-1003 | C5: ORD-73103 | D5: Billing Error | E5: High | F5: 4 | G5: 46191 | H5: 27 | I5: 46208 | J5: 46215 | K5: 46219 | L5: Billing - Nora Vale | M5: Resolved Pending Customer | N5: High | O5: Duplicate invoice line | P5: Signature withheld pending credit | Q5: Credit memo confirmation
A6: CASE-7205 | B6: A-1003 | C6: ORD-73103 | D6: Renewal Rate Objection | E6: Medium | F6: 3 | G6: 46211 | H6: 7 | I6: 46221 | J6: 46217 | K6: 46222 | L6: Sales Ops - Aaron Kim | M6: Waiting on Sales | N6: High | O6: Rate card update not explained | P6: Commercial approval delay | Q6: Rate hold language
A7: CASE-7206 | B7: A-1004 | C7: ORD-73104 | D7: Creative Trafficking | E7: Medium | F7: 3 | G7: 46204 | H7: 14 | I7: 46214 | J7: 46216 | K7: 46219 | L7: Ad Ops - Lena Ortiz | M7: Waiting on Ad Ops | N7: High | O7: Creative tags rejected | P7: Launch dates unclear | Q7: Creative retagging
A8: CASE-7207 | B8: A-1005 | C8: ORD-73105 | D8: Audience Mismatch | E8: Critical | F8: 5 | G8: 46187 | H8: 31 | I8: 46205 | J8: 46216 | K8: 46221 | L8: Product Support - Ravi Mehta | M8: Open | N8: Medium | O8: Lookalike seed list mismatch | P8: Audience quality dispute | Q8: Audience rebuild proof
A9: CASE-7208 | B9: A-1005 | C9: ORD-73105 | D9: Delivery Underpacing | E9: High | F9: 4 | G9: 46203 | H9: 15 | I9: 46213 | J9: 46216 | K9: 46221 | L9: Ad Ops - Lena Ortiz | M9: Waiting on Ad Ops | N9: Medium | O9: Audience cap after mismatch | P9: Forecast risk | Q9: Pacing reset
A10: CASE-7209 | B10: A-1006 | C10: ORD-73106 | D10: Billing Error | E10: Medium | F10: 3 | G10: 46208 | H10: 10 | I10: 46218 | J10: 46216 | K10: 46220 | L10: Billing - Nora Vale | M10: Open | N10: High | O10: Tax line miscoded | P10: Owner approval delayed | Q10: Credit memo draft
A11: CASE-7210 | B11: A-1007 | C11: ORD-73107 | D11: Delivery Underpacing | E11: High | F11: 4 | G11: 46195 | H11: 23 | I11: 46211 | J11: 46216 | K11: 46220 | L11: Ad Ops - Lena Ortiz | M11: Waiting on Ad Ops | N11: Medium | O11: Publisher inventory drop | P11: Written remedy requested | Q11: Makegood placement
A12: CASE-7211 | B12: A-1008 | C12: ORD-73108 | D12: Reporting Discrepancy | E12: Medium | F12: 3 | G12: 46209 | H12: 9 | I12: 46219 | J12: 46216 | K12: 46223 | L12: Reporting - Eli Park | M12: Open | N12: High | O12: District reach grouping error | P12: Budget meeting proof | Q12: Corrected district report
A13: CASE-7212 | B13: A-1009 | C13: ORD-73109 | D13: Creative Trafficking | E13: High | F13: 4 | G13: 46198 | H13: 20 | I13: 46210 | J13: 46216 | K13: 46219 | L13: Ad Ops - Lena Ortiz | M13: Waiting on Ad Ops | N13: Medium | O13: Brand safety tag review | P13: August flight risk | Q13: Creative approval proof
... A24: CASE-7223 | B24: A-1018 | C24: ORD-73118 | D24: Agency Consolidation | E24: Low | F24: 2 | G24: 46212 | H24: 6 | I24: 46227 | J24: 46217 | K24: 46267 | L24: Sales Ops - Aaron Kim | M24: Waiting on Customer | N24: High | O24: Agency buying team reorg | P24: Customer requested hold | Q24: September rebrief

Sheet Raw_Orders
A1: Account ID | B1: Opportunity ID | C1: Order ID | D1: Baseline Revenue | E1: Current Forecast | F1: Renewal Exposure | G1: Probability | H1: Forecast Category
A2: A-1001 | B2: OPP-2601 | C2: ORD-73101 | D2: 310000 | E2: 272000 | F2: 340000 | G2: 0.72 | H2: Commit at risk
A3: A-1002 | B3: OPP-2602 | C3: ORD-73102 | D3: 205000 | E3: 184000 | F3: 220000 | G3: 0.68 | H3: Best case
A4: A-1003 | B4: OPP-2603 | C4: ORD-73103 | D4: 275000 | E4: 240000 | F4: 295000 | G4: 0.65 | H4: Commit at risk
A5: A-1004 | B5: OPP-2604 | C5: ORD-73104 | D5: 142000 | E5: 129000 | F5: 150000 | G5: 0.7 | H5: Best case
A6: A-1005 | B6: OPP-2605 | C6: ORD-73105 | D6: 390000 | E6: 318000 | F6: 410000 | G6: 0.58 | H6: Commit at risk
A7: A-1006 | B7: OPP-2606 | C7: ORD-73106 | D7: 76000 | E7: 71000 | F7: 82000 | G7: 0.64 | H7: Pipeline
A8: A-1007 | B8: OPP-2607 | C8: ORD-73107 | D8: 246000 | E8: 206000 | F8: 260000 | G8: 0.61 | H8: Commit at risk
A9: A-1008 | B9: OPP-2608 | C9: ORD-73108 | D9: 98000 | E9: 88000 | F9: 110000 | G9: 0.6 | H9: Pipeline
A10: A-1009 | B10: OPP-2609 | C10: ORD-73109 | D10: 174000 | E10: 149000 | F10: 190000 | G10: 0.63 | H10: Best case
A11: A-1010 | B11: OPP-2610 | C11: ORD-73110 | D11: 72000 | E11: 70000 | F11: 75000 | G11: 0.59 | H11: Pipeline
A12: A-1011 | B12: OPP-2611 | C12: ORD-73111 | D12: 160000 | E12: 140000 | F12: 175000 | G12: 0.62 | H12: Best case
A13: A-1012 | B13: OPP-2612 | C13: ORD-73112 | D13: 290000 | E13: 238000 | F13: 305000 | G13: 0.57 | H13: Commit at risk
... A19: A-1018 | B19: OPP-2618 | C19: ORD-73118 | D19: 124000 | E19: 118000 | F19: 135000 | G19: 0.5 | H19: Pipeline

Sheet Raw_Contacts
A1: Contact ID | B1: Account ID | C1: Account Name | D1: Contact Name | E1: Title | F1: Contact Role | G1: Decision Authority | H1: Outreach Permission | I1: Preferred Channel | J1: Timezone | K1: Unavailable Window | L1: Sensitivity Flag | M1: Owner Rep | N1: Backup Owner
A2: CT-001A | B2: A-1001 | C2: Meridian Health Partners | D2: Dr. Lena Morris | E2: Chief Marketing Officer | F2: Final Renewal Approver | G2: Yes | H2: Approved | I2: Email then call | J2: Eastern | K2: None | L2: Executive expects delivery plan | M2: Maya Chen | N2: Devon Brooks
A3: CT-001B | B3: A-1001 | C3: Meridian Health Partners | D3: Nora Blake | E3: Ad Operations Counterpart | F3: Operational Contact | G3: No | H3: Approved | I3: Email | J3: Eastern | K3: None | L3: Standard operating route | M3: Maya Chen | N3: Devon Brooks
A4: CT-002A | B4: A-1002 | C4: Larkspur Credit Union | D4: Tanya Wells | E4: Director of Marketing | F4: Final Renewal Approver | G4: Yes | H4: Approved | I4: Email | J4: Central | K4: Avoid Friday after 12:00 | L4: Compliance copy required | M4: Jordan Patel | N4: Maya Chen
A5: CT-002B | B5: A-1002 | C5: Larkspur Credit Union | D5: Theo Walsh | E5: Compliance Marketing Contact | F5: Operational Contact | G5: No | H5: Approved | I5: Email | J5: Eastern | K5: None | L5: Standard operating route | M5: Jordan Patel | N5: Maya Chen
A6: CT-003A | B6: A-1003 | C6: Cobalt Cloud Systems | D6: Rafael Soto | E6: VP Demand Generation | F6: Final Renewal Approver | G6: Yes | H6: Approved | I6: Call | J6: Pacific | K6: Unavailable July 22 AM | L6: Wants billing proof first | M6: Priya Nair | N6: Jordan Patel
A7: CT-003B | B7: A-1003 | C7: Cobalt Cloud Systems | D7: Vikram Shah | E7: Demand Operations Contact | F7: Operational Contact | G7: No | H7: Approved | I7: Email | J7: Eastern | K7: None | L7: Standard operating route | M7: Priya Nair | N7: Jordan Patel
A8: CT-003C | B8: A-1003 | C8: Cobalt Cloud Systems | D8: Rafael Finance Desk | E8: Finance Contact | F8: Finance Contact | G8: No | H8: Finance Only | I8: Email | J8: Pacific | K8: None | L8: Use only for billing documentation | M8: Priya Nair | N8: Jordan Patel
A9: CT-004A | B9: A-1004 | C9: Harborview Furnishings | D9: Nina Cho | E9: Retail Media Lead | F9: Final Renewal Approver | G9: Yes | H9: Approved | I9: Email | J9: Pacific | K9: None | L9: Creative team must be copied | M9: Luis Romero | N9: Priya Nair
A10: CT-004B | B10: A-1004 | C10: Harborview Furnishings | D10: Paige Ellis | E10: Campaign Operations Contact | F10: Operational Contact | G10: No | H10: Approved | I10: Email | J10: Eastern | K10: None | L10: Standard operating route | M10: Luis Romero | N10: Priya Nair
A11: CT-005A | B11: A-1005 | C11: Axion Robotics | D11: Mark Feld | E11: VP Marketing | F11: Final Renewal Approver | G11: Yes | H11: Approved | I11: Call | J11: Central | K11: Unavailable July 19 | L11: Needs audience proof | M11: Devon Brooks | N11: Luis Romero
A12: CT-005B | B12: A-1005 | C12: Axion Robotics | D12: Olivia Grant | E12: Media Operations Contact | F12: Operational Contact | G12: No | H12: Approved | I12: Email | J12: Eastern | K12: None | L12: Standard operating route | M12: Devon Brooks | N12: Luis Romero
... A41: CT-018B | B41: A-1018 | C41: Pinyon Outdoor Media Buyers | D41: Noah Becker | E41: Agency Planner | F41: Operational Contact | G41: No | H41: Approved | I41: Email | J41: Pacific | K41: None | L41: Standard operating route | M41: Priya Nair | N41: Luis Romero

Sheet Raw_Activity
A1: Activity ID | B1: Account ID | C1: Owner Rep | D1: Activity Type | E1: Activity Date | F1: Customer Request | G1: Internal Commitment | H1: Commitment Due Date | I1: Commitment Status | J1: Confirmation Source | K1: Customer Sentiment | L1: Requested Decision Date | M1: Next Step | N1: Related Case ID | O1: Note
A2: ACT-26001A | B2: A-1001 | C2: Maya Chen | D2: Customer call | E2: 46206 | F2: CMO asked for delivery plan before renewal call. | G2: Open case review with operational owner | H2: 46210 | I2: Completed | J2: CRM call note | K2: Concerned | L2: 46227 | M2: Prepare recovery evidence | N2: CASE-7201 | O2: Initial escalation intake
A3: ACT-26001B | B3: A-1001 | C3: Maya Chen | D3: Email | E3: 46215 | F3: CMO asked for delivery plan before renewal call. | G3: Send corrected pacing plan | H3: 46217 | I3: Overdue | J3: Gmail thread | K3: Escalated | L3: 46227 | M3: Confirm makegood inventory and delivery recovery plan | N3: CASE-7201 | O3: Commitment carried into recovery review
A4: ACT-26002A | B4: A-1002 | C4: Jordan Patel | D4: Customer call | E4: 46204 | F4: Marketing director requested corrected reach report. | G4: Open case review with operational owner | H4: 46208 | I4: Completed | J4: CRM call note | K4: Concerned | L4: 46234 | M4: Prepare recovery evidence | N4: CASE-7203 | O4: Initial escalation intake
A5: ACT-26002B | B5: A-1002 | C5: Jordan Patel | D5: Email | E5: 46213 | F5: Marketing director requested corrected reach report. | G5: Provide reconciled reach report | H5: 46220 | I5: Open | J5: Gmail thread | K5: Concerned | L5: 46234 | M5: Deliver reconciled reporting package and executive summary | N5: CASE-7203 | O5: Commitment carried into recovery review
A6: ACT-26003A | B6: A-1003 | C6: Priya Nair | D6: Customer call | E6: 46205 | F6: Demand gen VP asked for invoice correction before signing. | G6: Open case review with operational owner | H6: 46209 | I6: Completed | J6: CRM call note | K6: Concerned | L6: 46235 | M6: Prepare recovery evidence | N6: CASE-7204 | O6: Initial escalation intake
A7: ACT-26003B | B7: A-1003 | C7: Priya Nair | D7: Email | E7: 46214 | F7: Demand gen VP asked for invoice correction before signing. | G7: Confirm billing investigation opened | H7: 46215 | I7: Completed | J7: Gmail thread | K7: Concerned | L7: 46239 | M7: Confirm verified billing credit and renewal rate hold | N7: CASE-7204 | O7: Commitment carried into recovery review
A8: ACT-26004A | B8: A-1004 | C8: Luis Romero | D8: Customer call | E8: 46203 | F8: Retail media lead requested trafficking fix and revised launch dates. | G8: Open case review with operational owner | H8: 46207 | I8: Completed | J8: CRM call note | K8: Cautious | L8: 46231 | M8: Prepare recovery evidence | N8: CASE-7206 | O8: Initial escalation intake
A9: ACT-26004B | B9: A-1004 | C9: Luis Romero | D9: Email | E9: 46212 | F9: Retail media lead requested trafficking fix and revised launch dates. | G9: Send creative retagging ETA | H9: 46215 | I9: Overdue | J9: Gmail thread | K9: Concerned | L9: 46231 | M9: Offer equivalent package swap after trafficking confirmation | N9: CASE-7206 | O9: Commitment carried into recovery review
A10: ACT-26005A | B10: A-1005 | C10: Devon Brooks | D10: Customer call | E10: 46202 | F10: VP Marketing requested audience correction plan before PO. | G10: Open case review with operational owner | H10: 46206 | I10: Completed | J10: CRM call note | K10: Concerned | L10: 46235 | M10: Prepare recovery evidence | N10: CASE-7207 | O10: Initial escalation intake
A11: ACT-26005B | B11: A-1005 | C11: Devon Brooks | D11: Email | E11: 46211 | F11: VP Marketing requested audience correction plan before PO. | G11: Share audience rebuild proof | H11: 46214 | I11: Missed | J11: No confirmation | K11: Escalated | L11: 46239 | M11: Swap misaligned audience package and reset delivery proof | N11: CASE-7207 | O11: Commitment carried into recovery review
A12: ACT-26006A | B12: A-1006 | C12: Maya Chen | D12: Customer call | E12: 46207 | F12: Owner asked for invoice correction before approving fall campaign. | G12: Open case review with operational owner | H12: 46211 | I12: Completed | J12: CRM call note | K12: Cautious | L12: 46229 | M12: Prepare recovery evidence | N12: CASE-7209 | O12: Initial escalation intake
A13: ACT-26006B | B13: A-1006 | C13: Maya Chen | D13: Email | E13: 46216 | F13: Owner asked for invoice correction before approving fall campaign. | G13: Send credit memo note | H13: 46220 | I13: Open | J13: Gmail thread | K13: Concerned | L13: 46229 | M13: Confirm verified invoice credit and corrected bill date | N13: CASE-7209 | O13: Commitment carried into recovery review
... A42: ACT-26041 | B42: A-1017 | C42: Jordan Patel | D42: Legal handoff | E42: 46217 | F42: Procurement requested data-use term changes not owned by the sales desk. | G42: Legal owner to draft data-use response | H42: 46227 | I42: Open | J42: Internal checkpoint | K42: Escalated | L42: 46239 | M42: Escalate to manager and legal owner; no rep commitment | N42: CASE-7221 | O42: Manager visibility item

Sheet Raw_Offers
A1: Offer Code | B1: Issue Type | C1: Eligible Tiers | D1: Max Value | E1: Approval Level | F1: Expiration Date | G1: Description | H1: Exclusions
A2: MG-15 | B2: Delivery Underpacing | C2: Key Growth, Core, Emerging | D2: 25000 | E2: Supervisor | F2: 46295 | G2: Makegood inventory up to 15% of affected booked impressions after ad-ops validation. | H2: No guaranteed performance or new inventory categories.
A3: CR-10K | B3: Billing Error | C3: Key Growth, Core, Emerging | D3: 10000 | E3: Supervisor | F3: 46295 | G3: Verified invoice credit up to $10,000 with billing case attached. | H3: Amounts above cap require manager approval.
A4: RH-60 | B4: Renewal Rate Objection | C4: Core, Emerging | D4: 0 | E4: Supervisor | F4: 46295 | G4: Hold current renewal CPM for 60 days when no extra credit is promised. | H4: Cannot combine with unapproved credit or terms beyond 60 days.
A5: SW-PKG | B5: Creative Trafficking; Audience Mismatch; Product Feed Blocker | C5: Key Growth, Core, Emerging | D5: 18000 | E5: Supervisor | F5: 46295 | G5: Equivalent-value package swap after operational owner confirms feasibility. | H5: No customer commitment before blocker clears.
A6: RPT-COMP | B6: Reporting Discrepancy | C6: Key Growth, Core, Emerging | D6: 0 | E6: Supervisor | F6: 46295 | G6: Expedited reporting reconciliation package with customer-facing summary. | H6: No performance guarantee or monetary credit.
A7: MGR-REQ | B7: Over-limit or unsupported | C7: All | D7: 0 | E7: Manager required | F7: 46295 | G7: Controlled exception route for over-limit credits, legal terms, unsupported offers, or missing authority. | H7: Reps may not present as approved local commitment.

Sheet Raw_Approval
A1: Account ID | B1: Approval Status | C1: Approved Offer | D1: Approved Action | E1: Exception Reason | F1: Execution Window Start | G1: Execution Window End
A2: A-1001 | B2: Approved execution | C2: MG-15 | D2: Confirm makegood inventory and delivery recovery plan | F2: 46220 | G2: 46227
A3: A-1002 | B3: Approved execution | C3: RPT-COMP | D3: Deliver reconciled reporting package and executive summary | F3: 46220 | G3: 46227
A4: A-1003 | B4: Approved execution | C4: CR-10K | D4: Confirm verified billing credit and renewal rate hold | F4: 46220 | G4: 46227
A5: A-1004 | B5: Approved execution | C5: SW-PKG | D5: Offer equivalent package swap after trafficking confirmation | F5: 46220 | G5: 46227
A6: A-1005 | B6: Approved execution | C6: SW-PKG | D6: Swap misaligned audience package and reset delivery proof | F6: 46220 | G6: 46227
A7: A-1006 | B7: Approved execution | C7: CR-10K | D7: Confirm verified invoice credit and corrected bill date | F7: 46220 | G7: 46227
A8: A-1007 | B8: Approved execution | C8: MG-15 | D8: Confirm makegood placement and revised delivery dates | F8: 46220 | G8: 46227
A9: A-1008 | B9: Approved execution | C9: RPT-COMP | D9: Send reconciled district reach report and renewal summary | F9: 46220 | G9: 46227
A10: A-1009 | B10: Approved execution | C10: SW-PKG | D10: Confirm package swap and creative approval timeline | F10: 46220 | G10: 46227
A11: A-1010 | B11: Approved execution | C11: RH-60 | D11: Offer 60-day rate hold without additional credit | F11: 46220 | G11: 46227
A12: A-1011 | B12: Approved execution | C12: RPT-COMP | D12: Send corrected lift summary and renewal confidence note | F12: 46220 | G12: 46227
A13: A-1012 | B13: Approved execution | C13: MG-15 | D13: Confirm makegood placement and invoice correction route | F13: 46220 | G13: 46227
A14: A-1013 | B14: Controlled exception | C14: MG-15 | D14: Hold customer-facing offer until decision-maker route is approved | E14: Decision-maker outreach permission pending | F14: 46220 | G14: 46227
A15: A-1014 | B15: Controlled exception | C15: MGR-REQ | D15: Route credit request to manager; do not promise local credit | E15: Requested credit is above supervisor authority | F15: 46220 | G15: 46227
A16: A-1015 | B16: Controlled exception | C16: SW-PKG | D16: Wait for product feed fix before customer offer | E16: Ad-ops blocker not cleared | F16: 46220 | G16: 46227
A17: A-1016 | B17: Excluded - no action | D17: No sprint action; keep closure note | E17: Closed renewal | F17: 46220 | G17: 46227
A18: A-1017 | B18: Controlled exception | C18: MGR-REQ | D18: Escalate to manager and legal owner; no rep commitment | E18: Contract terms outside local authority | F18: 46220 | G18: 46227
A19: A-1018 | B19: Excluded - no action | D19: Hold for September agency review | E19: Customer requested September review | F19: 46220 | G19: 46227

Sheet Case_Summary
A1: Account ID | B1: Open Cases | C1: Max Severity | D1: Avg Issue Age | E1: Primary Issue | F1: Source Case ID
A2: A-1001 | B2: 2 | C2: 4 | D2: 19 | E2: Delivery Underpacing | F2: CASE-7201
A3: A-1002 | B3: 1 | C3: 4 | D3: 17 | E3: Reporting Discrepancy | F3: CASE-7203
A4: A-1003 | B4: 2 | C4: 4 | D4: 17 | E4: Billing Error | F4: CASE-7204
A5: A-1004 | B5: 1 | C5: 3 | D5: 14 | E5: Creative Trafficking | F5: CASE-7206
A6: A-1005 | B6: 2 | C6: 5 | D6: 23 | E6: Audience Mismatch | F6: CASE-7207
A7: A-1006 | B7: 1 | C7: 3 | D7: 10 | E7: Billing Error | F7: CASE-7209
A8: A-1007 | B8: 1 | C8: 4 | D8: 23 | E8: Delivery Underpacing | F8: CASE-7210
A9: A-1008 | B9: 1 | C9: 3 | D9: 9 | E9: Reporting Discrepancy | F9: CASE-7211
A10: A-1009 | B10: 1 | C10: 4 | D10: 20 | E10: Creative Trafficking | F10: CASE-7212
A11: A-1010 | B11: 1 | C11: 2 | D11: 5 | E11: Renewal Rate Objection | F11: CASE-7213
A12: A-1011 | B12: 1 | C12: 4 | D12: 18 | E12: Reporting Discrepancy | F12: CASE-7214
A13: A-1012 | B13: 2 | C13: 5 | D13: 20 | E13: Delivery Underpacing | F13: CASE-7215
... A16: A-1015 | B16: 1 | C16: 4 | D16: 21 | E16: Product Feed Blocker | F16: CASE-7219
A17: A-1016 | B17: 0 | C17: 0 | D17: 0 | F17: CASE-7220
A18: A-1017 | B18: 2 | C18: 5 | D18: 29.5 | E18: Data-Use Terms | F18: CASE-7221
A19: A-1018 | B19: 1 | C19: 2 | D19: 6 | E19: Agency Consolidation | F19: CASE-7223

Sheet Activity_Summary
A1: Account ID | B1: Overdue Commitments | C1: Last Touch | D1: Days Since Last Touch
A2: A-1001 | B2: 1 | C2: 46217 | D2: 1
A3: A-1002 | B3: 0 | C3: 46213 | D3: 5
A4: A-1003 | B4: 0 | C4: 46214 | D4: 4
A5: A-1004 | B5: 1 | C5: 46212 | D5: 6
A6: A-1005 | B6: 1 | C6: 46216 | D6: 2
A7: A-1006 | B7: 0 | C7: 46216 | D7: 2
A8: A-1007 | B8: 1 | C8: 46213 | D8: 5
A9: A-1008 | B9: 0 | C9: 46215 | D9: 3
A10: A-1009 | B10: 1 | C10: 46212 | D10: 6
A11: A-1010 | B11: 0 | C11: 46217 | D11: 1
A12: A-1011 | B12: 0 | C12: 46213 | D12: 5
A13: A-1012 | B13: 1 | C13: 46217 | D13: 1
... A19: A-1018 | B19: 0 | C19: 46217 | D19: 1

Sheet Normalized_Accounts
A1: Account ID | B1: Account Name | C1: Segment | D1: Tier | E1: Owner Rep | F1: Renewal Date | G1: Health Score | H1: Approval Status | I1: Renewal Exposure | J1: Baseline Revenue | K1: Current Forecast | L1: Forecast Variance | M1: Open Cases | N1: Max Severity | O1: Avg Issue Age | P1: Overdue Commitments | Q1: Last Touch | R1: Days Since Last Touch | S1: Contact Readiness | T1: Primary Issue | U1: Approved Offer | V1: Requested Recovery Value | W1: Offer Cap | X1: Offer Compliance | Y1: Exception Reason | Z1: Source Lineage
A2: A-1001 | B2: =VLOOKUP(A2,Raw_CRM!$A$2:$L$19,2,FALSE()) -> Meridian Health Partners | C2: =VLOOKUP(A2,Raw_CRM!$A$2:$L$19,3,FALSE()) -> Healthcare | D2: =VLOOKUP(A2,Raw_CRM!$A$2:$L$19,4,FALSE()) -> Key Growth | E2: =VLOOKUP(A2,Raw_CRM!$A$2:$L$19,5,FALSE()) -> Maya Chen | F2: =VLOOKUP(A2,Raw_CRM!$A$2:$L$19,6,FALSE()) -> 46227 | G2: =VLOOKUP(A2,Raw_CRM!$A$2:$L$19,7,FALSE()) -> 48 | H2: =VLOOKUP(A2,Raw_Approval!$A$2:$G$19,2,FALSE()) -> Approved execution | I2: =VLOOKUP(A2,Raw_Orders!$A$2:$H$19,6,FALSE()) -> 340000 | J2: =VLOOKUP(A2,Raw_Orders!$A$2:$H$19,4,FALSE()) -> 310000 | K2: =VLOOKUP(A2,Raw_Orders!$A$2:$H$19,5,FALSE()) -> 272000 | L2: =K2-J2 -> -38000 | M2: =VLOOKUP(A2,Case_Summary!$A$2:$F$19,2,FALSE()) -> 2 | N2: =VLOOKUP(A2,Case_Summary!$A$2:$F$19,3,FALSE()) -> 4 | O2: =VLOOKUP(A2,Case_Summary!$A$2:$F$19,4,FALSE()) -> 19 | P2: =VLOOKUP(A2,Activity_Summary!$A$2:$D$19,2,FALSE()) -> 1 | Q2: =VLOOKUP(A2,Activity_Summary!$A$2:$D$19,3,FALSE()) -> 46217 | R2: =Assumptions!$B$8-Q2 -> 1 | S2: =IF(COUNTIFS(Raw_Contacts!$B$2:$B$41,A2,Raw_Contacts!$F$2:$F$41,"Final Renewal Approver",Raw_Contacts!$H$2:$H$41,"Approved")>0,"Ready",IF(COUNTIFS(Raw_Contacts!$B$2:$B$41,A2,Raw_Contacts!$H$2:$H$41,"Operations Only")>0,"Ops route only",IF(COUNTIFS(Raw_Contacts!$B$2:$B$41,A2,Raw_Contacts!$H$2:$H$41,"Do not contact executive")>0,"Manager route only","Pending permission"))) -> Ready | T2: =IF(VLOOKUP(A2,Case_Summary!$A$2:$F$19,5,FALSE())=0,"",VLOOKUP(A2,Case_Summary!$A$2:$F$19,5,FALSE())) -> Delivery Underpacing | U2: =IF(VLOOKUP(A2,Raw_Approval!$A$2:$G$19,3,FALSE())=0,"",VLOOKUP(A2,Raw_Approval!$A$2:$G$19,3,FALSE())) -> MG-15 | V2: =VLOOKUP(A2,Raw_CRM!$A$2:$L$19,10,FALSE()) -> 21000 | W2: =IF(U2="","",IFERROR(VLOOKUP(U2,Raw_Offers!$A$2:$G$7,4,FALSE()),0)) -> 25000 | X2: =IF(H2<>"Approved execution","Controlled",IF(U2="","No offer",IF(U2="MGR-REQ","Manager required",IF(OR(W2=0,V2<=W2),"Within authority","Over limit")))) -> Within authority | Y2: =IF(VLOOKUP(A2,Raw_Approval!$A$2:$G$19,5,FALSE())=0,"",VLOOKUP(A2,Raw_Approval!$A$2:$G$19,5,FALSE())) | Z2: CRM, cases, orders, contacts, activity, offers, approval
A3: A-1002 | B3: =VLOOKUP(A3,Raw_CRM!$A$2:$L$19,2,FALSE()) -> Larkspur Credit Union | C3: =VLOOKUP(A3,Raw_CRM!$A$2:$L$19,3,FALSE()) -> Financial Services | D3: =VLOOKUP(A3,Raw_CRM!$A$2:$L$19,4,FALSE()) -> Core | E3: =VLOOKUP(A3,Raw_CRM!$A$2:$L$19,5,FALSE()) -> Jordan Patel | F3: =VLOOKUP(A3,Raw_CRM!$A$2:$L$19,6,FALSE()) -> 46234 | G3: =VLOOKUP(A3,Raw_CRM!$A$2:$L$19,7,FALSE()) -> 52 | H3: =VLOOKUP(A3,Raw_Approval!$A$2:$G$19,2,FALSE()) -> Approved execution | I3: =VLOOKUP(A3,Raw_Orders!$A$2:$H$19,6,FALSE()) -> 220000 | J3: =VLOOKUP(A3,Raw_Orders!$A$2:$H$19,4,FALSE()) -> 205000 | K3: =VLOOKUP(A3,Raw_Orders!$A$2:$H$19,5,FALSE()) -> 184000 | L3: =K3-J3 -> -21000 | M3: =VLOOKUP(A3,Case_Summary!$A$2:$F$19,2,FALSE()) -> 1 | N3: =VLOOKUP(A3,Case_Summary!$A$2:$F$19,3,FALSE()) -> 4 | O3: =VLOOKUP(A3,Case_Summary!$A$2:$F$19,4,FALSE()) -> 17 | P3: =VLOOKUP(A3,Activity_Summary!$A$2:$D$19,2,FALSE()) -> 0 | Q3: =VLOOKUP(A3,Activity_Summary!$A$2:$D$19,3,FALSE()) -> 46213 | R3: =Assumptions!$B$8-Q3 -> 5 | S3: =IF(COUNTIFS(Raw_Contacts!$B$2:$B$41,A3,Raw_Contacts!$F$2:$F$41,"Final Renewal Approver",Raw_Contacts!$H$2:$H$41,"Approved")>0,"Ready",IF(COUNTIFS(Raw_Contacts!$B$2:$B$41,A3,Raw_Contacts!$H$2:$H$41,"Operations Only")>0,"Ops route only",IF(COUNTIFS(Raw_Contacts!$B$2:$B$41,A3,Raw_Contacts!$H$2:$H$41,"Do not contact executive")>0,"Manager route only","Pending permission"))) -> Ready | T3: =IF(VLOOKUP(A3,Case_Summary!$A$2:$F$19,5,FALSE())=0,"",VLOOKUP(A3,Case_Summary!$A$2:$F$19,5,FALSE())) -> Reporting Discrepancy | U3: =IF(VLOOKUP(A3,Raw_Approval!$A$2:$G$19,3,FALSE())=0,"",VLOOKUP(A3,Raw_Approval!$A$2:$G$19,3,FALSE())) -> RPT-COMP | V3: =VLOOKUP(A3,Raw_CRM!$A$2:$L$19,10,FALSE()) -> 0 | W3: =IF(U3="","",IFERROR(VLOOKUP(U3,Raw_Offers!$A$2:$G$7,4,FALSE()),0)) -> 0 | X3: =IF(H3<>"Approved execution","Controlled",IF(U3="","No offer",IF(U3="MGR-REQ","Manager required",IF(OR(W3=0,V3<=W3),"Within authority","Over limit")))) -> Within authority | Y3: =IF(VLOOKUP(A3,Raw_Approval!$A$2:$G$19,5,FALSE())=0,"",VLOOKUP(A3,Raw_Approval!$A$2:$G$19,5,FALSE())) | Z3: CRM, cases, orders, contacts, activity, offers, approval
A4: A-1003 | B4: =VLOOKUP(A4,Raw_CRM!$A$2:$L$19,2,FALSE()) -> Cobalt Cloud Systems | C4: =VLOOKUP(A4,Raw_CRM!$A$2:$L$19,3,FALSE()) -> Technology | D4: =VLOOKUP(A4,Raw_CRM!$A$2:$L$19,4,FALSE()) -> Key Growth | E4: =VLOOKUP(A4,Raw_CRM!$A$2:$L$19,5,FALSE()) -> Priya Nair | F4: =VLOOKUP(A4,Raw_CRM!$A$2:$L$19,6,FALSE()) -> 46239 | G4: =VLOOKUP(A4,Raw_CRM!$A$2:$L$19,7,FALSE()) -> 56 | H4: =VLOOKUP(A4,Raw_Approval!$A$2:$G$19,2,FALSE()) -> Approved execution | I4: =VLOOKUP(A4,Raw_Orders!$A$2:$H$19,6,FALSE()) -> 295000 | J4: =VLOOKUP(A4,Raw_Orders!$A$2:$H$19,4,FALSE()) -> 275000 | K4: =VLOOKUP(A4,Raw_Orders!$A$2:$H$19,5,FALSE()) -> 240000 | L4: =K4-J4 -> -35000 | M4: =VLOOKUP(A4,Case_Summary!$A$2:$F$19,2,FALSE()) -> 2 | N4: =VLOOKUP(A4,Case_Summary!$A$2:$F$19,3,FALSE()) -> 4 | O4: =VLOOKUP(A4,Case_Summary!$A$2:$F$19,4,FALSE()) -> 17 | P4: =VLOOKUP(A4,Activity_Summary!$A$2:$D$19,2,FALSE()) -> 0 | Q4: =VLOOKUP(A4,Activity_Summary!$A$2:$D$19,3,FALSE()) -> 46214 | R4: =Assumptions!$B$8-Q4 -> 4 | S4: =IF(COUNTIFS(Raw_Contacts!$B$2:$B$41,A4,Raw_Contacts!$F$2:$F$41,"Final Renewal Approver",Raw_Contacts!$H$2:$H$41,"Approved")>0,"Ready",IF(COUNTIFS(Raw_Contacts!$B$2:$B$41,A4,Raw_Contacts!$H$2:$H$41,"Operations Only")>0,"Ops route only",IF(COUNTIFS(Raw_Contacts!$B$2:$B$41,A4,Raw_Contacts!$H$2:$H$41,"Do not contact executive")>0,"Manager route only","Pending permission"))) -> Ready | T4: =IF(VLOOKUP(A4,Case_Summary!$A$2:$F$19,5,FALSE())=0,"",VLOOKUP(A4,Case_Summary!$A$2:$F$19,5,FALSE())) -> Billing Error | U4: =IF(VLOOKUP(A4,Raw_Approval!$A$2:$G$19,3,FALSE())=0,"",VLOOKUP(A4,Raw_Approval!$A$2:$G$19,3,FALSE())) -> CR-10K | V4: =VLOOKUP(A4,Raw_CRM!$A$2:$L$19,10,FALSE()) -> 9500 | W4: =IF(U4="","",IFERROR(VLOOKUP(U4,Raw_Offers!$A$2:$G$7,4,FALSE()),0)) -> 10000 | X4: =IF(H4<>"Approved execution","Controlled",IF(U4="","No offer",IF(U4="MGR-REQ","Manager required",IF(OR(W4=0,V4<=W4),"Within authority","Over limit")))) -> Within authority | Y4: =IF(VLOOKUP(A4,Raw_Approval!$A$2:$G$19,5,FALSE())=0,"",VLOOKUP(A4,Raw_Approval!$A$2:$G$19,5,FALSE())) | Z4: CRM, cases, orders, contacts, activity, offers, approval
A5: A-1004 | B5: =VLOOKUP(A5,Raw_CRM!$A$2:$L$19,2,FALSE()) -> Harborview Furnishings | C5: =VLOOKUP(A5,Raw_CRM!$A$2:$L$19,3,FALSE()) -> Retail | D5: =VLOOKUP(A5,Raw_CRM!$A$2:$L$19,4,FALSE()) -> Core | E5: =VLOOKUP(A5,Raw_CRM!$A$2:$L$19,5,FALSE()) -> Luis Romero | F5: =VLOOKUP(A5,Raw_CRM!$A$2:$L$19,6,FALSE()) -> 46231 | G5: =VLOOKUP(A5,Raw_CRM!$A$2:$L$19,7,FALSE()) -> 61 | H5: =VLOOKUP(A5,Raw_Approval!$A$2:$G$19,2,FALSE()) -> Approved execution | I5: =VLOOKUP(A5,Raw_Orders!$A$2:$H$19,6,FALSE()) -> 150000 | J5: =VLOOKUP(A5,Raw_Orders!$A$2:$H$19,4,FALSE()) -> 142000 | K5: =VLOOKUP(A5,Raw_Orders!$A$2:$H$19,5,FALSE()) -> 129000 | L5: =K5-J5 -> -13000 | M5: =VLOOKUP(A5,Case_Summary!$A$2:$F$19,2,FALSE()) -> 1 | N5: =VLOOKUP(A5,Case_Summary!$A$2:$F$19,3,FALSE()) -> 3 | O5: =VLOOKUP(A5,Case_Summary!$A$2:$F$19,4,FALSE()) -> 14 | P5: =VLOOKUP(A5,Activity_Summary!$A$2:$D$19,2,FALSE()) -> 1 | Q5: =VLOOKUP(A5,Activity_Summary!$A$2:$D$19,3,FALSE()) -> 46212 | R5: =Assumptions!$B$8-Q5 -> 6 | S5: =IF(COUNTIFS(Raw_Contacts!$B$2:$B$41,A5,Raw_Contacts!$F$2:$F$41,"Final Renewal Approver",Raw_Contacts!$H$2:$H$41,"Approved")>0,"Ready",IF(COUNTIFS(Raw_Contacts!$B$2:$B$41,A5,Raw_Contacts!$H$2:$H$41,"Operations Only")>0,"Ops route only",IF(COUNTIFS(Raw_Contacts!$B$2:$B$41,A5,Raw_Contacts!$H$2:$H$41,"Do not contact executive")>0,"Manager route only","Pending permission"))) -> Ready | T5: =IF(VLOOKUP(A5,Case_Summary!$A$2:$F$19,5,FALSE())=0,"",VLOOKUP(A5,Case_Summary!$A$2:$F$19,5,FALSE())) -> Creative Trafficking | U5: =IF(VLOOKUP(A5,Raw_Approval!$A$2:$G$19,3,FALSE())=0,"",VLOOKUP(A5,Raw_Approval!$A$2:$G$19,3,FALSE())) -> SW-PKG | V5: =VLOOKUP(A5,Raw_CRM!$A$2:$L$19,10,FALSE()) -> 12000 | W5: =IF(U5="","",IFERROR(VLOOKUP(U5,Raw_Offers!$A$2:$G$7,4,FALSE()),0)) -> 18000 | X5: =IF(H5<>"Approved execution","Controlled",IF(U5="","No offer",IF(U5="MGR-REQ","Manager required",IF(OR(W5=0,V5<=W5),"Within authority","Over limit")))) -> Within authority | Y5: =IF(VLOOKUP(A5,Raw_Approval!$A$2:$G$19,5,FALSE())=0,"",VLOOKUP(A5,Raw_Approval!$A$2:$G$19,5,FALSE())) | Z5: CRM, cases, orders, contacts, activity, offers, approval
A6: A-1005 | B6: =VLOOKUP(A6,Raw_CRM!$A$2:$L$19,2,FALSE()) -> Axion Robotics | C6: =VLOOKUP(A6,Raw_CRM!$A$2:$L$19,3,FALSE()) -> Industrial | D6: =VLOOKUP(A6,Raw_CRM!$A$2:$L$19,4,FALSE()) -> Key Growth | E6: =VLOOKUP(A6,Raw_CRM!$A$2:$L$19,5,FALSE()) -> Devon Brooks | F6: =VLOOKUP(A6,Raw_CRM!$A$2:$L$19,6,FALSE()) -> 46246 | G6: =VLOOKUP(A6,Raw_CRM!$A$2:$L$19,7,FALSE()) -> 44 | H6: =VLOOKUP(A6,Raw_Approval!$A$2:$G$19,2,FALSE()) -> Approved execution | I6: =VLOOKUP(A6,Raw_Orders!$A$2:$H$19,6,FALSE()) -> 410000 | J6: =VLOOKUP(A6,Raw_Orders!$A$2:$H$19,4,FALSE()) -> 390000 | K6: =VLOOKUP(A6,Raw_Orders!$A$2:$H$19,5,FALSE()) -> 318000 | L6: =K6-J6 -> -72000 | M6: =VLOOKUP(A6,Case_Summary!$A$2:$F$19,2,FALSE()) -> 2 | N6: =VLOOKUP(A6,Case_Summary!$A$2:$F$19,3,FALSE()) -> 5 | O6: =VLOOKUP(A6,Case_Summary!$A$2:$F$19,4,FALSE()) -> 23 | P6: =VLOOKUP(A6,Activity_Summary!$A$2:$D$19,2,FALSE()) -> 1 | Q6: =VLOOKUP(A6,Activity_Summary!$A$2:$D$19,3,FALSE()) -> 46216 | R6: =Assumptions!$B$8-Q6 -> 2 | S6: =IF(COUNTIFS(Raw_Contacts!$B$2:$B$41,A6,Raw_Contacts!$F$2:$F$41,"Final Renewal Approver",Raw_Contacts!$H$2:$H$41,"Approved")>0,"Ready",IF(COUNTIFS(Raw_Contacts!$B$2:$B$41,A6,Raw_Contacts!$H$2:$H$41,"Operations Only")>0,"Ops route only",IF(COUNTIFS(Raw_Contacts!$B$2:$B$41,A6,Raw_Contacts!$H$2:$H$41,"Do not contact executive")>0,"Manager route only","Pending permission"))) -> Ready | T6: =IF(VLOOKUP(A6,Case_Summary!$A$2:$F$19,5,FALSE())=0,"",VLOOKUP(A6,Case_Summary!$A$2:$F$19,5,FALSE())) -> Audience Mismatch | U6: =IF(VLOOKUP(A6,Raw_Approval!$A$2:$G$19,3,FALSE())=0,"",VLOOKUP(A6,Raw_Approval!$A$2:$G$19,3,FALSE())) -> SW-PKG | V6: =VLOOKUP(A6,Raw_CRM!$A$2:$L$19,10,FALSE()) -> 18000 | W6: =IF(U6="","",IFERROR(VLOOKUP(U6,Raw_Offers!$A$2:$G$7,4,FALSE()),0)) -> 18000 | X6: =IF(H6<>"Approved execution","Controlled",IF(U6="","No offer",IF(U6="MGR-REQ","Manager required",IF(OR(W6=0,V6<=W6),"Within authority","Over limit")))) -> Within authority | Y6: =IF(VLOOKUP(A6,Raw_Approval!$A$2:$G$19,5,FALSE())=0,"",VLOOKUP(A6,Raw_Approval!$A$2:$G$19,5,FALSE())) | Z6: CRM, cases, orders, contacts, activity, offers, approval
A7: A-1006 | B7: =VLOOKUP(A7,Raw_CRM!$A$2:$L$19,2,FALSE()) -> Greenway Kitchens | C7: =VLOOKUP(A7,Raw_CRM!$A$2:$L$19,3,FALSE()) -> Retail | D7: =VLOOKUP(A7,Raw_CRM!$A$2:$L$19,4,FALSE()) -> Emerging | E7: =VLOOKUP(A7,Raw_CRM!$A$2:$L$19,5,FALSE()) -> Maya Chen | F7: =VLOOKUP(A7,Raw_CRM!$A$2:$L$19,6,FALSE()) -> 46229 | G7: =VLOOKUP(A7,Raw_CRM!$A$2:$L$19,7,FALSE()) -> 68 | H7: =VLOOKUP(A7,Raw_Approval!$A$2:$G$19,2,FALSE()) -> Approved execution | I7: =VLOOKUP(A7,Raw_Orders!$A$2:$H$19,6,FALSE()) -> 82000 | J7: =VLOOKUP(A7,Raw_Orders!$A$2:$H$19,4,FALSE()) -> 76000 | K7: =VLOOKUP(A7,Raw_Orders!$A$2:$H$19,5,FALSE()) -> 71000 | L7: =K7-J7 -> -5000 | M7: =VLOOKUP(A7,Case_Summary!$A$2:$F$19,2,FALSE()) -> 1 | N7: =VLOOKUP(A7,Case_Summary!$A$2:$F$19,3,FALSE()) -> 3 | O7: =VLOOKUP(A7,Case_Summary!$A$2:$F$19,4,FALSE()) -> 10 | P7: =VLOOKUP(A7,Activity_Summary!$A$2:$D$19,2,FALSE()) -> 0 | Q7: =VLOOKUP(A7,Activity_Summary!$A$2:$D$19,3,FALSE()) -> 46216 | R7: =Assumptions!$B$8-Q7 -> 2 | S7: =IF(COUNTIFS(Raw_Contacts!$B$2:$B$41,A7,Raw_Contacts!$F$2:$F$41,"Final Renewal Approver",Raw_Contacts!$H$2:$H$41,"Approved")>0,"Ready",IF(COUNTIFS(Raw_Contacts!$B$2:$B$41,A7,Raw_Contacts!$H$2:$H$41,"Operations Only")>0,"Ops route only",IF(COUNTIFS(Raw_Contacts!$B$2:$B$41,A7,Raw_Contacts!$H$2:$H$41,"Do not contact executive")>0,"Manager route only","Pending permission"))) -> Ready | T7: =IF(VLOOKUP(A7,Case_Summary!$A$2:$F$19,5,FALSE())=0,"",VLOOKUP(A7,Case_Summary!$A$2:$F$19,5,FALSE())) -> Billing Error | U7: =IF(VLOOKUP(A7,Raw_Approval!$A$2:$G$19,3,FALSE())=0,"",VLOOKUP(A7,Raw_Approval!$A$2:$G$19,3,FALSE())) -> CR-10K | V7: =VLOOKUP(A7,Raw_CRM!$A$2:$L$19,10,FALSE()) -> 4800 | W7: =IF(U7="","",IFERROR(VLOOKUP(U7,Raw_Offers!$A$2:$G$7,4,FALSE()),0)) -> 10000 | X7: =IF(H7<>"Approved execution","Controlled",IF(U7="","No offer",IF(U7="MGR-REQ","Manager required",IF(OR(W7=0,V7<=W7),"Within authority","Over limit")))) -> Within authority | Y7: =IF(VLOOKUP(A7,Raw_Approval!$A$2:$G$19,5,FALSE())=0,"",VLOOKUP(A7,Raw_Approval!$A$2:$G$19,5,FALSE())) | Z7: CRM, cases, orders, contacts, activity, offers, approval
A8: A-1007 | B8: =VLOOKUP(A8,Raw_CRM!$A$2:$L$19,2,FALSE()) -> Northline Insurance | C8: =VLOOKUP(A8,Raw_CRM!$A$2:$L$19,3,FALSE()) -> Financial Services | D8: =VLOOKUP(A8,Raw_CRM!$A$2:$L$19,4,FALSE()) -> Core | E8: =VLOOKUP(A8,Raw_CRM!$A$2:$L$19,5,FALSE()) -> Jordan Patel | F8: =VLOOKUP(A8,Raw_CRM!$A$2:$L$19,6,FALSE()) -> 46237 | G8: =VLOOKUP(A8,Raw_CRM!$A$2:$L$19,7,FALSE()) -> 50 | H8: =VLOOKUP(A8,Raw_Approval!$A$2:$G$19,2,FALSE()) -> Approved execution | I8: =VLOOKUP(A8,Raw_Orders!$A$2:$H$19,6,FALSE()) -> 260000 | J8: =VLOOKUP(A8,Raw_Orders!$A$2:$H$19,4,FALSE()) -> 246000 | K8: =VLOOKUP(A8,Raw_Orders!$A$2:$H$19,5,FALSE()) -> 206000 | L8: =K8-J8 -> -40000 | M8: =VLOOKUP(A8,Case_Summary!$A$2:$F$19,2,FALSE()) -> 1 | N8: =VLOOKUP(A8,Case_Summary!$A$2:$F$19,3,FALSE()) -> 4 | O8: =VLOOKUP(A8,Case_Summary!$A$2:$F$19,4,FALSE()) -> 23 | P8: =VLOOKUP(A8,Activity_Summary!$A$2:$D$19,2,FALSE()) -> 1 | Q8: =VLOOKUP(A8,Activity_Summary!$A$2:$D$19,3,FALSE()) -> 46213 | R8: =Assumptions!$B$8-Q8 -> 5 | S8: =IF(COUNTIFS(Raw_Contacts!$B$2:$B$41,A8,Raw_Contacts!$F$2:$F$41,"Final Renewal Approver",Raw_Contacts!$H$2:$H$41,"Approved")>0,"Ready",IF(COUNTIFS(Raw_Contacts!$B$2:$B$41,A8,Raw_Contacts!$H$2:$H$41,"Operations Only")>0,"Ops route only",IF(COUNTIFS(Raw_Contacts!$B$2:$B$41,A8,Raw_Contacts!$H$2:$H$41,"Do not contact executive")>0,"Manager route only","Pending permission"))) -> Ready | T8: =IF(VLOOKUP(A8,Case_Summary!$A$2:$F$19,5,FALSE())=0,"",VLOOKUP(A8,Case_Summary!$A$2:$F$19,5,FALSE())) -> Delivery Underpacing | U8: =IF(VLOOKUP(A8,Raw_Approval!$A$2:$G$19,3,FALSE())=0,"",VLOOKUP(A8,Raw_Approval!$A$2:$G$19,3,FALSE())) -> MG-15 | V8: =VLOOKUP(A8,Raw_CRM!$A$2:$L$19,10,FALSE()) -> 22000 | W8: =IF(U8="","",IFERROR(VLOOKUP(U8,Raw_Offers!$A$2:$G$7,4,FALSE()),0)) -> 25000 | X8: =IF(H8<>"Approved execution","Controlled",IF(U8="","No offer",IF(U8="MGR-REQ","Manager required",IF(OR(W8=0,V8<=W8),"Within authority","Over limit")))) -> Within authority | Y8: =IF(VLOOKUP(A8,Raw_Approval!$A$2:$G$19,5,FALSE())=0,"",VLOOKUP(A8,Raw_Approval!$A$2:$G$19,5,FALSE())) | Z8: CRM, cases, orders, contacts, activity, offers, approval
A9: A-1008 | B9: =VLOOKUP(A9,Raw_CRM!$A$2:$L$19,2,FALSE()) -> Veridian Charter Schools | C9: =VLOOKUP(A9,Raw_CRM!$A$2:$L$19,3,FALSE()) -> Education | D9: =VLOOKUP(A9,Raw_CRM!$A$2:$L$19,4,FALSE()) -> Emerging | E9: =VLOOKUP(A9,Raw_CRM!$A$2:$L$19,5,FALSE()) -> Priya Nair | F9: =VLOOKUP(A9,Raw_CRM!$A$2:$L$19,6,FALSE()) -> 46249 | G9: =VLOOKUP(A9,Raw_CRM!$A$2:$L$19,7,FALSE()) -> 63 | H9: =VLOOKUP(A9,Raw_Approval!$A$2:$G$19,2,FALSE()) -> Approved execution | I9: =VLOOKUP(A9,Raw_Orders!$A$2:$H$19,6,FALSE()) -> 110000 | J9: =VLOOKUP(A9,Raw_Orders!$A$2:$H$19,4,FALSE()) -> 98000 | K9: =VLOOKUP(A9,Raw_Orders!$A$2:$H$19,5,FALSE()) -> 88000 | L9: =K9-J9 -> -10000 | M9: =VLOOKUP(A9,Case_Summary!$A$2:$F$19,2,FALSE()) -> 1 | N9: =VLOOKUP(A9,Case_Summary!$A$2:$F$19,3,FALSE()) -> 3 | O9: =VLOOKUP(A9,Case_Summary!$A$2:$F$19,4,FALSE()) -> 9 | P9: =VLOOKUP(A9,Activity_Summary!$A$2:$D$19,2,FALSE()) -> 0 | Q9: =VLOOKUP(A9,Activity_Summary!$A$2:$D$19,3,FALSE()) -> 46215 | R9: =Assumptions!$B$8-Q9 -> 3 | S9: =IF(COUNTIFS(Raw_Contacts!$B$2:$B$41,A9,Raw_Contacts!$F$2:$F$41,"Final Renewal Approver",Raw_Contacts!$H$2:$H$41,"Approved")>0,"Ready",IF(COUNTIFS(Raw_Contacts!$B$2:$B$41,A9,Raw_Contacts!$H$2:$H$41,"Operations Only")>0,"Ops route only",IF(COUNTIFS(Raw_Contacts!$B$2:$B$41,A9,Raw_Contacts!$H$2:$H$41,"Do not contact executive")>0,"Manager route only","Pending permission"))) -> Ready | T9: =IF(VLOOKUP(A9,Case_Summary!$A$2:$F$19,5,FALSE())=0,"",VLOOKUP(A9,Case_Summary!$A$2:$F$19,5,FALSE())) -> Reporting Discrepancy | U9: =IF(VLOOKUP(A9,Raw_Approval!$A$2:$G$19,3,FALSE())=0,"",VLOOKUP(A9,Raw_Approval!$A$2:$G$19,3,FALSE())) -> RPT-COMP | V9: =VLOOKUP(A9,Raw_CRM!$A$2:$L$19,10,FALSE()) -> 0 | W9: =IF(U9="","",IFERROR(VLOOKUP(U9,Raw_Offers!$A$2:$G$7,4,FALSE()),0)) -> 0 | X9: =IF(H9<>"Approved execution","Controlled",IF(U9="","No offer",IF(U9="MGR-REQ","Manager required",IF(OR(W9=0,V9<=W9),"Within authority","Over limit")))) -> Within authority | Y9: =IF(VLOOKUP(A9,Raw_Approval!$A$2:$G$19,5,FALSE())=0,"",VLOOKUP(A9,Raw_Approval!$A$2:$G$19,5,FALSE())) | Z9: CRM, cases, orders, contacts, activity, offers, approval
A10: A-1009 | B10: =VLOOKUP(A10,Raw_CRM!$A$2:$L$19,2,FALSE()) -> Copper Trail Hospitality | C10: =VLOOKUP(A10,Raw_CRM!$A$2:$L$19,3,FALSE()) -> Travel | D10: =VLOOKUP(A10,Raw_CRM!$A$2:$L$19,4,FALSE()) -> Core | E10: =VLOOKUP(A10,Raw_CRM!$A$2:$L$19,5,FALSE()) -> Luis Romero | F10: =VLOOKUP(A10,Raw_CRM!$A$2:$L$19,6,FALSE()) -> 46232 | G10: =VLOOKUP(A10,Raw_CRM!$A$2:$L$19,7,FALSE()) -> 58 | H10: =VLOOKUP(A10,Raw_Approval!$A$2:$G$19,2,FALSE()) -> Approved execution | I10: =VLOOKUP(A10,Raw_Orders!$A$2:$H$19,6,FALSE()) -> 190000 | J10: =VLOOKUP(A10,Raw_Orders!$A$2:$H$19,4,FALSE()) -> 174000 | K10: =VLOOKUP(A10,Raw_Orders!$A$2:$H$19,5,FALSE()) -> 149000 | L10: =K10-J10 -> -25000 | M10: =VLOOKUP(A10,Case_Summary!$A$2:$F$19,2,FALSE()) -> 1 | N10: =VLOOKUP(A10,Case_Summary!$A$2:$F$19,3,FALSE()) -> 4 | O10: =VLOOKUP(A10,Case_Summary!$A$2:$F$19,4,FALSE()) -> 20 | P10: =VLOOKUP(A10,Activity_Summary!$A$2:$D$19,2,FALSE()) -> 1 | Q10: =VLOOKUP(A10,Activity_Summary!$A$2:$D$19,3,FALSE()) -> 46212 | R10: =Assumptions!$B$8-Q10 -> 6 | S10: =IF(COUNTIFS(Raw_Contacts!$B$2:$B$41,A10,Raw_Contacts!$F$2:$F$41,"Final Renewal Approver",Raw_Contacts!$H$2:$H$41,"Approved")>0,"Ready",IF(COUNTIFS(Raw_Contacts!$B$2:$B$41,A10,Raw_Contacts!$H$2:$H$41,"Operations Only")>0,"Ops route only",IF(COUNTIFS(Raw_Contacts!$B$2:$B$41,A10,Raw_Contacts!$H$2:$H$41,"Do not contact executive")>0,"Manager route only","Pending permission"))) -> Ready | T10: =IF(VLOOKUP(A10,Case_Summary!$A$2:$F$19,5,FALSE())=0,"",VLOOKUP(A10,Case_Summary!$A$2:$F$19,5,FALSE())) -> Creative Trafficking | U10: =IF(VLOOKUP(A10,Raw_Approval!$A$2:$G$19,3,FALSE())=0,"",VLOOKUP(A10,Raw_Approval!$A$2:$G$19,3,FALSE())) -> SW-PKG | V10: =VLOOKUP(A10,Raw_CRM!$A$2:$L$19,10,FALSE()) -> 15000 | W10: =IF(U10="","",IFERROR(VLOOKUP(U10,Raw_Offers!$A$2:$G$7,4,FALSE()),0)) -> 18000 | X10: =IF(H10<>"Approved execution","Controlled",IF(U10="","No offer",IF(U10="MGR-REQ","Manager required",IF(OR(W10=0,V10<=W10),"Within authority","Over limit")))) -> Within authority | Y10: =IF(VLOOKUP(A10,Raw_Approval!$A$2:$G$19,5,FALSE())=0,"",VLOOKUP(A10,Raw_Approval!$A$2:$G$19,5,FALSE())) | Z10: CRM, cases, orders, contacts, activity, offers, approval
A11: A-1010 | B11: =VLOOKUP(A11,Raw_CRM!$A$2:$L$19,2,FALSE()) -> Finch Legal Group | C11: =VLOOKUP(A11,Raw_CRM!$A$2:$L$19,3,FALSE()) -> Professional Services | D11: =VLOOKUP(A11,Raw_CRM!$A$2:$L$19,4,FALSE()) -> Emerging | E11: =VLOOKUP(A11,Raw_CRM!$A$2:$L$19,5,FALSE()) -> Devon Brooks | F11: =VLOOKUP(A11,Raw_CRM!$A$2:$L$19,6,FALSE()) -> 46254 | G11: =VLOOKUP(A11,Raw_CRM!$A$2:$L$19,7,FALSE()) -> 70 | H11: =VLOOKUP(A11,Raw_Approval!$A$2:$G$19,2,FALSE()) -> Approved execution | I11: =VLOOKUP(A11,Raw_Orders!$A$2:$H$19,6,FALSE()) -> 75000 | J11: =VLOOKUP(A11,Raw_Orders!$A$2:$H$19,4,FALSE()) -> 72000 | K11: =VLOOKUP(A11,Raw_Orders!$A$2:$H$19,5,FALSE()) -> 70000 | L11: =K11-J11 -> -2000 | M11: =VLOOKUP(A11,Case_Summary!$A$2:$F$19,2,FALSE()) -> 1 | N11: =VLOOKUP(A11,Case_Summary!$A$2:$F$19,3,FALSE()) -> 2 | O11: =VLOOKUP(A11,Case_Summary!$A$2:$F$19,4,FALSE()) -> 5 | P11: =VLOOKUP(A11,Activity_Summary!$A$2:$D$19,2,FALSE()) -> 0 | Q11: =VLOOKUP(A11,Activity_Summary!$A$2:$D$19,3,FALSE()) -> 46217 | R11: =Assumptions!$B$8-Q11 -> 1 | S11: =IF(COUNTIFS(Raw_Contacts!$B$2:$B$41,A11,Raw_Contacts!$F$2:$F$41,"Final Renewal Approver",Raw_Contacts!$H$2:$H$41,"Approved")>0,"Ready",IF(COUNTIFS(Raw_Contacts!$B$2:$B$41,A11,Raw_Contacts!$H$2:$H$41,"Operations Only")>0,"Ops route only",IF(COUNTIFS(Raw_Contacts!$B$2:$B$41,A11,Raw_Contacts!$H$2:$H$41,"Do not contact executive")>0,"Manager route only","Pending permission"))) -> Ready | T11: =IF(VLOOKUP(A11,Case_Summary!$A$2:$F$19,5,FALSE())=0,"",VLOOKUP(A11,Case_Summary!$A$2:$F$19,5,FALSE())) -> Renewal Rate Objection | U11: =IF(VLOOKUP(A11,Raw_Approval!$A$2:$G$19,3,FALSE())=0,"",VLOOKUP(A11,Raw_Approval!$A$2:$G$19,3,FALSE())) -> RH-60 | V11: =VLOOKUP(A11,Raw_CRM!$A$2:$L$19,10,FALSE()) -> 0 | W11: =IF(U11="","",IFERROR(VLOOKUP(U11,Raw_Offers!$A$2:$G$7,4,FALSE()),0)) -> 0 | X11: =IF(H11<>"Approved execution","Controlled",IF(U11="","No offer",IF(U11="MGR-REQ","Manager required",IF(OR(W11=0,V11<=W11),"Within authority","Over limit")))) -> Within authority | Y11: =IF(VLOOKUP(A11,Raw_Approval!$A$2:$G$19,5,FALSE())=0,"",VLOOKUP(A11,Raw_Approval!$A$2:$G$19,5,FALSE())) | Z11: CRM, cases, orders, contacts, activity, offers, approval
A12: A-1011 | B12: =VLOOKUP(A12,Raw_CRM!$A$2:$L$19,2,FALSE()) -> Solstice Energy Co-op | C12: =VLOOKUP(A12,Raw_CRM!$A$2:$L$19,3,FALSE()) -> Energy | D12: =VLOOKUP(A12,Raw_CRM!$A$2:$L$19,4,FALSE()) -> Core | E12: =VLOOKUP(A12,Raw_CRM!$A$2:$L$19,5,FALSE()) -> Maya Chen | F12: =VLOOKUP(A12,Raw_CRM!$A$2:$L$19,6,FALSE()) -> 46243 | G12: =VLOOKUP(A12,Raw_CRM!$A$2:$L$19,7,FALSE()) -> 55 | H12: =VLOOKUP(A12,Raw_Approval!$A$2:$G$19,2,FALSE()) -> Approved execution | I12: =VLOOKUP(A12,Raw_Orders!$A$2:$H$19,6,FALSE()) -> 175000 | J12: =VLOOKUP(A12,Raw_Orders!$A$2:$H$19,4,FALSE()) -> 160000 | K12: =VLOOKUP(A12,Raw_Orders!$A$2:$H$19,5,FALSE()) -> 140000 | L12: =K12-J12 -> -20000 | M12: =VLOOKUP(A12,Case_Summary!$A$2:$F$19,2,FALSE()) -> 1 | N12: =VLOOKUP(A12,Case_Summary!$A$2:$F$19,3,FALSE()) -> 4 | O12: =VLOOKUP(A12,Case_Summary!$A$2:$F$19,4,FALSE()) -> 18 | P12: =VLOOKUP(A12,Activity_Summary!$A$2:$D$19,2,FALSE()) -> 0 | Q12: =VLOOKUP(A12,Activity_Summary!$A$2:$D$19,3,FALSE()) -> 46213 | R12: =Assumptions!$B$8-Q12 -> 5 | S12: =IF(COUNTIFS(Raw_Contacts!$B$2:$B$41,A12,Raw_Contacts!$F$2:$F$41,"Final Renewal Approver",Raw_Contacts!$H$2:$H$41,"Approved")>0,"Ready",IF(COUNTIFS(Raw_Contacts!$B$2:$B$41,A12,Raw_Contacts!$H$2:$H$41,"Operations Only")>0,"Ops route only",IF(COUNTIFS(Raw_Contacts!$B$2:$B$41,A12,Raw_Contacts!$H$2:$H$41,"Do not contact executive")>0,"Manager route only","Pending permission"))) -> Ready | T12: =IF(VLOOKUP(A12,Case_Summary!$A$2:$F$19,5,FALSE())=0,"",VLOOKUP(A12,Case_Summary!$A$2:$F$19,5,FALSE())) -> Reporting Discrepancy | U12: =IF(VLOOKUP(A12,Raw_Approval!$A$2:$G$19,3,FALSE())=0,"",VLOOKUP(A12,Raw_Approval!$A$2:$G$19,3,FALSE())) -> RPT-COMP | V12: =VLOOKUP(A12,Raw_CRM!$A$2:$L$19,10,FALSE()) -> 0 | W12: =IF(U12="","",IFERROR(VLOOKUP(U12,Raw_Offers!$A$2:$G$7,4,FALSE()),0)) -> 0 | X12: =IF(H12<>"Approved execution","Controlled",IF(U12="","No offer",IF(U12="MGR-REQ","Manager required",IF(OR(W12=0,V12<=W12),"Within authority","Over limit")))) -> Within authority | Y12: =IF(VLOOKUP(A12,Raw_Approval!$A$2:$G$19,5,FALSE())=0,"",VLOOKUP(A12,Raw_Approval!$A$2:$G$19,5,FALSE())) | Z12: CRM, cases, orders, contacts, activity, offers, approval
A13: A-1012 | B13: =VLOOKUP(A13,Raw_CRM!$A$2:$L$19,2,FALSE()) -> Vesta Apparel Collective | C13: =VLOOKUP(A13,Raw_CRM!$A$2:$L$19,3,FALSE()) -> Retail | D13: =VLOOKUP(A13,Raw_CRM!$A$2:$L$19,4,FALSE()) -> Key Growth | E13: =VLOOKUP(A13,Raw_CRM!$A$2:$L$19,5,FALSE()) -> Jordan Patel | F13: =VLOOKUP(A13,Raw_CRM!$A$2:$L$19,6,FALSE()) -> 46235 | G13: =VLOOKUP(A13,Raw_CRM!$A$2:$L$19,7,FALSE()) -> 47 | H13: =VLOOKUP(A13,Raw_Approval!$A$2:$G$19,2,FALSE()) -> Approved execution | I13: =VLOOKUP(A13,Raw_Orders!$A$2:$H$19,6,FALSE()) -> 305000 | J13: =VLOOKUP(A13,Raw_Orders!$A$2:$H$19,4,FALSE()) -> 290000 | K13: =VLOOKUP(A13,Raw_Orders!$A$2:$H$19,5,FALSE()) -> 238000 | L13: =K13-J13 -> -52000 | M13: =VLOOKUP(A13,Case_Summary!$A$2:$F$19,2,FALSE()) -> 2 | N13: =VLOOKUP(A13,Case_Summary!$A$2:$F$19,3,FALSE()) -> 5 | O13: =VLOOKUP(A13,Case_Summary!$A$2:$F$19,4,FALSE()) -> 20 | P13: =VLOOKUP(A13,Activity_Summary!$A$2:$D$19,2,FALSE()) -> 1 | Q13: =VLOOKUP(A13,Activity_Summary!$A$2:$D$19,3,FALSE()) -> 46217 | R13: =Assumptions!$B$8-Q13 -> 1 | S13: =IF(COUNTIFS(Raw_Contacts!$B$2:$B$41,A13,Raw_Contacts!$F$2:$F$41,"Final Renewal Approver",Raw_Contacts!$H$2:$H$41,"Approved")>0,"Ready",IF(COUNTIFS(Raw_Contacts!$B$2:$B$41,A13,Raw_Contacts!$H$2:$H$41,"Operations Only")>0,"Ops route only",IF(COUNTIFS(Raw_Contacts!$B$2:$B$41,A13,Raw_Contacts!$H$2:$H$41,"Do not contact executive")>0,"Manager route only","Pending permission"))) -> Ready | T13: =IF(VLOOKUP(A13,Case_Summary!$A$2:$F$19,5,FALSE())=0,"",VLOOKUP(A13,Case_Summary!$A$2:$F$19,5,FALSE())) -> Delivery Underpacing | U13: =IF(VLOOKUP(A13,Raw_Approval!$A$2:$G$19,3,FALSE())=0,"",VLOOKUP(A13,Raw_Approval!$A$2:$G$19,3,FALSE())) -> MG-15 | V13: =VLOOKUP(A13,Raw_CRM!$A$2:$L$19,10,FALSE()) -> 24000 | W13: =IF(U13="","",IFERROR(VLOOKUP(U13,Raw_Offers!$A$2:$G$7,4,FALSE()),0)) -> 25000 | X13: =IF(H13<>"Approved execution","Controlled",IF(U13="","No offer",IF(U13="MGR-REQ","Manager required",IF(OR(W13=0,V13<=W13),"Within authority","Over limit")))) -> Within authority | Y13: =IF(VLOOKUP(A13,Raw_Approval!$A$2:$G$19,5,FALSE())=0,"",VLOOKUP(A13,Raw_Approval!$A$2:$G$19,5,FALSE())) | Z13: CRM, cases, orders, contacts, activity, offers, approval
... A19: A-1018 | B19: =VLOOKUP(A19,Raw_CRM!$A$2:$L$19,2,FALSE()) -> Pinyon Outdoor Media Buyers | C19: =VLOOKUP(A19,Raw_CRM!$A$2:$L$19,3,FALSE()) -> Agency | D19: =VLOOKUP(A19,Raw_CRM!$A$2:$L$19,4,FALSE()) -> Core | E19: =VLOOKUP(A19,Raw_CRM!$A$2:$L$19,5,FALSE()) -> Priya Nair | F19: =VLOOKUP(A19,Raw_CRM!$A$2:$L$19,6,FALSE()) -> 46283 | G19: =VLOOKUP(A19,Raw_CRM!$A$2:$L$19,7,FALSE()) -> 66 | H19: =VLOOKUP(A19,Raw_Approval!$A$2:$G$19,2,FALSE()) -> Excluded - no action | I19: =VLOOKUP(A19,Raw_Orders!$A$2:$H$19,6,FALSE()) -> 135000 | J19: =VLOOKUP(A19,Raw_Orders!$A$2:$H$19,4,FALSE()) -> 124000 | K19: =VLOOKUP(A19,Raw_Orders!$A$2:$H$19,5,FALSE()) -> 118000 | L19: =K19-J19 -> -6000 | M19: =VLOOKUP(A19,Case_Summary!$A$2:$F$19,2,FALSE()) -> 1 | N19: =VLOOKUP(A19,Case_Summary!$A$2:$F$19,3,FALSE()) -> 2 | O19: =VLOOKUP(A19,Case_Summary!$A$2:$F$19,4,FALSE()) -> 6 | P19: =VLOOKUP(A19,Activity_Summary!$A$2:$D$19,2,FALSE()) -> 0 | Q19: =VLOOKUP(A19,Activity_Summary!$A$2:$D$19,3,FALSE()) -> 46217 | R19: =Assumptions!$B$8-Q19 -> 1 | S19: =IF(COUNTIFS(Raw_Contacts!$B$2:$B$41,A19,Raw_Contacts!$F$2:$F$41,"Final Renewal Approver",Raw_Contacts!$H$2:$H$41,"Approved")>0,"Ready",IF(COUNTIFS(Raw_Contacts!$B$2:$B$41,A19,Raw_Contacts!$H$2:$H$41,"Operations Only")>0,"Ops route only",IF(COUNTIFS(Raw_Contacts!$B$2:$B$41,A19,Raw_Contacts!$H$2:$H$41,"Do not contact executive")>0,"Manager route only","Pending permission"))) -> Pending permission | T19: =IF(VLOOKUP(A19,Case_Summary!$A$2:$F$19,5,FALSE())=0,"",VLOOKUP(A19,Case_Summary!$A$2:$F$19,5,FALSE())) -> Agency Consolidation | U19: =IF(VLOOKUP(A19,Raw_Approval!$A$2:$G$19,3,FALSE())=0,"",VLOOKUP(A19,Raw_Approval!$A$2:$G$19,3,FALSE())) | V19: =VLOOKUP(A19,Raw_CRM!$A$2:$L$19,10,FALSE()) -> 0 | W19: =IF(U19="","",IFERROR(VLOOKUP(U19,Raw_Offers!$A$2:$G$7,4,FALSE()),0)) | X19: =IF(H19<>"Approved execution","Controlled",IF(U19="","No offer",IF(U19="MGR-REQ","Manager required",IF(OR(W19=0,V19<=W19),"Within authority","Over limit")))) -> Controlled | Y19: =IF(VLOOKUP(A19,Raw_Approval!$A$2:$G$19,5,FALSE())=0,"",VLOOKUP(A19,Raw_Approval!$A$2:$G$19,5,FALSE())) -> Customer requested September review | Z19: CRM, cases, orders, contacts, activity, offers, approval

Sheet Scoring
A1: Account ID | B1: Account Name | C1: Approval Status | D1: Exposure Score | E1: Issue Burden Score | F1: Health Risk Score | G1: Urgency Score | H1: Activity Risk Score | I1: Forecast Risk Score | J1: Contact Readiness Score | K1: Recovery Risk Score | L1: Priority Score | M1: Rank | N1: Priority Tier
A2: A-1001 | B2: =VLOOKUP(A2,Normalized_Accounts!$A$2:$Z$19,2,FALSE()) -> Meridian Health Partners | C2: =VLOOKUP(A2,Normalized_Accounts!$A$2:$Z$19,8,FALSE()) -> Approved execution | D2: =MIN(100,VLOOKUP(A2,Normalized_Accounts!$A$2:$Z$19,9,FALSE())/Assumptions!$B$7*100) -> 85 | E2: =MIN(100,VLOOKUP(A2,Normalized_Accounts!$A$2:$Z$19,13,FALSE())*12+VLOOKUP(A2,Normalized_Accounts!$A$2:$Z$19,14,FALSE())*10+VLOOKUP(A2,Normalized_Accounts!$A$2:$Z$19,15,FALSE())*0.9) -> 81.1 | F2: =100-VLOOKUP(A2,Normalized_Accounts!$A$2:$Z$19,7,FALSE()) -> 52 | G2: =IF(VLOOKUP(A2,Normalized_Accounts!$A$2:$Z$19,6,FALSE())-Assumptions!$B$8<=14,100,IF(VLOOKUP(A2,Normalized_Accounts!$A$2:$Z$19,6,FALSE())-Assumptions!$B$8<=30,75,IF(VLOOKUP(A2,Normalized_Accounts!$A$2:$Z$19,6,FALSE())-Assumptions!$B$8<=45,50,25))) -> 100 | H2: =MIN(100,VLOOKUP(A2,Normalized_Accounts!$A$2:$Z$19,16,FALSE())*30+VLOOKUP(A2,Normalized_Accounts!$A$2:$Z$19,18,FALSE())*2) -> 32 | I2: =MIN(100,ABS(VLOOKUP(A2,Normalized_Accounts!$A$2:$Z$19,12,FALSE()))/100000*100) -> 38 | J2: =IF(VLOOKUP(A2,Normalized_Accounts!$A$2:$Z$19,19,FALSE())="Ready",100,IF(VLOOKUP(A2,Normalized_Accounts!$A$2:$Z$19,19,FALSE())="Ops route only",60,IF(VLOOKUP(A2,Normalized_Accounts!$A$2:$Z$19,19,FALSE())="Manager route only",20,0))) -> 100 | K2: =F2*0.35+E2*0.4+H2*0.25 -> 58.64 | L2: =D2*Assumptions!$B$2+K2*Assumptions!$B$3+G2*Assumptions!$B$4+J2*Assumptions!$B$5+I2*Assumptions!$B$6 -> 77.924 | M2: =RANK(L2,$L$2:$L$19,0) -> 2 | N2: =IF(C2<>"Approved execution","Controlled exception/hold",IF(L2>=75,"Tier 1",IF(L2>=60,"Tier 2","Tier 3"))) -> Tier 1
A3: A-1002 | B3: =VLOOKUP(A3,Normalized_Accounts!$A$2:$Z$19,2,FALSE()) -> Larkspur Credit Union | C3: =VLOOKUP(A3,Normalized_Accounts!$A$2:$Z$19,8,FALSE()) -> Approved execution | D3: =MIN(100,VLOOKUP(A3,Normalized_Accounts!$A$2:$Z$19,9,FALSE())/Assumptions!$B$7*100) -> 55 | E3: =MIN(100,VLOOKUP(A3,Normalized_Accounts!$A$2:$Z$19,13,FALSE())*12+VLOOKUP(A3,Normalized_Accounts!$A$2:$Z$19,14,FALSE())*10+VLOOKUP(A3,Normalized_Accounts!$A$2:$Z$19,15,FALSE())*0.9) -> 67.3 | F3: =100-VLOOKUP(A3,Normalized_Accounts!$A$2:$Z$19,7,FALSE()) -> 48 | G3: =IF(VLOOKUP(A3,Normalized_Accounts!$A$2:$Z$19,6,FALSE())-Assumptions!$B$8<=14,100,IF(VLOOKUP(A3,Normalized_Accounts!$A$2:$Z$19,6,FALSE())-Assumptions!$B$8<=30,75,IF(VLOOKUP(A3,Normalized_Accounts!$A$2:$Z$19,6,FALSE())-Assumptions!$B$8<=45,50,25))) -> 75 | H3: =MIN(100,VLOOKUP(A3,Normalized_Accounts!$A$2:$Z$19,16,FALSE())*30+VLOOKUP(A3,Normalized_Accounts!$A$2:$Z$19,18,FALSE())*2) -> 10 | I3: =MIN(100,ABS(VLOOKUP(A3,Normalized_Accounts!$A$2:$Z$19,12,FALSE()))/100000*100) -> 21 | J3: =IF(VLOOKUP(A3,Normalized_Accounts!$A$2:$Z$19,19,FALSE())="Ready",100,IF(VLOOKUP(A3,Normalized_Accounts!$A$2:$Z$19,19,FALSE())="Ops route only",60,IF(VLOOKUP(A3,Normalized_Accounts!$A$2:$Z$19,19,FALSE())="Manager route only",20,0))) -> 100 | K3: =F3*0.35+E3*0.4+H3*0.25 -> 46.22 | L3: =D3*Assumptions!$B$2+K3*Assumptions!$B$3+G3*Assumptions!$B$4+J3*Assumptions!$B$5+I3*Assumptions!$B$6 -> 58.727 | M3: =RANK(L3,$L$2:$L$19,0) -> 10 | N3: =IF(C3<>"Approved execution","Controlled exception/hold",IF(L3>=75,"Tier 1",IF(L3>=60,"Tier 2","Tier 3"))) -> Tier 3
A4: A-1003 | B4: =VLOOKUP(A4,Normalized_Accounts!$A$2:$Z$19,2,FALSE()) -> Cobalt Cloud Systems | C4: =VLOOKUP(A4,Normalized_Accounts!$A$2:$Z$19,8,FALSE()) -> Approved execution | D4: =MIN(100,VLOOKUP(A4,Normalized_Accounts!$A$2:$Z$19,9,FALSE())/Assumptions!$B$7*100) -> 73.75 | E4: =MIN(100,VLOOKUP(A4,Normalized_Accounts!$A$2:$Z$19,13,FALSE())*12+VLOOKUP(A4,Normalized_Accounts!$A$2:$Z$19,14,FALSE())*10+VLOOKUP(A4,Normalized_Accounts!$A$2:$Z$19,15,FALSE())*0.9) -> 79.3 | F4: =100-VLOOKUP(A4,Normalized_Accounts!$A$2:$Z$19,7,FALSE()) -> 44 | G4: =IF(VLOOKUP(A4,Normalized_Accounts!$A$2:$Z$19,6,FALSE())-Assumptions!$B$8<=14,100,IF(VLOOKUP(A4,Normalized_Accounts!$A$2:$Z$19,6,FALSE())-Assumptions!$B$8<=30,75,IF(VLOOKUP(A4,Normalized_Accounts!$A$2:$Z$19,6,FALSE())-Assumptions!$B$8<=45,50,25))) -> 75 | H4: =MIN(100,VLOOKUP(A4,Normalized_Accounts!$A$2:$Z$19,16,FALSE())*30+VLOOKUP(A4,Normalized_Accounts!$A$2:$Z$19,18,FALSE())*2) -> 8 | I4: =MIN(100,ABS(VLOOKUP(A4,Normalized_Accounts!$A$2:$Z$19,12,FALSE()))/100000*100) -> 35 | J4: =IF(VLOOKUP(A4,Normalized_Accounts!$A$2:$Z$19,19,FALSE())="Ready",100,IF(VLOOKUP(A4,Normalized_Accounts!$A$2:$Z$19,19,FALSE())="Ops route only",60,IF(VLOOKUP(A4,Normalized_Accounts!$A$2:$Z$19,19,FALSE())="Manager route only",20,0))) -> 100 | K4: =F4*0.35+E4*0.4+H4*0.25 -> 49.12 | L4: =D4*Assumptions!$B$2+K4*Assumptions!$B$3+G4*Assumptions!$B$4+J4*Assumptions!$B$5+I4*Assumptions!$B$6 -> 66.067 | M4: =RANK(L4,$L$2:$L$19,0) -> 7 | N4: =IF(C4<>"Approved execution","Controlled exception/hold",IF(L4>=75,"Tier 1",IF(L4>=60,"Tier 2","Tier 3"))) -> Tier 2
A5: A-1004 | B5: =VLOOKUP(A5,Normalized_Accounts!$A$2:$Z$19,2,FALSE()) -> Harborview Furnishings | C5: =VLOOKUP(A5,Normalized_Accounts!$A$2:$Z$19,8,FALSE()) -> Approved execution | D5: =MIN(100,VLOOKUP(A5,Normalized_Accounts!$A$2:$Z$19,9,FALSE())/Assumptions!$B$7*100) -> 37.5 | E5: =MIN(100,VLOOKUP(A5,Normalized_Accounts!$A$2:$Z$19,13,FALSE())*12+VLOOKUP(A5,Normalized_Accounts!$A$2:$Z$19,14,FALSE())*10+VLOOKUP(A5,Normalized_Accounts!$A$2:$Z$19,15,FALSE())*0.9) -> 54.6 | F5: =100-VLOOKUP(A5,Normalized_Accounts!$A$2:$Z$19,7,FALSE()) -> 39 | G5: =IF(VLOOKUP(A5,Normalized_Accounts!$A$2:$Z$19,6,FALSE())-Assumptions!$B$8<=14,100,IF(VLOOKUP(A5,Normalized_Accounts!$A$2:$Z$19,6,FALSE())-Assumptions!$B$8<=30,75,IF(VLOOKUP(A5,Normalized_Accounts!$A$2:$Z$19,6,FALSE())-Assumptions!$B$8<=45,50,25))) -> 100 | H5: =MIN(100,VLOOKUP(A5,Normalized_Accounts!$A$2:$Z$19,16,FALSE())*30+VLOOKUP(A5,Normalized_Accounts!$A$2:$Z$19,18,FALSE())*2) -> 42 | I5: =MIN(100,ABS(VLOOKUP(A5,Normalized_Accounts!$A$2:$Z$19,12,FALSE()))/100000*100) -> 13 | J5: =IF(VLOOKUP(A5,Normalized_Accounts!$A$2:$Z$19,19,FALSE())="Ready",100,IF(VLOOKUP(A5,Normalized_Accounts!$A$2:$Z$19,19,FALSE())="Ops route only",60,IF(VLOOKUP(A5,Normalized_Accounts!$A$2:$Z$19,19,FALSE())="Manager route only",20,0))) -> 100 | K5: =F5*0.35+E5*0.4+H5*0.25 -> 45.99 | L5: =D5*Assumptions!$B$2+K5*Assumptions!$B$3+G5*Assumptions!$B$4+J5*Assumptions!$B$5+I5*Assumptions!$B$6 -> 57.9965 | M5: =RANK(L5,$L$2:$L$19,0) -> 11 | N5: =IF(C5<>"Approved execution","Controlled exception/hold",IF(L5>=75,"Tier 1",IF(L5>=60,"Tier 2","Tier 3"))) -> Tier 3
A6: A-1005 | B6: =VLOOKUP(A6,Normalized_Accounts!$A$2:$Z$19,2,FALSE()) -> Axion Robotics | C6: =VLOOKUP(A6,Normalized_Accounts!$A$2:$Z$19,8,FALSE()) -> Approved execution | D6: =MIN(100,VLOOKUP(A6,Normalized_Accounts!$A$2:$Z$19,9,FALSE())/Assumptions!$B$7*100) -> 100 | E6: =MIN(100,VLOOKUP(A6,Normalized_Accounts!$A$2:$Z$19,13,FALSE())*12+VLOOKUP(A6,Normalized_Accounts!$A$2:$Z$19,14,FALSE())*10+VLOOKUP(A6,Normalized_Accounts!$A$2:$Z$19,15,FALSE())*0.9) -> 94.7 | F6: =100-VLOOKUP(A6,Normalized_Accounts!$A$2:$Z$19,7,FALSE()) -> 56 | G6: =IF(VLOOKUP(A6,Normalized_Accounts!$A$2:$Z$19,6,FALSE())-Assumptions!$B$8<=14,100,IF(VLOOKUP(A6,Normalized_Accounts!$A$2:$Z$19,6,FALSE())-Assumptions!$B$8<=30,75,IF(VLOOKUP(A6,Normalized_Accounts!$A$2:$Z$19,6,FALSE())-Assumptions!$B$8<=45,50,25))) -> 75 | H6: =MIN(100,VLOOKUP(A6,Normalized_Accounts!$A$2:$Z$19,16,FALSE())*30+VLOOKUP(A6,Normalized_Accounts!$A$2:$Z$19,18,FALSE())*2) -> 34 | I6: =MIN(100,ABS(VLOOKUP(A6,Normalized_Accounts!$A$2:$Z$19,12,FALSE()))/100000*100) -> 72 | J6: =IF(VLOOKUP(A6,Normalized_Accounts!$A$2:$Z$19,19,FALSE())="Ready",100,IF(VLOOKUP(A6,Normalized_Accounts!$A$2:$Z$19,19,FALSE())="Ops route only",60,IF(VLOOKUP(A6,Normalized_Accounts!$A$2:$Z$19,19,FALSE())="Manager route only",20,0))) -> 100 | K6: =F6*0.35+E6*0.4+H6*0.25 -> 65.98 | L6: =D6*Assumptions!$B$2+K6*Assumptions!$B$3+G6*Assumptions!$B$4+J6*Assumptions!$B$5+I6*Assumptions!$B$6 -> 81.693 | M6: =RANK(L6,$L$2:$L$19,0) -> 1 | N6: =IF(C6<>"Approved execution","Controlled exception/hold",IF(L6>=75,"Tier 1",IF(L6>=60,"Tier 2","Tier 3"))) -> Tier 1
A7: A-1006 | B7: =VLOOKUP(A7,Normalized_Accounts!$A$2:$Z$19,2,FALSE()) -> Greenway Kitchens | C7: =VLOOKUP(A7,Normalized_Accounts!$A$2:$Z$19,8,FALSE()) -> Approved execution | D7: =MIN(100,VLOOKUP(A7,Normalized_Accounts!$A$2:$Z$19,9,FALSE())/Assumptions!$B$7*100) -> 20.5 | E7: =MIN(100,VLOOKUP(A7,Normalized_Accounts!$A$2:$Z$19,13,FALSE())*12+VLOOKUP(A7,Normalized_Accounts!$A$2:$Z$19,14,FALSE())*10+VLOOKUP(A7,Normalized_Accounts!$A$2:$Z$19,15,FALSE())*0.9) -> 51 | F7: =100-VLOOKUP(A7,Normalized_Accounts!$A$2:$Z$19,7,FALSE()) -> 32 | G7: =IF(VLOOKUP(A7,Normalized_Accounts!$A$2:$Z$19,6,FALSE())-Assumptions!$B$8<=14,100,IF(VLOOKUP(A7,Normalized_Accounts!$A$2:$Z$19,6,FALSE())-Assumptions!$B$8<=30,75,IF(VLOOKUP(A7,Normalized_Accounts!$A$2:$Z$19,6,FALSE())-Assumptions!$B$8<=45,50,25))) -> 100 | H7: =MIN(100,VLOOKUP(A7,Normalized_Accounts!$A$2:$Z$19,16,FALSE())*30+VLOOKUP(A7,Normalized_Accounts!$A$2:$Z$19,18,FALSE())*2) -> 4 | I7: =MIN(100,ABS(VLOOKUP(A7,Normalized_Accounts!$A$2:$Z$19,12,FALSE()))/100000*100) -> 5 | J7: =IF(VLOOKUP(A7,Normalized_Accounts!$A$2:$Z$19,19,FALSE())="Ready",100,IF(VLOOKUP(A7,Normalized_Accounts!$A$2:$Z$19,19,FALSE())="Ops route only",60,IF(VLOOKUP(A7,Normalized_Accounts!$A$2:$Z$19,19,FALSE())="Manager route only",20,0))) -> 100 | K7: =F7*0.35+E7*0.4+H7*0.25 -> 32.6 | L7: =D7*Assumptions!$B$2+K7*Assumptions!$B$3+G7*Assumptions!$B$4+J7*Assumptions!$B$5+I7*Assumptions!$B$6 -> 47.81 | M7: =RANK(L7,$L$2:$L$19,0) -> 13 | N7: =IF(C7<>"Approved execution","Controlled exception/hold",IF(L7>=75,"Tier 1",IF(L7>=60,"Tier 2","Tier 3"))) -> Tier 3
A8: A-1007 | B8: =VLOOKUP(A8,Normalized_Accounts!$A$2:$Z$19,2,FALSE()) -> Northline Insurance | C8: =VLOOKUP(A8,Normalized_Accounts!$A$2:$Z$19,8,FALSE()) -> Approved execution | D8: =MIN(100,VLOOKUP(A8,Normalized_Accounts!$A$2:$Z$19,9,FALSE())/Assumptions!$B$7*100) -> 65 | E8: =MIN(100,VLOOKUP(A8,Normalized_Accounts!$A$2:$Z$19,13,FALSE())*12+VLOOKUP(A8,Normalized_Accounts!$A$2:$Z$19,14,FALSE())*10+VLOOKUP(A8,Normalized_Accounts!$A$2:$Z$19,15,FALSE())*0.9) -> 72.7 | F8: =100-VLOOKUP(A8,Normalized_Accounts!$A$2:$Z$19,7,FALSE()) -> 50 | G8: =IF(VLOOKUP(A8,Normalized_Accounts!$A$2:$Z$19,6,FALSE())-Assumptions!$B$8<=14,100,IF(VLOOKUP(A8,Normalized_Accounts!$A$2:$Z$19,6,FALSE())-Assumptions!$B$8<=30,75,IF(VLOOKUP(A8,Normalized_Accounts!$A$2:$Z$19,6,FALSE())-Assumptions!$B$8<=45,50,25))) -> 75 | H8: =MIN(100,VLOOKUP(A8,Normalized_Accounts!$A$2:$Z$19,16,FALSE())*30+VLOOKUP(A8,Normalized_Accounts!$A$2:$Z$19,18,FALSE())*2) -> 40 | I8: =MIN(100,ABS(VLOOKUP(A8,Normalized_Accounts!$A$2:$Z$19,12,FALSE()))/100000*100) -> 40 | J8: =IF(VLOOKUP(A8,Normalized_Accounts!$A$2:$Z$19,19,FALSE())="Ready",100,IF(VLOOKUP(A8,Normalized_Accounts!$A$2:$Z$19,19,FALSE())="Ops route only",60,IF(VLOOKUP(A8,Normalized_Accounts!$A$2:$Z$19,19,FALSE())="Manager route only",20,0))) -> 100 | K8: =F8*0.35+E8*0.4+H8*0.25 -> 56.58 | L8: =D8*Assumptions!$B$2+K8*Assumptions!$B$3+G8*Assumptions!$B$4+J8*Assumptions!$B$5+I8*Assumptions!$B$6 -> 66.303 | M8: =RANK(L8,$L$2:$L$19,0) -> 6 | N8: =IF(C8<>"Approved execution","Controlled exception/hold",IF(L8>=75,"Tier 1",IF(L8>=60,"Tier 2","Tier 3"))) -> Tier 2
A9: A-1008 | B9: =VLOOKUP(A9,Normalized_Accounts!$A$2:$Z$19,2,FALSE()) -> Veridian Charter Schools | C9: =VLOOKUP(A9,Normalized_Accounts!$A$2:$Z$19,8,FALSE()) -> Approved execution | D9: =MIN(100,VLOOKUP(A9,Normalized_Accounts!$A$2:$Z$19,9,FALSE())/Assumptions!$B$7*100) -> 27.5 | E9: =MIN(100,VLOOKUP(A9,Normalized_Accounts!$A$2:$Z$19,13,FALSE())*12+VLOOKUP(A9,Normalized_Accounts!$A$2:$Z$19,14,FALSE())*10+VLOOKUP(A9,Normalized_Accounts!$A$2:$Z$19,15,FALSE())*0.9) -> 50.1 | F9: =100-VLOOKUP(A9,Normalized_Accounts!$A$2:$Z$19,7,FALSE()) -> 37 | G9: =IF(VLOOKUP(A9,Normalized_Accounts!$A$2:$Z$19,6,FALSE())-Assumptions!$B$8<=14,100,IF(VLOOKUP(A9,Normalized_Accounts!$A$2:$Z$19,6,FALSE())-Assumptions!$B$8<=30,75,IF(VLOOKUP(A9,Normalized_Accounts!$A$2:$Z$19,6,FALSE())-Assumptions!$B$8<=45,50,25))) -> 50 | H9: =MIN(100,VLOOKUP(A9,Normalized_Accounts!$A$2:$Z$19,16,FALSE())*30+VLOOKUP(A9,Normalized_Accounts!$A$2:$Z$19,18,FALSE())*2) -> 6 | I9: =MIN(100,ABS(VLOOKUP(A9,Normalized_Accounts!$A$2:$Z$19,12,FALSE()))/100000*100) -> 10 | J9: =IF(VLOOKUP(A9,Normalized_Accounts!$A$2:$Z$19,19,FALSE())="Ready",100,IF(VLOOKUP(A9,Normalized_Accounts!$A$2:$Z$19,19,FALSE())="Ops route only",60,IF(VLOOKUP(A9,Normalized_Accounts!$A$2:$Z$19,19,FALSE())="Manager route only",20,0))) -> 100 | K9: =F9*0.35+E9*0.4+H9*0.25 -> 34.49 | L9: =D9*Assumptions!$B$2+K9*Assumptions!$B$3+G9*Assumptions!$B$4+J9*Assumptions!$B$5+I9*Assumptions!$B$6 -> 40.8215 | M9: =RANK(L9,$L$2:$L$19,0) -> 15 | N9: =IF(C9<>"Approved execution","Controlled exception/hold",IF(L9>=75,"Tier 1",IF(L9>=60,"Tier 2","Tier 3"))) -> Tier 3
A10: A-1009 | B10: =VLOOKUP(A10,Normalized_Accounts!$A$2:$Z$19,2,FALSE()) -> Copper Trail Hospitality | C10: =VLOOKUP(A10,Normalized_Accounts!$A$2:$Z$19,8,FALSE()) -> Approved execution | D10: =MIN(100,VLOOKUP(A10,Normalized_Accounts!$A$2:$Z$19,9,FALSE())/Assumptions!$B$7*100) -> 47.5 | E10: =MIN(100,VLOOKUP(A10,Normalized_Accounts!$A$2:$Z$19,13,FALSE())*12+VLOOKUP(A10,Normalized_Accounts!$A$2:$Z$19,14,FALSE())*10+VLOOKUP(A10,Normalized_Accounts!$A$2:$Z$19,15,FALSE())*0.9) -> 70 | F10: =100-VLOOKUP(A10,Normalized_Accounts!$A$2:$Z$19,7,FALSE()) -> 42 | G10: =IF(VLOOKUP(A10,Normalized_Accounts!$A$2:$Z$19,6,FALSE())-Assumptions!$B$8<=14,100,IF(VLOOKUP(A10,Normalized_Accounts!$A$2:$Z$19,6,FALSE())-Assumptions!$B$8<=30,75,IF(VLOOKUP(A10,Normalized_Accounts!$A$2:$Z$19,6,FALSE())-Assumptions!$B$8<=45,50,25))) -> 100 | H10: =MIN(100,VLOOKUP(A10,Normalized_Accounts!$A$2:$Z$19,16,FALSE())*30+VLOOKUP(A10,Normalized_Accounts!$A$2:$Z$19,18,FALSE())*2) -> 42 | I10: =MIN(100,ABS(VLOOKUP(A10,Normalized_Accounts!$A$2:$Z$19,12,FALSE()))/100000*100) -> 25 | J10: =IF(VLOOKUP(A10,Normalized_Accounts!$A$2:$Z$19,19,FALSE())="Ready",100,IF(VLOOKUP(A10,Normalized_Accounts!$A$2:$Z$19,19,FALSE())="Ops route only",60,IF(VLOOKUP(A10,Normalized_Accounts!$A$2:$Z$19,19,FALSE())="Manager route only",20,0))) -> 100 | K10: =F10*0.35+E10*0.4+H10*0.25 -> 53.2 | L10: =D10*Assumptions!$B$2+K10*Assumptions!$B$3+G10*Assumptions!$B$4+J10*Assumptions!$B$5+I10*Assumptions!$B$6 -> 64.12 | M10: =RANK(L10,$L$2:$L$19,0) -> 8 | N10: =IF(C10<>"Approved execution","Controlled exception/hold",IF(L10>=75,"Tier 1",IF(L10>=60,"Tier 2","Tier 3"))) -> Tier 2
A11: A-1010 | B11: =VLOOKUP(A11,Normalized_Accounts!$A$2:$Z$19,2,FALSE()) -> Finch Legal Group | C11: =VLOOKUP(A11,Normalized_Accounts!$A$2:$Z$19,8,FALSE()) -> Approved execution | D11: =MIN(100,VLOOKUP(A11,Normalized_Accounts!$A$2:$Z$19,9,FALSE())/Assumptions!$B$7*100) -> 18.75 | E11: =MIN(100,VLOOKUP(A11,Normalized_Accounts!$A$2:$Z$19,13,FALSE())*12+VLOOKUP(A11,Normalized_Accounts!$A$2:$Z$19,14,FALSE())*10+VLOOKUP(A11,Normalized_Accounts!$A$2:$Z$19,15,FALSE())*0.9) -> 36.5 | F11: =100-VLOOKUP(A11,Normalized_Accounts!$A$2:$Z$19,7,FALSE()) -> 30 | G11: =IF(VLOOKUP(A11,Normalized_Accounts!$A$2:$Z$19,6,FALSE())-Assumptions!$B$8<=14,100,IF(VLOOKUP(A11,Normalized_Accounts!$A$2:$Z$19,6,FALSE())-Assumptions!$B$8<=30,75,IF(VLOOKUP(A11,Normalized_Accounts!$A$2:$Z$19,6,FALSE())-Assumptions!$B$8<=45,50,25))) -> 50 | H11: =MIN(100,VLOOKUP(A11,Normalized_Accounts!$A$2:$Z$19,16,FALSE())*30+VLOOKUP(A11,Normalized_Accounts!$A$2:$Z$19,18,FALSE())*2) -> 2 | I11: =MIN(100,ABS(VLOOKUP(A11,Normalized_Accounts!$A$2:$Z$19,12,FALSE()))/100000*100) -> 2 | J11: =IF(VLOOKUP(A11,Normalized_Accounts!$A$2:$Z$19,19,FALSE())="Ready",100,IF(VLOOKUP(A11,Normalized_Accounts!$A$2:$Z$19,19,FALSE())="Ops route only",60,IF(VLOOKUP(A11,Normalized_Accounts!$A$2:$Z$19,19,FALSE())="Manager route only",20,0))) -> 100 | K11: =F11*0.35+E11*0.4+H11*0.25 -> 25.6 | L11: =D11*Assumptions!$B$2+K11*Assumptions!$B$3+G11*Assumptions!$B$4+J11*Assumptions!$B$5+I11*Assumptions!$B$6 -> 34.685 | M11: =RANK(L11,$L$2:$L$19,0) -> 17 | N11: =IF(C11<>"Approved execution","Controlled exception/hold",IF(L11>=75,"Tier 1",IF(L11>=60,"Tier 2","Tier 3"))) -> Tier 3
A12: A-1011 | B12: =VLOOKUP(A12,Normalized_Accounts!$A$2:$Z$19,2,FALSE()) -> Solstice Energy Co-op | C12: =VLOOKUP(A12,Normalized_Accounts!$A$2:$Z$19,8,FALSE()) -> Approved execution | D12: =MIN(100,VLOOKUP(A12,Normalized_Accounts!$A$2:$Z$19,9,FALSE())/Assumptions!$B$7*100) -> 43.75 | E12: =MIN(100,VLOOKUP(A12,Normalized_Accounts!$A$2:$Z$19,13,FALSE())*12+VLOOKUP(A12,Normalized_Accounts!$A$2:$Z$19,14,FALSE())*10+VLOOKUP(A12,Normalized_Accounts!$A$2:$Z$19,15,FALSE())*0.9) -> 68.2 | F12: =100-VLOOKUP(A12,Normalized_Accounts!$A$2:$Z$19,7,FALSE()) -> 45 | G12: =IF(VLOOKUP(A12,Normalized_Accounts!$A$2:$Z$19,6,FALSE())-Assumptions!$B$8<=14,100,IF(VLOOKUP(A12,Normalized_Accounts!$A$2:$Z$19,6,FALSE())-Assumptions!$B$8<=30,75,IF(VLOOKUP(A12,Normalized_Accounts!$A$2:$Z$19,6,FALSE())-Assumptions!$B$8<=45,50,25))) -> 75 | H12: =MIN(100,VLOOKUP(A12,Normalized_Accounts!$A$2:$Z$19,16,FALSE())*30+VLOOKUP(A12,Normalized_Accounts!$A$2:$Z$19,18,FALSE())*2) -> 10 | I12: =MIN(100,ABS(VLOOKUP(A12,Normalized_Accounts!$A$2:$Z$19,12,FALSE()))/100000*100) -> 20 | J12: =IF(VLOOKUP(A12,Normalized_Accounts!$A$2:$Z$19,19,FALSE())="Ready",100,IF(VLOOKUP(A12,Normalized_Accounts!$A$2:$Z$19,19,FALSE())="Ops route only",60,IF(VLOOKUP(A12,Normalized_Accounts!$A$2:$Z$19,19,FALSE())="Manager route only",20,0))) -> 100 | K12: =F12*0.35+E12*0.4+H12*0.25 -> 45.53 | L12: =D12*Assumptions!$B$2+K12*Assumptions!$B$3+G12*Assumptions!$B$4+J12*Assumptions!$B$5+I12*Assumptions!$B$6 -> 55.0605 | M12: =RANK(L12,$L$2:$L$19,0) -> 12 | N12: =IF(C12<>"Approved execution","Controlled exception/hold",IF(L12>=75,"Tier 1",IF(L12>=60,"Tier 2","Tier 3"))) -> Tier 3
A13: A-1012 | B13: =VLOOKUP(A13,Normalized_Accounts!$A$2:$Z$19,2,FALSE()) -> Vesta Apparel Collective | C13: =VLOOKUP(A13,Normalized_Accounts!$A$2:$Z$19,8,FALSE()) -> Approved execution | D13: =MIN(100,VLOOKUP(A13,Normalized_Accounts!$A$2:$Z$19,9,FALSE())/Assumptions!$B$7*100) -> 76.25 | E13: =MIN(100,VLOOKUP(A13,Normalized_Accounts!$A$2:$Z$19,13,FALSE())*12+VLOOKUP(A13,Normalized_Accounts!$A$2:$Z$19,14,FALSE())*10+VLOOKUP(A13,Normalized_Accounts!$A$2:$Z$19,15,FALSE())*0.9) -> 92 | F13: =100-VLOOKUP(A13,Normalized_Accounts!$A$2:$Z$19,7,FALSE()) -> 53 | G13: =IF(VLOOKUP(A13,Normalized_Accounts!$A$2:$Z$19,6,FALSE())-Assumptions!$B$8<=14,100,IF(VLOOKUP(A13,Normalized_Accounts!$A$2:$Z$19,6,FALSE())-Assumptions!$B$8<=30,75,IF(VLOOKUP(A13,Normalized_Accounts!$A$2:$Z$19,6,FALSE())-Assumptions!$B$8<=45,50,25))) -> 75 | H13: =MIN(100,VLOOKUP(A13,Normalized_Accounts!$A$2:$Z$19,16,FALSE())*30+VLOOKUP(A13,Normalized_Accounts!$A$2:$Z$19,18,FALSE())*2) -> 32 | I13: =MIN(100,ABS(VLOOKUP(A13,Normalized_Accounts!$A$2:$Z$19,12,FALSE()))/100000*100) -> 52 | J13: =IF(VLOOKUP(A13,Normalized_Accounts!$A$2:$Z$19,19,FALSE())="Ready",100,IF(VLOOKUP(A13,Normalized_Accounts!$A$2:$Z$19,19,FALSE())="Ops route only",60,IF(VLOOKUP(A13,Normalized_Accounts!$A$2:$Z$19,19,FALSE())="Manager route only",20,0))) -> 100 | K13: =F13*0.35+E13*0.4+H13*0.25 -> 63.35 | L13: =D13*Assumptions!$B$2+K13*Assumptions!$B$3+G13*Assumptions!$B$4+J13*Assumptions!$B$5+I13*Assumptions!$B$6 -> 72.6475 | M13: =RANK(L13,$L$2:$L$19,0) -> 4 | N13: =IF(C13<>"Approved execution","Controlled exception/hold",IF(L13>=75,"Tier 1",IF(L13>=60,"Tier 2","Tier 3"))) -> Tier 2
... A19: A-1018 | B19: =VLOOKUP(A19,Normalized_Accounts!$A$2:$Z$19,2,FALSE()) -> Pinyon Outdoor Media Buyers | C19: =VLOOKUP(A19,Normalized_Accounts!$A$2:$Z$19,8,FALSE()) -> Excluded - no action | D19: =MIN(100,VLOOKUP(A19,Normalized_Accounts!$A$2:$Z$19,9,FALSE())/Assumptions!$B$7*100) -> 33.75 | E19: =MIN(100,VLOOKUP(A19,Normalized_Accounts!$A$2:$Z$19,13,FALSE())*12+VLOOKUP(A19,Normalized_Accounts!$A$2:$Z$19,14,FALSE())*10+VLOOKUP(A19,Normalized_Accounts!$A$2:$Z$19,15,FALSE())*0.9) -> 37.4 | F19: =100-VLOOKUP(A19,Normalized_Accounts!$A$2:$Z$19,7,FALSE()) -> 34 | G19: =IF(VLOOKUP(A19,Normalized_Accounts!$A$2:$Z$19,6,FALSE())-Assumptions!$B$8<=14,100,IF(VLOOKUP(A19,Normalized_Accounts!$A$2:$Z$19,6,FALSE())-Assumptions!$B$8<=30,75,IF(VLOOKUP(A19,Normalized_Accounts!$A$2:$Z$19,6,FALSE())-Assumptions!$B$8<=45,50,25))) -> 25 | H19: =MIN(100,VLOOKUP(A19,Normalized_Accounts!$A$2:$Z$19,16,FALSE())*30+VLOOKUP(A19,Normalized_Accounts!$A$2:$Z$19,18,FALSE())*2) -> 2 | I19: =MIN(100,ABS(VLOOKUP(A19,Normalized_Accounts!$A$2:$Z$19,12,FALSE()))/100000*100) -> 6 | J19: =IF(VLOOKUP(A19,Normalized_Accounts!$A$2:$Z$19,19,FALSE())="Ready",100,IF(VLOOKUP(A19,Normalized_Accounts!$A$2:$Z$19,19,FALSE())="Ops route only",60,IF(VLOOKUP(A19,Normalized_Accounts!$A$2:$Z$19,19,FALSE())="Manager route only",20,0))) -> 0 | K19: =F19*0.35+E19*0.4+H19*0.25 -> 27.36 | L19: =D19*Assumptions!$B$2+K19*Assumptions!$B$3+G19*Assumptions!$B$4+J19*Assumptions!$B$5+I19*Assumptions!$B$6 -> 25.001 | M19: =RANK(L19,$L$2:$L$19,0) -> 18 | N19: =IF(C19<>"Approved execution","Controlled exception/hold",IF(L19>=75,"Tier 1",IF(L19>=60,"Tier 2","Tier 3"))) -> Controlled exception/hold

Sheet Decisions
A1: Account ID | B1: Account Name | C1: Owner Rep | D1: Priority Tier | E1: Decision Status | F1: Approved Action | G1: Approved Offer | H1: Primary Contact | I1: Due Date | J1: Exception Reason | K1: Source Case | L1: Communication Status
A2: A-1001 | B2: =VLOOKUP(A2,Normalized_Accounts!$A$2:$Z$19,2,FALSE()) -> Meridian Health Partners | C2: =VLOOKUP(A2,Normalized_Accounts!$A$2:$Z$19,5,FALSE()) -> Maya Chen | D2: =VLOOKUP(A2,Scoring!$A$2:$N$19,14,FALSE()) -> Tier 1 | E2: =VLOOKUP(A2,Normalized_Accounts!$A$2:$Z$19,8,FALSE()) -> Approved execution | F2: =VLOOKUP(A2,Raw_Approval!$A$2:$G$19,4,FALSE()) -> Confirm makegood inventory and delivery recovery plan | G2: =IF(VLOOKUP(A2,Normalized_Accounts!$A$2:$Z$19,21,FALSE())=0,"",VLOOKUP(A2,Normalized_Accounts!$A$2:$Z$19,21,FALSE())) -> MG-15 | H2: Dr. Lena Morris | I2: =IF(E2="Approved execution",IF(D2="Tier 1",DATE(2026,7,20),IF(D2="Tier 2",DATE(2026,7,22),DATE(2026,7,24))),"") -> 46223 | J2: =IF(VLOOKUP(A2,Normalized_Accounts!$A$2:$Z$19,25,FALSE())=0,"",VLOOKUP(A2,Normalized_Accounts!$A$2:$Z$19,25,FALSE())) | K2: CASE-7201 | L2: =IF(E2="Approved execution","Ready to schedule",IF(E2="Controlled exception","Controlled exception","No sprint outreach")) -> Ready to schedule
A3: A-1002 | B3: =VLOOKUP(A3,Normalized_Accounts!$A$2:$Z$19,2,FALSE()) -> Larkspur Credit Union | C3: =VLOOKUP(A3,Normalized_Accounts!$A$2:$Z$19,5,FALSE()) -> Jordan Patel | D3: =VLOOKUP(A3,Scoring!$A$2:$N$19,14,FALSE()) -> Tier 3 | E3: =VLOOKUP(A3,Normalized_Accounts!$A$2:$Z$19,8,FALSE()) -> Approved execution | F3: =VLOOKUP(A3,Raw_Approval!$A$2:$G$19,4,FALSE()) -> Deliver reconciled reporting package and executive summary | G3: =IF(VLOOKUP(A3,Normalized_Accounts!$A$2:$Z$19,21,FALSE())=0,"",VLOOKUP(A3,Normalized_Accounts!$A$2:$Z$19,21,FALSE())) -> RPT-COMP | H3: Tanya Wells | I3: =IF(E3="Approved execution",IF(D3="Tier 1",DATE(2026,7,20),IF(D3="Tier 2",DATE(2026,7,22),DATE(2026,7,24))),"") -> 46227 | J3: =IF(VLOOKUP(A3,Normalized_Accounts!$A$2:$Z$19,25,FALSE())=0,"",VLOOKUP(A3,Normalized_Accounts!$A$2:$Z$19,25,FALSE())) | K3: CASE-7203 | L3: =IF(E3="Approved execution","Ready to schedule",IF(E3="Controlled exception","Controlled exception","No sprint outreach")) -> Ready to schedule
A4: A-1003 | B4: =VLOOKUP(A4,Normalized_Accounts!$A$2:$Z$19,2,FALSE()) -> Cobalt Cloud Systems | C4: =VLOOKUP(A4,Normalized_Accounts!$A$2:$Z$19,5,FALSE()) -> Priya Nair | D4: =VLOOKUP(A4,Scoring!$A$2:$N$19,14,FALSE()) -> Tier 2 | E4: =VLOOKUP(A4,Normalized_Accounts!$A$2:$Z$19,8,FALSE()) -> Approved execution | F4: =VLOOKUP(A4,Raw_Approval!$A$2:$G$19,4,FALSE()) -> Confirm verified billing credit and renewal rate hold | G4: =IF(VLOOKUP(A4,Normalized_Accounts!$A$2:$Z$19,21,FALSE())=0,"",VLOOKUP(A4,Normalized_Accounts!$A$2:$Z$19,21,FALSE())) -> CR-10K | H4: Rafael Soto | I4: =IF(E4="Approved execution",IF(D4="Tier 1",DATE(2026,7,20),IF(D4="Tier 2",DATE(2026,7,22),DATE(2026,7,24))),"") -> 46225 | J4: =IF(VLOOKUP(A4,Normalized_Accounts!$A$2:$Z$19,25,FALSE())=0,"",VLOOKUP(A4,Normalized_Accounts!$A$2:$Z$19,25,FALSE())) | K4: CASE-7204 | L4: =IF(E4="Approved execution","Ready to schedule",IF(E4="Controlled exception","Controlled exception","No sprint outreach")) -> Ready to schedule
A5: A-1004 | B5: =VLOOKUP(A5,Normalized_Accounts!$A$2:$Z$19,2,FALSE()) -> Harborview Furnishings | C5: =VLOOKUP(A5,Normalized_Accounts!$A$2:$Z$19,5,FALSE()) -> Luis Romero | D5: =VLOOKUP(A5,Scoring!$A$2:$N$19,14,FALSE()) -> Tier 3 | E5: =VLOOKUP(A5,Normalized_Accounts!$A$2:$Z$19,8,FALSE()) -> Approved execution | F5: =VLOOKUP(A5,Raw_Approval!$A$2:$G$19,4,FALSE()) -> Offer equivalent package swap after trafficking confirmation | G5: =IF(VLOOKUP(A5,Normalized_Accounts!$A$2:$Z$19,21,FALSE())=0,"",VLOOKUP(A5,Normalized_Accounts!$A$2:$Z$19,21,FALSE())) -> SW-PKG | H5: Nina Cho | I5: =IF(E5="Approved execution",IF(D5="Tier 1",DATE(2026,7,20),IF(D5="Tier 2",DATE(2026,7,22),DATE(2026,7,24))),"") -> 46227 | J5: =IF(VLOOKUP(A5,Normalized_Accounts!$A$2:$Z$19,25,FALSE())=0,"",VLOOKUP(A5,Normalized_Accounts!$A$2:$Z$19,25,FALSE())) | K5: CASE-7206 | L5: =IF(E5="Approved execution","Ready to schedule",IF(E5="Controlled exception","Controlled exception","No sprint outreach")) -> Ready to schedule
A6: A-1005 | B6: =VLOOKUP(A6,Normalized_Accounts!$A$2:$Z$19,2,FALSE()) -> Axion Robotics | C6: =VLOOKUP(A6,Normalized_Accounts!$A$2:$Z$19,5,FALSE()) -> Devon Brooks | D6: =VLOOKUP(A6,Scoring!$A$2:$N$19,14,FALSE()) -> Tier 1 | E6: =VLOOKUP(A6,Normalized_Accounts!$A$2:$Z$19,8,FALSE()) -> Approved execution | F6: =VLOOKUP(A6,Raw_Approval!$A$2:$G$19,4,FALSE()) -> Swap misaligned audience package and reset delivery proof | G6: =IF(VLOOKUP(A6,Normalized_Accounts!$A$2:$Z$19,21,FALSE())=0,"",VLOOKUP(A6,Normalized_Accounts!$A$2:$Z$19,21,FALSE())) -> SW-PKG | H6: Mark Feld | I6: =IF(E6="Approved execution",IF(D6="Tier 1",DATE(2026,7,20),IF(D6="Tier 2",DATE(2026,7,22),DATE(2026,7,24))),"") -> 46223 | J6: =IF(VLOOKUP(A6,Normalized_Accounts!$A$2:$Z$19,25,FALSE())=0,"",VLOOKUP(A6,Normalized_Accounts!$A$2:$Z$19,25,FALSE())) | K6: CASE-7207 | L6: =IF(E6="Approved execution","Ready to schedule",IF(E6="Controlled exception","Controlled exception","No sprint outreach")) -> Ready to schedule
A7: A-1006 | B7: =VLOOKUP(A7,Normalized_Accounts!$A$2:$Z$19,2,FALSE()) -> Greenway Kitchens | C7: =VLOOKUP(A7,Normalized_Accounts!$A$2:$Z$19,5,FALSE()) -> Maya Chen | D7: =VLOOKUP(A7,Scoring!$A$2:$N$19,14,FALSE()) -> Tier 3 | E7: =VLOOKUP(A7,Normalized_Accounts!$A$2:$Z$19,8,FALSE()) -> Approved execution | F7: =VLOOKUP(A7,Raw_Approval!$A$2:$G$19,4,FALSE()) -> Confirm verified invoice credit and corrected bill date | G7: =IF(VLOOKUP(A7,Normalized_Accounts!$A$2:$Z$19,21,FALSE())=0,"",VLOOKUP(A7,Normalized_Accounts!$A$2:$Z$19,21,FALSE())) -> CR-10K | H7: Gloria Kim | I7: =IF(E7="Approved execution",IF(D7="Tier 1",DATE(2026,7,20),IF(D7="Tier 2",DATE(2026,7,22),DATE(2026,7,24))),"") -> 46227 | J7: =IF(VLOOKUP(A7,Normalized_Accounts!$A$2:$Z$19,25,FALSE())=0,"",VLOOKUP(A7,Normalized_Accounts!$A$2:$Z$19,25,FALSE())) | K7: CASE-7209 | L7: =IF(E7="Approved execution","Ready to schedule",IF(E7="Controlled exception","Controlled exception","No sprint outreach")) -> Ready to schedule
A8: A-1007 | B8: =VLOOKUP(A8,Normalized_Accounts!$A$2:$Z$19,2,FALSE()) -> Northline Insurance | C8: =VLOOKUP(A8,Normalized_Accounts!$A$2:$Z$19,5,FALSE()) -> Jordan Patel | D8: =VLOOKUP(A8,Scoring!$A$2:$N$19,14,FALSE()) -> Tier 2 | E8: =VLOOKUP(A8,Normalized_Accounts!$A$2:$Z$19,8,FALSE()) -> Approved execution | F8: =VLOOKUP(A8,Raw_Approval!$A$2:$G$19,4,FALSE()) -> Confirm makegood placement and revised delivery dates | G8: =IF(VLOOKUP(A8,Normalized_Accounts!$A$2:$Z$19,21,FALSE())=0,"",VLOOKUP(A8,Normalized_Accounts!$A$2:$Z$19,21,FALSE())) -> MG-15 | H8: Samira Ahmad | I8: =IF(E8="Approved execution",IF(D8="Tier 1",DATE(2026,7,20),IF(D8="Tier 2",DATE(2026,7,22),DATE(2026,7,24))),"") -> 46225 | J8: =IF(VLOOKUP(A8,Normalized_Accounts!$A$2:$Z$19,25,FALSE())=0,"",VLOOKUP(A8,Normalized_Accounts!$A$2:$Z$19,25,FALSE())) | K8: CASE-7210 | L8: =IF(E8="Approved execution","Ready to schedule",IF(E8="Controlled exception","Controlled exception","No sprint outreach")) -> Ready to schedule
A9: A-1008 | B9: =VLOOKUP(A9,Normalized_Accounts!$A$2:$Z$19,2,FALSE()) -> Veridian Charter Schools | C9: =VLOOKUP(A9,Normalized_Accounts!$A$2:$Z$19,5,FALSE()) -> Priya Nair | D9: =VLOOKUP(A9,Scoring!$A$2:$N$19,14,FALSE()) -> Tier 3 | E9: =VLOOKUP(A9,Normalized_Accounts!$A$2:$Z$19,8,FALSE()) -> Approved execution | F9: =VLOOKUP(A9,Raw_Approval!$A$2:$G$19,4,FALSE()) -> Send reconciled district reach report and renewal summary | G9: =IF(VLOOKUP(A9,Normalized_Accounts!$A$2:$Z$19,21,FALSE())=0,"",VLOOKUP(A9,Normalized_Accounts!$A$2:$Z$19,21,FALSE())) -> RPT-COMP | H9: Julian Pierce | I9: =IF(E9="Approved execution",IF(D9="Tier 1",DATE(2026,7,20),IF(D9="Tier 2",DATE(2026,7,22),DATE(2026,7,24))),"") -> 46227 | J9: =IF(VLOOKUP(A9,Normalized_Accounts!$A$2:$Z$19,25,FALSE())=0,"",VLOOKUP(A9,Normalized_Accounts!$A$2:$Z$19,25,FALSE())) | K9: CASE-7211 | L9: =IF(E9="Approved execution","Ready to schedule",IF(E9="Controlled exception","Controlled exception","No sprint outreach")) -> Ready to schedule
A10: A-1009 | B10: =VLOOKUP(A10,Normalized_Accounts!$A$2:$Z$19,2,FALSE()) -> Copper Trail Hospitality | C10: =VLOOKUP(A10,Normalized_Accounts!$A$2:$Z$19,5,FALSE()) -> Luis Romero | D10: =VLOOKUP(A10,Scoring!$A$2:$N$19,14,FALSE()) -> Tier 2 | E10: =VLOOKUP(A10,Normalized_Accounts!$A$2:$Z$19,8,FALSE()) -> Approved execution | F10: =VLOOKUP(A10,Raw_Approval!$A$2:$G$19,4,FALSE()) -> Confirm package swap and creative approval timeline | G10: =IF(VLOOKUP(A10,Normalized_Accounts!$A$2:$Z$19,21,FALSE())=0,"",VLOOKUP(A10,Normalized_Accounts!$A$2:$Z$19,21,FALSE())) -> SW-PKG | H10: Cora Lind | I10: =IF(E10="Approved execution",IF(D10="Tier 1",DATE(2026,7,20),IF(D10="Tier 2",DATE(2026,7,22),DATE(2026,7,24))),"") -> 46225 | J10: =IF(VLOOKUP(A10,Normalized_Accounts!$A$2:$Z$19,25,FALSE())=0,"",VLOOKUP(A10,Normalized_Accounts!$A$2:$Z$19,25,FALSE())) | K10: CASE-7212 | L10: =IF(E10="Approved execution","Ready to schedule",IF(E10="Controlled exception","Controlled exception","No sprint outreach")) -> Ready to schedule
A11: A-1010 | B11: =VLOOKUP(A11,Normalized_Accounts!$A$2:$Z$19,2,FALSE()) -> Finch Legal Group | C11: =VLOOKUP(A11,Normalized_Accounts!$A$2:$Z$19,5,FALSE()) -> Devon Brooks | D11: =VLOOKUP(A11,Scoring!$A$2:$N$19,14,FALSE()) -> Tier 3 | E11: =VLOOKUP(A11,Normalized_Accounts!$A$2:$Z$19,8,FALSE()) -> Approved execution | F11: =VLOOKUP(A11,Raw_Approval!$A$2:$G$19,4,FALSE()) -> Offer 60-day rate hold without additional credit | G11: =IF(VLOOKUP(A11,Normalized_Accounts!$A$2:$Z$19,21,FALSE())=0,"",VLOOKUP(A11,Normalized_Accounts!$A$2:$Z$19,21,FALSE())) -> RH-60 | H11: Evan Finch | I11: =IF(E11="Approved execution",IF(D11="Tier 1",DATE(2026,7,20),IF(D11="Tier 2",DATE(2026,7,22),DATE(2026,7,24))),"") -> 46227 | J11: =IF(VLOOKUP(A11,Normalized_Accounts!$A$2:$Z$19,25,FALSE())=0,"",VLOOKUP(A11,Normalized_Accounts!$A$2:$Z$19,25,FALSE())) | K11: CASE-7213 | L11: =IF(E11="Approved execution","Ready to schedule",IF(E11="Controlled exception","Controlled exception","No sprint outreach")) -> Ready to schedule
A12: A-1011 | B12: =VLOOKUP(A12,Normalized_Accounts!$A$2:$Z$19,2,FALSE()) -> Solstice Energy Co-op | C12: =VLOOKUP(A12,Normalized_Accounts!$A$2:$Z$19,5,FALSE()) -> Maya Chen | D12: =VLOOKUP(A12,Scoring!$A$2:$N$19,14,FALSE()) -> Tier 3 | E12: =VLOOKUP(A12,Normalized_Accounts!$A$2:$Z$19,8,FALSE()) -> Approved execution | F12: =VLOOKUP(A12,Raw_Approval!$A$2:$G$19,4,FALSE()) -> Send corrected lift summary and renewal confidence note | G12: =IF(VLOOKUP(A12,Normalized_Accounts!$A$2:$Z$19,21,FALSE())=0,"",VLOOKUP(A12,Normalized_Accounts!$A$2:$Z$19,21,FALSE())) -> RPT-COMP | H12: Imani Hart | I12: =IF(E12="Approved execution",IF(D12="Tier 1",DATE(2026,7,20),IF(D12="Tier 2",DATE(2026,7,22),DATE(2026,7,24))),"") -> 46227 | J12: =IF(VLOOKUP(A12,Normalized_Accounts!$A$2:$Z$19,25,FALSE())=0,"",VLOOKUP(A12,Normalized_Accounts!$A$2:$Z$19,25,FALSE())) | K12: CASE-7214 | L12: =IF(E12="Approved execution","Ready to schedule",IF(E12="Controlled exception","Controlled exception","No sprint outreach")) -> Ready to schedule
A13: A-1012 | B13: =VLOOKUP(A13,Normalized_Accounts!$A$2:$Z$19,2,FALSE()) -> Vesta Apparel Collective | C13: =VLOOKUP(A13,Normalized_Accounts!$A$2:$Z$19,5,FALSE()) -> Jordan Patel | D13: =VLOOKUP(A13,Scoring!$A$2:$N$19,14,FALSE()) -> Tier 2 | E13: =VLOOKUP(A13,Normalized_Accounts!$A$2:$Z$19,8,FALSE()) -> Approved execution | F13: =VLOOKUP(A13,Raw_Approval!$A$2:$G$19,4,FALSE()) -> Confirm makegood placement and invoice correction route | G13: =IF(VLOOKUP(A13,Normalized_Accounts!$A$2:$Z$19,21,FALSE())=0,"",VLOOKUP(A13,Normalized_Accounts!$A$2:$Z$19,21,FALSE())) -> MG-15 | H13: Marta Ruiz | I13: =IF(E13="Approved execution",IF(D13="Tier 1",DATE(2026,7,20),IF(D13="Tier 2",DATE(2026,7,22),DATE(2026,7,24))),"") -> 46225 | J13: =IF(VLOOKUP(A13,Normalized_Accounts!$A$2:$Z$19,25,FALSE())=0,"",VLOOKUP(A13,Normalized_Accounts!$A$2:$Z$19,25,FALSE())) | K13: CASE-7215 | L13: =IF(E13="Approved execution","Ready to schedule",IF(E13="Controlled exception","Controlled exception","No sprint outreach")) -> Ready to schedule
... A19: A-1018 | B19: =VLOOKUP(A19,Normalized_Accounts!$A$2:$Z$19,2,FALSE()) -> Pinyon Outdoor Media Buyers | C19: =VLOOKUP(A19,Normalized_Accounts!$A$2:$Z$19,5,FALSE()) -> Priya Nair | D19: =VLOOKUP(A19,Scoring!$A$2:$N$19,14,FALSE()) -> Controlled exception/hold | E19: =VLOOKUP(A19,Normalized_Accounts!$A$2:$Z$19,8,FALSE()) -> Excluded - no action | F19: =VLOOKUP(A19,Raw_Approval!$A$2:$G$19,4,FALSE()) -> Hold for September agency review | G19: =IF(VLOOKUP(A19,Normalized_Accounts!$A$2:$Z$19,21,FALSE())=0,"",VLOOKUP(A19,Normalized_Accounts!$A$2:$Z$19,21,FALSE())) | H19: Morgan Price | I19: =IF(E19="Approved execution",IF(D19="Tier 1",DATE(2026,7,20),IF(D19="Tier 2",DATE(2026,7,22),DATE(2026,7,24))),"") | J19: =IF(VLOOKUP(A19,Normalized_Accounts!$A$2:$Z$19,25,FALSE())=0,"",VLOOKUP(A19,Normalized_Accounts!$A$2:$Z$19,25,FALSE())) -> Customer requested September review | K19: CASE-7223 | L19: =IF(E19="Approved execution","Ready to schedule",IF(E19="Controlled exception","Controlled exception","No sprint outreach")) -> No sprint outreach

Sheet Checks
A1: Check | B1: Formula | C1: Expected | D1: Status
A2: Account population | B2: =COUNTA(Normalized_Accounts!$A$2:$A$19) -> 18 | C2: 18 | D2: =IF(B2=C2,"Pass","Review") -> Pass
A3: Approved execution count | B3: =COUNTIF(Normalized_Accounts!$H$2:$H$19,"Approved execution") -> 12 | C3: 12 | D3: =IF(B3=C3,"Pass","Review") -> Pass
A4: Controlled exception count | B4: =COUNTIF(Normalized_Accounts!$H$2:$H$19,"Controlled exception") -> 4 | C4: 4 | D4: =IF(B4=C4,"Pass","Review") -> Pass
A5: Excluded no-action count | B5: =COUNTIF(Normalized_Accounts!$H$2:$H$19,"Excluded*") -> 2 | C5: 2 | D5: =IF(B5=C5,"Pass","Review") -> Pass
A6: Weight total | B6: =SUM(Assumptions!$B$2:$B$6) -> 1 | C6: 1 | D6: =IF(ABS(B6-C6)<0.0001,"Pass","Review") -> Pass
A7: Over-limit local offers | B7: =COUNTIFS(Normalized_Accounts!$X$2:$X$19,"Over limit") -> 0 | C7: 0 | D7: =IF(B7=C7,"Pass","Review") -> Pass
A8: Rank uniqueness | B8: =SUMPRODUCT(1/COUNTIF(Scoring!$M$2:$M$19,Scoring!$M$2:$M$19)) -> 18 | C8: 18 | D8: =IF(B8=C8,"Pass","Review") -> Pass
A9: Executable exposure | B9: =SUMIFS(Normalized_Accounts!$I$2:$I$19,Normalized_Accounts!$H$2:$H$19,"Approved execution") -> 2612000 | C9: 2612000 | D9: =IF(B9=C9,"Pass","Review") -> Pass
A10: Total forecast variance | B10: =SUM(Normalized_Accounts!$L$2:$L$19) -> -557000 | C10: -557000 | D10: =IF(B10=C10,"Pass","Review") -> Pass

Sheet Chart_Data
A1: Priority Tier | B1: Commit at risk | C1: Best case | D1: Pipeline
A2: Tier 1 | B2: 750000 | C2: 0 | D2: 0
A3: Tier 2 | B3: 860000 | C3: 190000 | D3: 0
A4: Tier 3 | B4: 0 | C4: 545000 | D4: 267000
A5: Controlled exception/hold | B5: 0 | C5: 0 | D5: 0
A8: Segment | B8: Forecast Variance | C8: Variance decline | D8: Variance improvement | E8: Account | F8: Issue Age | G8: Severity | H8: Exposure
A9: Agency | B9: =SUMIFS(Normalized_Accounts!$L$2:$L$19,Normalized_Accounts!$C$2:$C$19,A9) -> -6000 | C9: =IF($B9<0,$B9,0) -> -6000 | D9: =IF($B9>0,$B9,0) -> 0 | E9: Meridian Health Partners | F9: 19 | G9: 4 | H9: 340000
A10: Education | B10: =SUMIFS(Normalized_Accounts!$L$2:$L$19,Normalized_Accounts!$C$2:$C$19,A10) -> -10000 | C10: =IF($B10<0,$B10,0) -> -10000 | D10: =IF($B10>0,$B10,0) -> 0 | E10: Larkspur Credit Union | F10: 17 | G10: 4 | H10: 220000
A11: Energy | B11: =SUMIFS(Normalized_Accounts!$L$2:$L$19,Normalized_Accounts!$C$2:$C$19,A11) -> -20000 | C11: =IF($B11<0,$B11,0) -> -20000 | D11: =IF($B11>0,$B11,0) -> 0 | E11: Cobalt Cloud Systems | F11: 17 | G11: 4 | H11: 295000
A12: Financial Services | B12: =SUMIFS(Normalized_Accounts!$L$2:$L$19,Normalized_Accounts!$C$2:$C$19,A12) -> -121000 | C12: =IF($B12<0,$B12,0) -> -121000 | D12: =IF($B12>0,$B12,0) -> 0 | E12: Harborview Furnishings | F12: 14 | G12: 3 | H12: 150000
A13: Healthcare | B13: =SUMIFS(Normalized_Accounts!$L$2:$L$19,Normalized_Accounts!$C$2:$C$19,A13) -> -160000 | C13: =IF($B13<0,$B13,0) -> -160000 | D13: =IF($B13>0,$B13,0) -> 0 | E13: Axion Robotics | F13: 23 | G13: 5 | H13: 410000
A14: Industrial | B14: =SUMIFS(Normalized_Accounts!$L$2:$L$19,Normalized_Accounts!$C$2:$C$19,A14) -> -110000 | C14: =IF($B14<0,$B14,0) -> -110000 | D14: =IF($B14>0,$B14,0) -> 0 | E14: Greenway Kitchens | F14: 10 | G14: 3 | H14: 82000
A15: Local Services | B15: =SUMIFS(Normalized_Accounts!$L$2:$L$19,Normalized_Accounts!$C$2:$C$19,A15) -> 2000 | C15: =IF($B15<0,$B15,0) -> 0 | D15: =IF($B15>0,$B15,0) -> 2000 | E15: Northline Insurance | F15: 23 | G15: 4 | H15: 260000
A16: Professional Services | B16: =SUMIFS(Normalized_Accounts!$L$2:$L$19,Normalized_Accounts!$C$2:$C$19,A16) -> -2000 | C16: =IF($B16<0,$B16,0) -> -2000 | D16: =IF($B16>0,$B16,0) -> 0 | E16: Veridian Charter Schools | F16: 9 | G16: 3 | H16: 110000
A17: Retail | B17: =SUMIFS(Normalized_Accounts!$L$2:$L$19,Normalized_Accounts!$C$2:$C$19,A17) -> -70000 | C17: =IF($B17<0,$B17,0) -> -70000 | D17: =IF($B17>0,$B17,0) -> 0 | E17: Copper Trail Hospitality | F17: 20 | G17: 4 | H17: 190000
A18: Technology | B18: =SUMIFS(Normalized_Accounts!$L$2:$L$19,Normalized_Accounts!$C$2:$C$19,A18) -> -35000 | C18: =IF($B18<0,$B18,0) -> -35000 | D18: =IF($B18>0,$B18,0) -> 0 | E18: Finch Legal Group | F18: 5 | G18: 2 | H18: 75000
A19: Travel | B19: =SUMIFS(Normalized_Accounts!$L$2:$L$19,Normalized_Accounts!$C$2:$C$19,A19) -> -25000 | C19: =IF($B19<0,$B19,0) -> -25000 | D19: =IF($B19>0,$B19,0) -> 0 | E19: Solstice Energy Co-op | F19: 18 | G19: 4 | H19: 175000
E20: Vesta Apparel Collective | F20: 20 | G20: 5 | H20: 305000
E21: BrightPath Dental Alliance | F21: 12 | G21: 3 | H21: 165000
E22: SummitBank SMB Services | F22: 33 | G22: 5 | H22: 360000
E23: Mesa Tool Supply | F23: 21 | G23: 4 | H23: 210000
E24: Riverstone Fitness | F24: 0 | G24: 0 | H24: 62000
E25: Atlas BioLabs | F25: 29.5 | G25: 5 | H25: 520000
E26: Pinyon Outdoor Media Buyers | F26: 6 | G26: 2 | H26: 135000
A31: Owner Rep | B31: Tier 1 Accounts | C31: Scheduled Tasks | D31: Available Slots | G31: Priority Tier | H31: Ready | I31: Ops route only | J31: Pending or manager
A32: Devon Brooks | B32: 1 | C32: 4 | D32: 8 | G32: Tier 1 | H32: 2 | I32: 0 | J32: 0
A33: Jordan Patel | B33: 0 | C33: 6 | D33: 8 | G33: Tier 2 | H33: 4 | I33: 0 | J33: 0
A34: Luis Romero | B34: 0 | C34: 4 | D34: 8 | G34: Tier 3 | H34: 6 | I34: 0 | J34: 0
A35: Maya Chen | B35: 1 | C35: 6 | D35: 8 | G35: Controlled exception/hold | H35: 3 | I35: 1 | J35: 2
A36: Priya Nair | B36: 0 | C36: 4 | D36: 8
A45: Issue Type | B45: Within Authority | C45: Controlled | F45: Age Bucket | G45: Devon Brooks | H45: Jordan Patel | I45: Luis Romero | J45: Maya Chen | K45: Priya Nair
A46: Agency Consolidation | B46: 0 | C46: 1 | F46: 0-3 days | G46: 1 | H46: 2 | I46: 2 | J46: 1 | K46: 0
A47: Audience Mismatch | B47: 1 | C47: 0 | F47: 4-7 days | G47: 1 | H47: 0 | I47: 0 | J47: 0 | K47: 0
A48: Billing Error | B48: 2 | C48: 1 | F48: 8-14 days | G48: 0 | H48: 0 | I48: 0 | J48: 0 | K48: 0
A49: Creative Trafficking | B49: 2 | C49: 0 | F49: 15+ days | G49: 0 | H49: 0 | I49: 0 | J49: 0 | K49: 0
A50: Data-Use Terms | B50: 0 | C50: 1
A51: Delivery Underpacing | B51: 3 | C51: 1
A52: Product Feed Blocker | B52: 0 | C52: 1
A53: Renewal Rate Objection | B53: 1 | C53: 0
A54: Reporting Discrepancy | B54: 3 | C54: 0
A58: Account | B58: Renewal Exposure | C58: Recovery Risk | D58: Priority Score | E58: Priority Route | F58: Segment
A59: A-1001 | B59: =Normalized_Accounts!I2 -> 340000 | C59: =Scoring!K2 -> 58.64 | D59: =Scoring!L2 -> 77.924 | E59: =IF(Scoring!$N$2="Controlled exception/hold",IF(Normalized_Accounts!$H$2="Controlled exception","Controlled exception","Excluded/hold"),Scoring!$N$2) -> Tier 1 | F59: =Normalized_Accounts!$C$2 -> Healthcare
A60: A-1002 | B60: =Normalized_Accounts!I3 -> 220000 | C60: =Scoring!K3 -> 46.22 | D60: =Scoring!L3 -> 58.727 | E60: =IF(Scoring!$N$3="Controlled exception/hold",IF(Normalized_Accounts!$H$3="Controlled exception","Controlled exception","Excluded/hold"),Scoring!$N$3) -> Tier 3 | F60: =Normalized_Accounts!$C$3 -> Financial Services
A61: A-1003 | B61: =Normalized_Accounts!I4 -> 295000 | C61: =Scoring!K4 -> 49.12 | D61: =Scoring!L4 -> 66.067 | E61: =IF(Scoring!$N$4="Controlled exception/hold",IF(Normalized_Accounts!$H$4="Controlled exception","Controlled exception","Excluded/hold"),Scoring!$N$4) -> Tier 2 | F61: =Normalized_Accounts!$C$4 -> Technology
A62: A-1004 | B62: =Normalized_Accounts!I5 -> 150000 | C62: =Scoring!K5 -> 45.99 | D62: =Scoring!L5 -> 57.9965 | E62: =IF(Scoring!$N$5="Controlled exception/hold",IF(Normalized_Accounts!$H$5="Controlled exception","Controlled exception","Excluded/hold"),Scoring!$N$5) -> Tier 3 | F62: =Normalized_Accounts!$C$5 -> Retail
A63: A-1005 | B63: =Normalized_Accounts!I6 -> 410000 | C63: =Scoring!K6 -> 65.98 | D63: =Scoring!L6 -> 81.693 | E63: =IF(Scoring!$N$6="Controlled exception/hold",IF(Normalized_Accounts!$H$6="Controlled exception","Controlled exception","Excluded/hold"),Scoring!$N$6) -> Tier 1 | F63: =Normalized_Accounts!$C$6 -> Industrial
A64: A-1006 | B64: =Normalized_Accounts!I7 -> 82000 | C64: =Scoring!K7 -> 32.6 | D64: =Scoring!L7 -> 47.81 | E64: =IF(Scoring!$N$7="Controlled exception/hold",IF(Normalized_Accounts!$H$7="Controlled exception","Controlled exception","Excluded/hold"),Scoring!$N$7) -> Tier 3 | F64: =Normalized_Accounts!$C$7 -> Retail
A65: A-1007 | B65: =Normalized_Accounts!I8 -> 260000 | C65: =Scoring!K8 -> 56.58 | D65: =Scoring!L8 -> 66.303 | E65: =IF(Scoring!$N$8="Controlled exception/hold",IF(Normalized_Accounts!$H$8="Controlled exception","Controlled exception","Excluded/hold"),Scoring!$N$8) -> Tier 2 | F65: =Normalized_Accounts!$C$8 -> Financial Services
A66: A-1008 | B66: =Normalized_Accounts!I9 -> 110000 | C66: =Scoring!K9 -> 34.49 | D66: =Scoring!L9 -> 40.8215 | E66: =IF(Scoring!$N$9="Controlled exception/hold",IF(Normalized_Accounts!$H$9="Controlled exception","Controlled exception","Excluded/hold"),Scoring!$N$9) -> Tier 3 | F66: =Normalized_Accounts!$C$9 -> Education
A67: A-1009 | B67: =Normalized_Accounts!I10 -> 190000 | C67: =Scoring!K10 -> 53.2 | D67: =Scoring!L10 -> 64.12 | E67: =IF(Scoring!$N$10="Controlled exception/hold",IF(Normalized_Accounts!$H$10="Controlled exception","Controlled exception","Excluded/hold"),Scoring!$N$10) -> Tier 2 | F67: =Normalized_Accounts!$C$10 -> Travel
A68: A-1010 | B68: =Normalized_Accounts!I11 -> 75000 | C68: =Scoring!K11 -> 25.6 | D68: =Scoring!L11 -> 34.685 | E68: =IF(Scoring!$N$11="Controlled exception/hold",IF(Normalized_Accounts!$H$11="Controlled exception","Controlled exception","Excluded/hold"),Scoring!$N$11) -> Tier 3 | F68: =Normalized_Accounts!$C$11 -> Professional Services
A69: A-1011 | B69: =Normalized_Accounts!I12 -> 175000 | C69: =Scoring!K12 -> 45.53 | D69: =Scoring!L12 -> 55.0605 | E69: =IF(Scoring!$N$12="Controlled exception/hold",IF(Normalized_Accounts!$H$12="Controlled exception","Controlled exception","Excluded/hold"),Scoring!$N$12) -> Tier 3 | F69: =Normalized_Accounts!$C$12 -> Energy
A70: A-1012 | B70: =Normalized_Accounts!I13 -> 305000 | C70: =Scoring!K13 -> 63.35 | D70: =Scoring!L13 -> 72.6475 | E70: =IF(Scoring!$N$13="Controlled exception/hold",IF(Normalized_Accounts!$H$13="Controlled exception","Controlled exception","Excluded/hold"),Scoring!$N$13) -> Tier 2 | F70: =Normalized_Accounts!$C$13 -> Retail
A71: A-1013 | B71: =Normalized_Accounts!I14 -> 165000 | C71: =Scoring!K14 -> 37.47 | D71: =Scoring!L14 -> 42.0895 | E71: =IF(Scoring!$N$14="Controlled exception/hold",IF(Normalized_Accounts!$H$14="Controlled exception","Controlled exception","Excluded/hold"),Scoring!$N$14) -> Controlled exception | F71: =Normalized_Accounts!$C$14 -> Healthcare
A72: A-1014 | B72: =Normalized_Accounts!I15 -> 360000 | C72: =Scoring!K15 -> 57.48 | D72: =Scoring!L15 -> 75.118 | E72: =IF(Scoring!$N$15="Controlled exception/hold",IF(Normalized_Accounts!$H$15="Controlled exception","Controlled exception","Excluded/hold"),Scoring!$N$15) -> Controlled exception | F72: =Normalized_Accounts!$C$15 -> Financial Services
A73: A-1015 | B73: =Normalized_Accounts!I16 -> 210000 | C73: =Scoring!K16 -> 57.71 | D73: =Scoring!L16 -> 62.8485 | E73: =IF(Scoring!$N$16="Controlled exception/hold",IF(Normalized_Accounts!$H$16="Controlled exception","Controlled exception","Excluded/hold"),Scoring!$N$16) -> Controlled exception | F73: =Normalized_Accounts!$C$16 -> Industrial
A74: A-1016 | B74: =Normalized_Accounts!I17 -> 62000 | C74: =Scoring!K17 -> 10.4 | D74: =Scoring!L17 -> 38.39 | E74: =IF(Scoring!$N$17="Controlled exception/hold",IF(Normalized_Accounts!$H$17="Controlled exception","Controlled exception","Excluded/hold"),Scoring!$N$17) -> Excluded/hold | F74: =Normalized_Accounts!$C$17 -> Local Services
A75: A-1017 | B75: =Normalized_Accounts!I18 -> 520000 | C75: =Scoring!K18 -> 61.5 | D75: =Scoring!L18 -> 68.525 | E75: =IF(Scoring!$N$18="Controlled exception/hold",IF(Normalized_Accounts!$H$18="Controlled exception","Controlled exception","Excluded/hold"),Scoring!$N$18) -> Controlled exception | F75: =Normalized_Accounts!$C$18 -> Healthcare
A76: A-1018 | B76: =Normalized_Accounts!I19 -> 135000 | C76: =Scoring!K19 -> 27.36 | D76: =Scoring!L19 -> 25.001 | E76: =IF(Scoring!$N$19="Controlled exception/hold",IF(Normalized_Accounts!$H$19="Controlled exception","Controlled exception","Excluded/hold"),Scoring!$N$19) -> Excluded/hold | F76: =Normalized_Accounts!$C$19 -> Agency
A80: Tier 1 matrix source | B80: Renewal Exposure | C80: Recovery Risk | D80: Segment
A81: =Chart_Data!$A$59 -> A-1001 | B81: =Chart_Data!$B$59 -> 340000 | C81: =Chart_Data!$C$59 -> 58.64 | D81: =Chart_Data!$F$59 -> Healthcare
A82: =Chart_Data!$A$63 -> A-1005 | B82: =Chart_Data!$B$63 -> 410000 | C82: =Chart_Data!$C$63 -> 65.98 | D82: =Chart_Data!$F$63 -> Industrial
A84: Tier 2 matrix source | B84: Renewal Exposure | C84: Recovery Risk | D84: Segment
A85: =Chart_Data!$A$61 -> A-1003 | B85: =Chart_Data!$B$61 -> 295000 | C85: =Chart_Data!$C$61 -> 49.12 | D85: =Chart_Data!$F$61 -> Technology
A86: =Chart_Data!$A$65 -> A-1007 | B86: =Chart_Data!$B$65 -> 260000 | C86: =Chart_Data!$C$65 -> 56.58 | D86: =Chart_Data!$F$65 -> Financial Services
A87: =Chart_Data!$A$67 -> A-1009 | B87: =Chart_Data!$B$67 -> 190000 | C87: =Chart_Data!$C$67 -> 53.2 | D87: =Chart_Data!$F$67 -> Travel
A88: =Chart_Data!$A$70 -> A-1012 | B88: =Chart_Data!$B$70 -> 305000 | C88: =Chart_Data!$C$70 -> 63.35 | D88: =Chart_Data!$F$70 -> Retail
A90: Tier 3 matrix source | B90: Renewal Exposure | C90: Recovery Risk | D90: Segment
A91: =Chart_Data!$A$60 -> A-1002 | B91: =Chart_Data!$B$60 -> 220000 | C91: =Chart_Data!$C$60 -> 46.22 | D91: =Chart_Data!$F$60 -> Financial Services
A92: =Chart_Data!$A$62 -> A-1004 | B92: =Chart_Data!$B$62 -> 150000 | C92: =Chart_Data!$C$62 -> 45.99 | D92: =Chart_Data!$F$62 -> Retail
A93: =Chart_Data!$A$64 -> A-1006 | B93: =Chart_Data!$B$64 -> 82000 | C93: =Chart_Data!$C$64 -> 32.6 | D93: =Chart_Data!$F$64 -> Retail
A94: =Chart_Data!$A$66 -> A-1008 | B94: =Chart_Data!$B$66 -> 110000 | C94: =Chart_Data!$C$66 -> 34.49 | D94: =Chart_Data!$F$66 -> Education
A95: =Chart_Data!$A$68 -> A-1010 | B95: =Chart_Data!$B$68 -> 75000 | C95: =Chart_Data!$C$68 -> 25.6 | D95: =Chart_Data!$F$68 -> Professional Services
A96: =Chart_Data!$A$69 -> A-1011 | B96: =Chart_Data!$B$69 -> 175000 | C96: =Chart_Data!$C$69 -> 45.53 | D96: =Chart_Data!$F$69 -> Energy
A98: Controlled exception matrix source | B98: Renewal Exposure | C98: Recovery Risk | D98: Segment
A99: =Chart_Data!$A$71 -> A-1013 | B99: =Chart_Data!$B$71 -> 165000 | C99: =Chart_Data!$C$71 -> 37.47 | D99: =Chart_Data!$F$71 -> Healthcare
A100: =Chart_Data!$A$72 -> A-1014 | B100: =Chart_Data!$B$72 -> 360000 | C100: =Chart_Data!$C$72 -> 57.48 | D100: =Chart_Data!$F$72 -> Financial Services
A101: =Chart_Data!$A$73 -> A-1015 | B101: =Chart_Data!$B$73 -> 210000 | C101: =Chart_Data!$C$73 -> 57.71 | D101: =Chart_Data!$F$73 -> Industrial
A102: =Chart_Data!$A$75 -> A-1017 | B102: =Chart_Data!$B$75 -> 520000 | C102: =Chart_Data!$C$75 -> 61.5 | D102: =Chart_Data!$F$75 -> Healthcare
A104: Excluded/hold matrix source | B104: Renewal Exposure | C104: Recovery Risk | D104: Segment
A105: =Chart_Data!$A$74 -> A-1016 | B105: =Chart_Data!$B$74 -> 62000 | C105: =Chart_Data!$C$74 -> 10.4 | D105: =Chart_Data!$F$74 -> Local Services
A106: =Chart_Data!$A$76 -> A-1018 | B106: =Chart_Data!$B$76 -> 135000 | C106: =Chart_Data!$C$76 -> 27.36 | D106: =Chart_Data!$F$76 -> Agency

Sheet Dashboard
A1: Portfolio prioritization dashboard
A2: Approved actions execute locally; exceptions remain controlled.

Sheet Forecast Impact
A1: Waterfall-style variance: negative segment impacts fall below baseline; positive movement rises above zero.

Sheet Priority Analysis

Sheet Coverage

Sheet Compliance
