Workbook

Sheet Workability Board
A1: Northstar Sprint Workability Board
A2: The control decision comes before risk priority: approved desk work, customer release, controlled exceptions, and holds are separate lanes.
A4: Control Lane | B4: Current Count | C4: Account IDs | D4: Can the Desk Work It Now? | E4: Can the Rep Contact the Customer Now? | F4: Release Rule | G4: Owner | H4: Control Note
A5: WORK NOW — CLEAR / PREPARE | B5: 12 | C5: A-1001, A-1002, A-1003, A-1004, A-1005, A-1006, A-1007, A-1008, A-1009, A-1010, A-1011, A-1012 | D5: Yes — supervisor and owner rep may complete the named evidence and prepare the approved action. | E5: No accounts are customer-ready in the supplied evidence snapshot. | F5: Customer contact only after all four row-level source controls calculate a Cleared release. | G5: Dana Morales | H5: These accounts are approved for local execution; rank applies only inside this lane.
A6: CUSTOMER-READY NOW | B6: =COUNTIF('Approved Work Queue'!V5:V16,"Cleared") | C6: See Cleared Contact Path | D6: Only accounts displayed on Cleared Contact Path are released for dated contact. | E6: Only after Release Status calculates Cleared | F6: Current case exports show an open dependency, missing confirmation, or required deliverable for every approved row at package creation. | G6: Dana Morales | H6: Reassess from current owner evidence at sprint launch; do not infer clearance from an expected date.
A7: CONTROLLED EXCEPTION | B7: 4 | C7: A-1013, A-1014, A-1015, A-1017 | D7: Internal escalation only. | E7: No local commitment | F7: Named manager, legal, contact-route, or operational owner must approve a route. | G7: Dana Morales | H7: These accounts are physically separated from the work-now queue and carry no execution rank.
A8: EXCLUDED / HOLD | B8: 2 | C8: A-1016, A-1018 | D8: Recordkeeping or future scheduling only. | E8: No | F8: A-1016 remains closed; A-1018 remains held for the September agency review. | G8: Dana Morales | H8: No July recovery outreach.
A11: How an account becomes customer-ready
A12: 1. The July 15 email must name the account for local execution and support the package lane.
A13: 2. The directory must show an approved contact route, and the authority matrix must support the exact offer, tier, and value.
A14: 3. The operational or billing owner supplies the exact evidence named in Required Evidence Gate; Dana marks only Case Evidence Support.
A15: 4. Release Status calculates Cleared only when all four source controls are Supported; only then may the rep make customer contact.
A16: 5. A failed control moves to Controlled Exceptions with a named owner and decision date—it is never pushed down the ranking.

Sheet Sprint Control
A1: Northstar July Recovery Sprint — Supervisor Work Package
A2: One controlled package for local execution, exceptions, holds, daily checkpoints, and closeout.
A4: Supervisor owner | B4: Dana Morales | C4: Approval source | D4: Elena Whitaker — July 15 approval
A5: Execution window | B5: 2026-07-17 through 2026-07-24 | C5: Daily checkpoint | D5: 16:00 Eastern
A6: Approved local execution | B6: 12 | C6: Controlled exceptions | D6: 4
A7: Excluded / hold | B7: 2 | C7: Operating rule | D7: A planned date never overrides an uncleared evidence gate.
A10: Supervisor operating sequence
A11: 1 | B11: Gate | C11: Confirm the required case evidence is attached; update only Case Evidence Support.
A12: 2 | B12: Authorize | C12: Confirm offer code, tier, requested value, contact route, and customer language.
A13: 3 | B13: Assign | C13: Release the row to the owner rep only after the first two checks pass.
A14: 4 | B14: Checkpoint | C14: Update outreach status, note, next step, and next-step due date by 16:00 Eastern.
A15: 5 | B15: Escalate | C15: Move any failed gate to the exception lane; do not improvise a customer promise.
A16: 6 | B16: Close | C16: On July 24 reconcile model decision, outreach result, open exceptions, and forecast-risk change.
A19: Scope and authority guardrails
A20: • Use only MG-15, CR-10K, RH-60, SW-PKG, or RPT-COMP where the account row passes its authority check.
A21: • Do not promise future performance, unverified credits, new product terms, legal terms, or an uncleared operational action.
A22: • MGR-REQ is an escalation route, not a customer offer.
A23: • Cobalt Cloud (A-1003): local authority covers the verified CR-10K credit only; RH-60 is not eligible for Key Growth.

Sheet Approved Work Queue
A1: Approved Local Execution Queue
A2: Release is formula-controlled: approval email + contact route + case evidence + offer authority must all support the exact action.
A4: Desk Work Lane | B4: Execution Rank | C4: Conditional Contact Target | D4: Account ID | E4: Account Name | F4: Owner Rep | G4: Supervisor | H4: Renewal Date | I4: Days to Renewal | J4: Renewal Exposure | K4: Forecast Variance | L4: Priority Score | M4: Primary Issue | N4: Case IDs | O4: Operational Owner(s) | P4: Expected Clearance | Q4: Required Evidence Gate | R4: Approval Email Support | S4: Contact Route Support | T4: Case Evidence Support | U4: Offer Authority Support | V4: Release Status | W4: Released Contact Date | X4: Approved Offer | Y4: Authority Limit | Z4: Requested Value | AA4: Authority Check | AB4: Approved Contact | AC4: Contact Role | AD4: Preferred Channel | AE4: Timezone | AF4: Contact Restriction | AG4: Supervisor-Approved Customer Action | AH4: Customer Language Guardrail | AI4: Current Rep Commitment | AJ4: Commitment Due | AK4: Outreach Status | AL4: Checkpoint Note | AM4: Next Step | AN4: Next Step Due
A5: WORK NOW — CLEAR / PREPARE | B5: 1 | C5: 46223 | D5: A-1005 | E5: Axion Robotics | F5: Devon Brooks | G5: Dana Morales | H5: 46246 | I5: =H5-C5 | J5: 410000 | K5: -72000 | L5: 81.7 | M5: Audience Mismatch | N5: CASE-7207, CASE-7208 | O5: Product Support - Ravi Mehta, Ad Ops - Lena Ortiz | P5: 46221 | Q5: Audience rebuild proof and package-swap feasibility confirmed by Product Support / Ad Ops. | R5: Supported — July 15 approval | S5: Supported — Mark Feld / Approved | T5: Pending — evidence not yet confirmed | U5: Supported — SW-PKG / Key Growth / $18,000 | V5: =IF(COUNTIF(R5:U5,"Supported*")=4,"Cleared","Blocked") | W5: =IF(V5="Cleared",C5,"") | X5: SW-PKG | Y5: $18,000 equivalent-value package swap | Z5: 18000 | AA5: Within local authority after gate clears | AB5: Mark Feld | AC5: Final Renewal Approver | AD5: Call | AE5: Central | AF5: Approved; Needs audience proof; Unavailable July 19 | AG5: Swap misaligned audience package and reset delivery proof | AH5: Describe the equivalent-value package swap only after feasibility is documented; do not guarantee future performance. | AI5: Share audience rebuild proof | AJ5: 46214 | AK5: Not started | AM5: Swap misaligned audience package and reset delivery proof | AN5: 46223
A6: WORK NOW — CLEAR / PREPARE | B6: 2 | C6: 46220 | D6: A-1001 | E6: Meridian Health Partners | F6: Maya Chen | G6: Dana Morales | H6: 46227 | I6: =H6-C6 | J6: 340000 | K6: -38000 | L6: 77.9 | M6: Delivery Underpacing | N6: CASE-7201, CASE-7202 | O6: Ad Ops - Lena Ortiz, Reporting - Eli Park | P6: 46219 | Q6: Traffic pacing confirmation and makegood inventory validation attached to CASE-7201. | R6: Supported — July 15 approval | S6: Supported — Dr. Lena Morris / Approved | T6: Pending — evidence not yet confirmed | U6: Supported — MG-15 / Key Growth / $21,000 | V6: =IF(COUNTIF(R6:U6,"Supported*")=4,"Cleared","Blocked") | W6: =IF(V6="Cleared",C6,"") | X6: MG-15 | Y6: $25,000 / up to 15% of affected booked impressions | Z6: 21000 | AA6: Within local authority after gate clears | AB6: Dr. Lena Morris | AC6: Final Renewal Approver | AD6: Email then call | AE6: Eastern | AF6: Approved; Executive expects delivery plan; None | AG6: Confirm makegood inventory and delivery recovery plan | AH6: Describe the validated makegood inventory and revised delivery plan; do not promise unvalidated impressions. | AI6: Send corrected pacing plan | AJ6: 46217 | AK6: Not started | AM6: Confirm makegood inventory and delivery recovery plan | AN6: 46220
A7: WORK NOW — CLEAR / PREPARE | B7: 3 | C7: 46223 | D7: A-1012 | E7: Vesta Apparel Collective | F7: Jordan Patel | G7: Dana Morales | H7: 46235 | I7: =H7-C7 | J7: 305000 | K7: -52000 | L7: 72.6 | M7: Delivery Underpacing | N7: CASE-7215, CASE-7216 | O7: Ad Ops - Lena Ortiz, Billing - Nora Vale | P7: 46221 | Q7: Makegood placement validated and invoice PO correction route documented. | R7: Supported — July 15 approval | S7: Supported — Marta Ruiz / Approved | T7: Pending — evidence not yet confirmed | U7: Supported — MG-15 / Key Growth / $24,000 | V7: =IF(COUNTIF(R7:U7,"Supported*")=4,"Cleared","Blocked") | W7: =IF(V7="Cleared",C7,"") | X7: MG-15 | Y7: $25,000 / up to 15% of affected booked impressions | Z7: 24000 | AA7: Within local authority after gate clears | AB7: Marta Ruiz | AC7: Final Renewal Approver | AD7: Call | AE7: Eastern | AF7: Approved; Finance asks for PO note; Unavailable July 18 | AG7: Confirm makegood placement and invoice correction route | AH7: Describe the validated makegood placement and invoice-correction process; do not combine this with an unapproved credit. | AI7: Send makegood and PO correction note | AJ7: 46215 | AK7: Not started | AM7: Confirm makegood placement and invoice correction route | AN7: 46223
A8: WORK NOW — CLEAR / PREPARE | B8: 4 | C8: 46223 | D8: A-1007 | E8: Northline Insurance | F8: Jordan Patel | G8: Dana Morales | H8: 46237 | I8: =H8-C8 | J8: 260000 | K8: -40000 | L8: 66.3 | M8: Delivery Underpacing | N8: CASE-7210 | O8: Ad Ops - Lena Ortiz | P8: 46220 | Q8: Makegood placement and revised delivery dates confirmed by Ad Ops. | R8: Supported — July 15 approval | S8: Supported — Samira Ahmad / Approved | T8: Pending — evidence not yet confirmed | U8: Supported — MG-15 / Core / $22,000 | V8: =IF(COUNTIF(R8:U8,"Supported*")=4,"Cleared","Blocked") | W8: =IF(V8="Cleared",C8,"") | X8: MG-15 | Y8: $25,000 / up to 15% of affected booked impressions | Z8: 22000 | AA8: Within local authority after gate clears | AB8: Samira Ahmad | AC8: Final Renewal Approver | AD8: Email | AE8: Eastern | AF8: Approved; Legal observer on copy; None | AG8: Confirm makegood placement and revised delivery dates | AH8: Describe the validated underdelivery remedy and dates; do not guarantee future delivery. | AI8: Provide underdelivery remedy | AJ8: 46217 | AK8: Not started | AM8: Confirm makegood placement and revised delivery dates | AN8: 46223
A9: WORK NOW — CLEAR / PREPARE | B9: 5 | C9: 46220 | D9: A-1003 | E9: Cobalt Cloud Systems | F9: Priya Nair | G9: Dana Morales | H9: 46239 | I9: =H9-C9 | J9: 295000 | K9: -35000 | L9: 66.1 | M9: Billing Error | N9: CASE-7204, CASE-7205 | O9: Billing - Nora Vale, Sales Ops - Aaron Kim | P9: 46219 | Q9: Verified credit memo up to $9,500 attached; any rate-hold request removed or separately escalated. | R9: Supported — July 15 approval | S9: Supported — Rafael Soto / Approved | T9: Pending — evidence not yet confirmed | U9: Supported — CR-10K / Key Growth / $9,500 | V9: =IF(COUNTIF(R9:U9,"Supported*")=4,"Cleared","Blocked") | W9: =IF(V9="Cleared",C9,"") | X9: CR-10K | Y9: $10,000 verified invoice credit | Z9: 9500 | AA9: CR-10K only; RH-60 is not eligible for Key Growth | AB9: Rafael Soto | AC9: Final Renewal Approver | AD9: Call | AE9: Pacific | AF9: Approved; Wants billing proof first; Unavailable July 22 AM | AG9: Confirm verified invoice credit only; escalate any rate-hold request | AH9: Discuss only the verified invoice credit under CR-10K. Do not offer a local rate hold because Key Growth is not RH-60 eligible. | AI9: Confirm billing investigation opened | AJ9: 46215 | AK9: Not started | AM9: Confirm verified invoice credit only; escalate any rate-hold request | AN9: 46220
A10: WORK NOW — CLEAR / PREPARE | B10: 6 | C10: 46220 | D10: A-1009 | E10: Copper Trail Hospitality | F10: Luis Romero | G10: Dana Morales | H10: 46232 | I10: =H10-C10 | J10: 190000 | K10: -25000 | L10: 64.1 | M10: Creative Trafficking | N10: CASE-7212 | O10: Ad Ops - Lena Ortiz | P10: 46219 | Q10: Creative approval proof and equivalent package-swap feasibility confirmed by Ad Ops. | R10: Supported — July 15 approval | S10: Supported — Cora Lind / Approved | T10: Pending — evidence not yet confirmed | U10: Supported — SW-PKG / Core / $15,000 | V10: =IF(COUNTIF(R10:U10,"Supported*")=4,"Cleared","Blocked") | W10: =IF(V10="Cleared",C10,"") | X10: SW-PKG | Y10: $18,000 equivalent-value package swap | Z10: 15000 | AA10: Within local authority after gate clears | AB10: Cora Lind | AC10: Final Renewal Approver | AD10: Call | AE10: Pacific | AF10: Approved; Sensitive to launch dates; Unavailable July 20 PM | AG10: Confirm package swap and creative approval timeline | AH10: Describe the approved equivalent-value swap and confirmed timeline; do not promise launch timing before validation. | AI10: Send brand safety approval path | AJ10: 46216 | AK10: Not started | AM10: Confirm package swap and creative approval timeline | AN10: 46220
A11: WORK NOW — CLEAR / PREPARE | B11: 7 | C11: 46224 | D11: A-1002 | E11: Larkspur Credit Union | F11: Jordan Patel | G11: Dana Morales | H11: 46234 | I11: =H11-C11 | J11: 220000 | K11: -21000 | L11: 58.7 | M11: Reporting Discrepancy | N11: CASE-7203 | O11: Reporting - Eli Park | P11: 46220 | Q11: Corrected reach report and customer-facing reconciliation summary attached. | R11: Supported — July 15 approval | S11: Supported — Tanya Wells / Approved | T11: Pending — evidence not yet confirmed | U11: Supported — RPT-COMP / Core / $0 | V11: =IF(COUNTIF(R11:U11,"Supported*")=4,"Cleared","Blocked") | W11: =IF(V11="Cleared",C11,"") | X11: RPT-COMP | Y11: No credit; reporting reconciliation package | Z11: 0 | AA11: Within local authority after gate clears | AB11: Tanya Wells | AC11: Final Renewal Approver | AD11: Email | AE11: Central | AF11: Approved; Compliance copy required; Avoid Friday after 12:00 | AG11: Deliver reconciled reporting package and executive summary | AH11: Provide the reconciled reporting package; make no commercial or performance promise. | AI11: Provide reconciled reach report | AJ11: 46220 | AK11: Not started | AM11: Deliver reconciled reporting package and executive summary | AN11: 46224
A12: WORK NOW — CLEAR / PREPARE | B12: 8 | C12: 46220 | D12: A-1004 | E12: Harborview Furnishings | F12: Luis Romero | G12: Dana Morales | H12: 46231 | I12: =H12-C12 | J12: 150000 | K12: -13000 | L12: 58 | M12: Creative Trafficking | N12: CASE-7206 | O12: Ad Ops - Lena Ortiz | P12: 46219 | Q12: Creative retagging confirmation and package-swap feasibility documented by Ad Ops. | R12: Supported — July 15 approval | S12: Supported — Nina Cho / Approved | T12: Pending — evidence not yet confirmed | U12: Supported — SW-PKG / Core / $12,000 | V12: =IF(COUNTIF(R12:U12,"Supported*")=4,"Cleared","Blocked") | W12: =IF(V12="Cleared",C12,"") | X12: SW-PKG | Y12: $18,000 equivalent-value package swap | Z12: 12000 | AA12: Within local authority after gate clears | AB12: Nina Cho | AC12: Final Renewal Approver | AD12: Email | AE12: Pacific | AF12: Approved; Creative team must be copied; None | AG12: Offer equivalent package swap after trafficking confirmation | AH12: Describe the approved equivalent-value swap after trafficking confirmation; do not promise timing before validation. | AI12: Send creative retagging ETA | AJ12: 46215 | AK12: Not started | AM12: Offer equivalent package swap after trafficking confirmation | AN12: 46220
A13: WORK NOW — CLEAR / PREPARE | B13: 9 | C13: 46224 | D13: A-1011 | E13: Solstice Energy Co-op | F13: Maya Chen | G13: Dana Morales | H13: 46243 | I13: =H13-C13 | J13: 175000 | K13: -20000 | L13: 55.1 | M13: Reporting Discrepancy | N13: CASE-7214 | O13: Reporting - Eli Park | P13: 46221 | Q13: Corrected lift model and customer-facing summary attached. | R13: Supported — July 15 approval | S13: Supported — Imani Hart / Approved | T13: Pending — evidence not yet confirmed | U13: Supported — RPT-COMP / Core / $0 | V13: =IF(COUNTIF(R13:U13,"Supported*")=4,"Cleared","Blocked") | W13: =IF(V13="Cleared",C13,"") | X13: RPT-COMP | Y13: No credit; reporting reconciliation package | Z13: 0 | AA13: Within local authority after gate clears | AB13: Imani Hart | AC13: Final Renewal Approver | AD13: Email | AE13: Central | AF13: Approved; Procurement copied; None | AG13: Send corrected lift summary and renewal confidence note | AH13: Provide the corrected reporting package; make no commercial or performance promise. | AI13: Send corrected lift summary | AJ13: 46221 | AK13: Not started | AM13: Send corrected lift summary and renewal confidence note | AN13: 46224
A14: WORK NOW — CLEAR / PREPARE | B14: 10 | C14: 46223 | D14: A-1006 | E14: Greenway Kitchens | F14: Maya Chen | G14: Dana Morales | H14: 46229 | I14: =H14-C14 | J14: 82000 | K14: -5000 | L14: 47.8 | M14: Billing Error | N14: CASE-7209 | O14: Billing - Nora Vale | P14: 46220 | Q14: Verified credit memo up to $4,800 and corrected bill date attached. | R14: Supported — July 15 approval | S14: Supported — Gloria Kim / Approved | T14: Pending — evidence not yet confirmed | U14: Supported — CR-10K / Emerging / $4,800 | V14: =IF(COUNTIF(R14:U14,"Supported*")=4,"Cleared","Blocked") | W14: =IF(V14="Cleared",C14,"") | X14: CR-10K | Y14: $10,000 verified invoice credit | Z14: 4800 | AA14: Within local authority after gate clears | AB14: Gloria Kim | AC14: Final Renewal Approver | AD14: SMS then email | AE14: Eastern | AF14: Approved; Prefers concise invoice note; None | AG14: Confirm verified invoice credit and corrected bill date | AH14: Discuss only the verified invoice correction under CR-10K; do not exceed $4,800. | AI14: Send credit memo note | AJ14: 46220 | AK14: Not started | AM14: Confirm verified invoice credit and corrected bill date | AN14: 46223
A15: WORK NOW — CLEAR / PREPARE | B15: 11 | C15: 46224 | D15: A-1008 | E15: Veridian Charter Schools | F15: Priya Nair | G15: Dana Morales | H15: 46249 | I15: =H15-C15 | J15: 110000 | K15: -10000 | L15: 40.8 | M15: Reporting Discrepancy | N15: CASE-7211 | O15: Reporting - Eli Park | P15: 46223 | Q15: Corrected district reach report and renewal summary attached. | R15: Supported — July 15 approval | S15: Supported — Julian Pierce / Approved | T15: Pending — evidence not yet confirmed | U15: Supported — RPT-COMP / Emerging / $0 | V15: =IF(COUNTIF(R15:U15,"Supported*")=4,"Cleared","Blocked") | W15: =IF(V15="Cleared",C15,"") | X15: RPT-COMP | Y15: No credit; reporting reconciliation package | Z15: 0 | AA15: Within local authority after gate clears | AB15: Julian Pierce | AC15: Final Renewal Approver | AD15: Email | AE15: Mountain | AF15: Approved; No vendor calls before report; School board meeting July 23 | AG15: Send reconciled district reach report and renewal summary | AH15: Provide the reconciled district report; make no commercial or performance promise. | AI15: Share district reach report | AJ15: 46223 | AK15: Not started | AM15: Send reconciled district reach report and renewal summary | AN15: 46224
A16: WORK NOW — CLEAR / PREPARE | B16: 12 | C16: 46225 | D16: A-1010 | E16: Finch Legal Group | F16: Devon Brooks | G16: Dana Morales | H16: 46254 | I16: =H16-C16 | J16: 75000 | K16: -2000 | L16: 34.7 | M16: Renewal Rate Objection | N16: CASE-7213 | O16: Sales Ops - Aaron Kim | P16: 46224 | Q16: 60-day CPM hold language documented with no additional credit. | R16: Supported — July 15 approval | S16: Supported — Evan Finch / Approved | T16: Pending — evidence not yet confirmed | U16: Supported — RH-60 / Emerging / $0 | V16: =IF(COUNTIF(R16:U16,"Supported*")=4,"Cleared","Blocked") | W16: =IF(V16="Cleared",C16,"") | X16: RH-60 | Y16: No credit; current CPM held for 60 days | Z16: 0 | AA16: Within local authority after gate clears | AB16: Evan Finch | AC16: Final Renewal Approver | AD16: Email | AE16: Eastern | AF16: Approved; Rate hold only; Court calendar mornings | AG16: Offer 60-day rate hold without additional credit | AH16: Offer only the 60-day current-CPM hold under RH-60; do not add a credit. | AI16: Confirm 60-day rate hold | AJ16: 46224 | AK16: Not started | AM16: Offer 60-day rate hold without additional credit | AN16: 46225

Sheet Cleared Contact Path
A1: Cleared-Only Dated Contact Path
A2: This view populates only when all four source controls calculate Release Status = Cleared. Blocked, controlled, and held accounts cannot appear here.
A4: Released Contact Date | B4: Account ID | C4: Account Name | D4: Owner Rep | E4: Approved Contact | F4: Preferred Channel | G4: Supervisor-Approved Customer Action | H4: Release Status | I4: Outreach Status
A5: =IF('Approved Work Queue'!$V$5="Cleared",'Approved Work Queue'!$W$5,"") | B5: =IF('Approved Work Queue'!$V$5="Cleared",'Approved Work Queue'!$D$5,"") | C5: =IF('Approved Work Queue'!$V$5="Cleared",'Approved Work Queue'!$E$5,"") | D5: =IF('Approved Work Queue'!$V$5="Cleared",'Approved Work Queue'!$F$5,"") | E5: =IF('Approved Work Queue'!$V$5="Cleared",'Approved Work Queue'!$AB$5,"") | F5: =IF('Approved Work Queue'!$V$5="Cleared",'Approved Work Queue'!$AD$5,"") | G5: =IF('Approved Work Queue'!$V$5="Cleared",'Approved Work Queue'!$AG$5,"") | H5: =IF('Approved Work Queue'!$V$5="Cleared",'Approved Work Queue'!$V$5,"") | I5: =IF('Approved Work Queue'!$V$5="Cleared",'Approved Work Queue'!$AK$5,"")
A6: =IF('Approved Work Queue'!$V$6="Cleared",'Approved Work Queue'!$W$6,"") | B6: =IF('Approved Work Queue'!$V$6="Cleared",'Approved Work Queue'!$D$6,"") | C6: =IF('Approved Work Queue'!$V$6="Cleared",'Approved Work Queue'!$E$6,"") | D6: =IF('Approved Work Queue'!$V$6="Cleared",'Approved Work Queue'!$F$6,"") | E6: =IF('Approved Work Queue'!$V$6="Cleared",'Approved Work Queue'!$AB$6,"") | F6: =IF('Approved Work Queue'!$V$6="Cleared",'Approved Work Queue'!$AD$6,"") | G6: =IF('Approved Work Queue'!$V$6="Cleared",'Approved Work Queue'!$AG$6,"") | H6: =IF('Approved Work Queue'!$V$6="Cleared",'Approved Work Queue'!$V$6,"") | I6: =IF('Approved Work Queue'!$V$6="Cleared",'Approved Work Queue'!$AK$6,"")
A7: =IF('Approved Work Queue'!$V$7="Cleared",'Approved Work Queue'!$W$7,"") | B7: =IF('Approved Work Queue'!$V$7="Cleared",'Approved Work Queue'!$D$7,"") | C7: =IF('Approved Work Queue'!$V$7="Cleared",'Approved Work Queue'!$E$7,"") | D7: =IF('Approved Work Queue'!$V$7="Cleared",'Approved Work Queue'!$F$7,"") | E7: =IF('Approved Work Queue'!$V$7="Cleared",'Approved Work Queue'!$AB$7,"") | F7: =IF('Approved Work Queue'!$V$7="Cleared",'Approved Work Queue'!$AD$7,"") | G7: =IF('Approved Work Queue'!$V$7="Cleared",'Approved Work Queue'!$AG$7,"") | H7: =IF('Approved Work Queue'!$V$7="Cleared",'Approved Work Queue'!$V$7,"") | I7: =IF('Approved Work Queue'!$V$7="Cleared",'Approved Work Queue'!$AK$7,"")
A8: =IF('Approved Work Queue'!$V$8="Cleared",'Approved Work Queue'!$W$8,"") | B8: =IF('Approved Work Queue'!$V$8="Cleared",'Approved Work Queue'!$D$8,"") | C8: =IF('Approved Work Queue'!$V$8="Cleared",'Approved Work Queue'!$E$8,"") | D8: =IF('Approved Work Queue'!$V$8="Cleared",'Approved Work Queue'!$F$8,"") | E8: =IF('Approved Work Queue'!$V$8="Cleared",'Approved Work Queue'!$AB$8,"") | F8: =IF('Approved Work Queue'!$V$8="Cleared",'Approved Work Queue'!$AD$8,"") | G8: =IF('Approved Work Queue'!$V$8="Cleared",'Approved Work Queue'!$AG$8,"") | H8: =IF('Approved Work Queue'!$V$8="Cleared",'Approved Work Queue'!$V$8,"") | I8: =IF('Approved Work Queue'!$V$8="Cleared",'Approved Work Queue'!$AK$8,"")
A9: =IF('Approved Work Queue'!$V$9="Cleared",'Approved Work Queue'!$W$9,"") | B9: =IF('Approved Work Queue'!$V$9="Cleared",'Approved Work Queue'!$D$9,"") | C9: =IF('Approved Work Queue'!$V$9="Cleared",'Approved Work Queue'!$E$9,"") | D9: =IF('Approved Work Queue'!$V$9="Cleared",'Approved Work Queue'!$F$9,"") | E9: =IF('Approved Work Queue'!$V$9="Cleared",'Approved Work Queue'!$AB$9,"") | F9: =IF('Approved Work Queue'!$V$9="Cleared",'Approved Work Queue'!$AD$9,"") | G9: =IF('Approved Work Queue'!$V$9="Cleared",'Approved Work Queue'!$AG$9,"") | H9: =IF('Approved Work Queue'!$V$9="Cleared",'Approved Work Queue'!$V$9,"") | I9: =IF('Approved Work Queue'!$V$9="Cleared",'Approved Work Queue'!$AK$9,"")
A10: =IF('Approved Work Queue'!$V$10="Cleared",'Approved Work Queue'!$W$10,"") | B10: =IF('Approved Work Queue'!$V$10="Cleared",'Approved Work Queue'!$D$10,"") | C10: =IF('Approved Work Queue'!$V$10="Cleared",'Approved Work Queue'!$E$10,"") | D10: =IF('Approved Work Queue'!$V$10="Cleared",'Approved Work Queue'!$F$10,"") | E10: =IF('Approved Work Queue'!$V$10="Cleared",'Approved Work Queue'!$AB$10,"") | F10: =IF('Approved Work Queue'!$V$10="Cleared",'Approved Work Queue'!$AD$10,"") | G10: =IF('Approved Work Queue'!$V$10="Cleared",'Approved Work Queue'!$AG$10,"") | H10: =IF('Approved Work Queue'!$V$10="Cleared",'Approved Work Queue'!$V$10,"") | I10: =IF('Approved Work Queue'!$V$10="Cleared",'Approved Work Queue'!$AK$10,"")
A11: =IF('Approved Work Queue'!$V$11="Cleared",'Approved Work Queue'!$W$11,"") | B11: =IF('Approved Work Queue'!$V$11="Cleared",'Approved Work Queue'!$D$11,"") | C11: =IF('Approved Work Queue'!$V$11="Cleared",'Approved Work Queue'!$E$11,"") | D11: =IF('Approved Work Queue'!$V$11="Cleared",'Approved Work Queue'!$F$11,"") | E11: =IF('Approved Work Queue'!$V$11="Cleared",'Approved Work Queue'!$AB$11,"") | F11: =IF('Approved Work Queue'!$V$11="Cleared",'Approved Work Queue'!$AD$11,"") | G11: =IF('Approved Work Queue'!$V$11="Cleared",'Approved Work Queue'!$AG$11,"") | H11: =IF('Approved Work Queue'!$V$11="Cleared",'Approved Work Queue'!$V$11,"") | I11: =IF('Approved Work Queue'!$V$11="Cleared",'Approved Work Queue'!$AK$11,"")
A12: =IF('Approved Work Queue'!$V$12="Cleared",'Approved Work Queue'!$W$12,"") | B12: =IF('Approved Work Queue'!$V$12="Cleared",'Approved Work Queue'!$D$12,"") | C12: =IF('Approved Work Queue'!$V$12="Cleared",'Approved Work Queue'!$E$12,"") | D12: =IF('Approved Work Queue'!$V$12="Cleared",'Approved Work Queue'!$F$12,"") | E12: =IF('Approved Work Queue'!$V$12="Cleared",'Approved Work Queue'!$AB$12,"") | F12: =IF('Approved Work Queue'!$V$12="Cleared",'Approved Work Queue'!$AD$12,"") | G12: =IF('Approved Work Queue'!$V$12="Cleared",'Approved Work Queue'!$AG$12,"") | H12: =IF('Approved Work Queue'!$V$12="Cleared",'Approved Work Queue'!$V$12,"") | I12: =IF('Approved Work Queue'!$V$12="Cleared",'Approved Work Queue'!$AK$12,"")
A13: =IF('Approved Work Queue'!$V$13="Cleared",'Approved Work Queue'!$W$13,"") | B13: =IF('Approved Work Queue'!$V$13="Cleared",'Approved Work Queue'!$D$13,"") | C13: =IF('Approved Work Queue'!$V$13="Cleared",'Approved Work Queue'!$E$13,"") | D13: =IF('Approved Work Queue'!$V$13="Cleared",'Approved Work Queue'!$F$13,"") | E13: =IF('Approved Work Queue'!$V$13="Cleared",'Approved Work Queue'!$AB$13,"") | F13: =IF('Approved Work Queue'!$V$13="Cleared",'Approved Work Queue'!$AD$13,"") | G13: =IF('Approved Work Queue'!$V$13="Cleared",'Approved Work Queue'!$AG$13,"") | H13: =IF('Approved Work Queue'!$V$13="Cleared",'Approved Work Queue'!$V$13,"") | I13: =IF('Approved Work Queue'!$V$13="Cleared",'Approved Work Queue'!$AK$13,"")
A14: =IF('Approved Work Queue'!$V$14="Cleared",'Approved Work Queue'!$W$14,"") | B14: =IF('Approved Work Queue'!$V$14="Cleared",'Approved Work Queue'!$D$14,"") | C14: =IF('Approved Work Queue'!$V$14="Cleared",'Approved Work Queue'!$E$14,"") | D14: =IF('Approved Work Queue'!$V$14="Cleared",'Approved Work Queue'!$F$14,"") | E14: =IF('Approved Work Queue'!$V$14="Cleared",'Approved Work Queue'!$AB$14,"") | F14: =IF('Approved Work Queue'!$V$14="Cleared",'Approved Work Queue'!$AD$14,"") | G14: =IF('Approved Work Queue'!$V$14="Cleared",'Approved Work Queue'!$AG$14,"") | H14: =IF('Approved Work Queue'!$V$14="Cleared",'Approved Work Queue'!$V$14,"") | I14: =IF('Approved Work Queue'!$V$14="Cleared",'Approved Work Queue'!$AK$14,"")
A15: =IF('Approved Work Queue'!$V$15="Cleared",'Approved Work Queue'!$W$15,"") | B15: =IF('Approved Work Queue'!$V$15="Cleared",'Approved Work Queue'!$D$15,"") | C15: =IF('Approved Work Queue'!$V$15="Cleared",'Approved Work Queue'!$E$15,"") | D15: =IF('Approved Work Queue'!$V$15="Cleared",'Approved Work Queue'!$F$15,"") | E15: =IF('Approved Work Queue'!$V$15="Cleared",'Approved Work Queue'!$AB$15,"") | F15: =IF('Approved Work Queue'!$V$15="Cleared",'Approved Work Queue'!$AD$15,"") | G15: =IF('Approved Work Queue'!$V$15="Cleared",'Approved Work Queue'!$AG$15,"") | H15: =IF('Approved Work Queue'!$V$15="Cleared",'Approved Work Queue'!$V$15,"") | I15: =IF('Approved Work Queue'!$V$15="Cleared",'Approved Work Queue'!$AK$15,"")
A16: =IF('Approved Work Queue'!$V$16="Cleared",'Approved Work Queue'!$W$16,"") | B16: =IF('Approved Work Queue'!$V$16="Cleared",'Approved Work Queue'!$D$16,"") | C16: =IF('Approved Work Queue'!$V$16="Cleared",'Approved Work Queue'!$E$16,"") | D16: =IF('Approved Work Queue'!$V$16="Cleared",'Approved Work Queue'!$F$16,"") | E16: =IF('Approved Work Queue'!$V$16="Cleared",'Approved Work Queue'!$AB$16,"") | F16: =IF('Approved Work Queue'!$V$16="Cleared",'Approved Work Queue'!$AD$16,"") | G16: =IF('Approved Work Queue'!$V$16="Cleared",'Approved Work Queue'!$AG$16,"") | H16: =IF('Approved Work Queue'!$V$16="Cleared",'Approved Work Queue'!$V$16,"") | I16: =IF('Approved Work Queue'!$V$16="Cleared",'Approved Work Queue'!$AK$16,"")

Sheet Daily Runbook
A1: July 17–24 Daily Runbook
A2: Column C prepares accounts against their conditional contact targets. Only accounts appearing on Cleared Contact Path may enter column D.
A4: Date | B4: Supervisor Focus | C4: Pre-contact Clearance Work | D4: Cleared Customer Contacts Only | E4: Exception / Hold Check | F4: 16:00 ET Checkpoint Deliverable | G4: Completion Status | H4: Supervisor Note
A5: 46220 | B5: Launch: validate evidence, authorize only cleared rows, assign rep actions. | C5: A-1001, A-1003, A-1004, A-1009 | D5: None until rows appear on Cleared Contact Path | E5: A-1014 manager credit decision | F5: Gate status, released actions, blocked items, and owner/due date. | G5: Not started
A6: 46223 | B6: Clear weekend operational dependencies and run highest-risk outreach. | C6: A-1005, A-1012, A-1007, A-1006 | D6: Use Cleared Contact Path only | E6: A-1013 contact-route decision | F6: Outreach result, customer response, missed gates, and updated forecast risk. | G6: Not started
A7: 46224 | B7: Complete reporting-package actions and evidence-only follow-up. | C7: A-1002, A-1011, A-1008 | D7: Use Cleared Contact Path only | E7: A-1015 product-feed status | F7: Reports delivered, follow-ups booked, exception changes, and forecast risk. | G7: Not started
A8: 46225 | B8: Complete rate-hold action and rescue any slipped approved account. | C8: A-1010 plus slipped approved rows | D8: Use Cleared Contact Path only | E8: A-1015 feed-fix decision | F8: Completed actions, rescue assignments, outstanding customer decisions. | G8: Not started
A9: 46226 | B9: Resolve follow-ups and prepare closeout reconciliation. | C9: All open approved rows | D9: Use Cleared Contact Path only | E9: A-1017 legal route status | F9: Open actions with owners/dates; draft decision and forecast reconciliation. | G9: Not started
A10: 46227 | B10: Final follow-up and sprint closeout. | C10: A-1001 renewal checkpoint; all remaining approved rows | D10: Use Cleared Contact Path only | E10: All four exceptions; confirm A-1016/A-1018 remain held | F10: Final model decision, outreach status, exceptions, and forecast-risk change. | G10: Not started

Sheet Controlled Exceptions
A1: Controlled Exception Queue
A2: Visible to the supervisor, but not releasable as local customer commitments.
A4: Control Lane | B4: Account ID | C4: Account Name | D4: Owner Rep | E4: Supervisor | F4: Renewal Date | G4: Renewal Exposure | H4: Forecast Variance | I4: Primary Issue | J4: Exception Reason | K4: Escalation Owner | L4: Decision Due | M4: Required Route | N4: Customer Contact Rule | O4: Exception Status | P4: Checkpoint Note | Q4: Next Step
A5: CONTROLLED — NO LOCAL COMMITMENT | B5: A-1014 | C5: SummitBank SMB Services | D5: Luis Romero | E5: Dana Morales | F5: 46233 | G5: 360000 | H5: -60000 | I5: Billing Error | J5: Requested credit is above supervisor authority | K5: Sales manager | L5: 46220 | M5: Decide the $42,000 over-limit credit route; no local credit promise. | N5: No local commitment; evidence-only contact where directory permits. | O5: Open | Q5: Decide the $42,000 over-limit credit route; no local credit promise.
A6: CONTROLLED — NO LOCAL COMMITMENT | B6: A-1017 | C6: Atlas BioLabs | D6: Jordan Patel | E6: Dana Morales | F6: 46262 | G6: 520000 | H6: -110000 | I6: Data-Use Terms | J6: Contract terms outside local authority | K6: Sales manager and Legal | L6: 46227 | M6: Draft the data-use response through the manager/legal route; no rep commitment. | N6: No local commitment; evidence-only contact where directory permits. | O6: Open | Q6: Draft the data-use response through the manager/legal route; no rep commitment.
A7: CONTROLLED — NO LOCAL COMMITMENT | B7: A-1015 | C7: Mesa Tool Supply | D7: Devon Brooks | E7: Dana Morales | F7: 46241 | G7: 210000 | H7: -38000 | I7: Product Feed Blocker | J7: Ad-ops blocker not cleared | K7: Product Support / Ad Ops | L7: 46225 | M7: Clear the feed blocker and provide feasibility proof before any package-swap offer. | N7: No local commitment; evidence-only contact where directory permits. | O7: Open | Q7: Clear the feed blocker and provide feasibility proof before any package-swap offer.
A8: CONTROLLED — NO LOCAL COMMITMENT | B8: A-1013 | C8: BrightPath Dental Alliance | D8: Priya Nair | E8: Dana Morales | F8: 46251 | G8: 165000 | H8: -12000 | I8: Delivery Underpacing | J8: Decision-maker outreach permission pending | K8: Supervisor / contact-route approval | L8: 46223 | M8: Obtain permission for the final approver route; operational contact may receive issue evidence only. | N8: No local commitment; evidence-only contact where directory permits. | O8: Open | Q8: Obtain permission for the final approver route; operational contact may receive issue evidence only.

Sheet Excluded and Holds
A1: Excluded and Hold Records
A2: No sprint outreach or local commercial action.
A4: Account ID | B4: Account Name | C4: Owner Rep | D4: Status | E4: Reason | F4: Permitted Supervisor Action | G4: Review Date | H4: Note
A5: A-1016 | B5: Riverstone Fitness | C5: Maya Chen | D5: Excluded — closed renewal | E5: Issue resolved and renewal signed. | F5: Retain closure evidence only. | G5: 46227 | H5: No outreach.
A6: A-1018 | B6: Pinyon Outdoor Media Buyers | C6: Priya Nair | D6: Customer hold | E6: Agency requested September consolidation review. | F6: Preserve hold and schedule September rebrief only. | G6: 46267 | H6: No July outreach.

Sheet Source Reconciliation
A1: Account-by-Account Source Reconciliation
A2: Reconciles the package to CRM health, opportunity exposure, ops cases, contact authority, offer authority, the watchlist, and the July 15 approval.
A4: Account ID | B4: Account Name | C4: July 15 Approval Scope | D4: Package Control Lane | E4: Scope Match | F4: CRM Lifecycle State | G4: CRM Opportunity Approval | H4: Owner Match | I4: Renewal Date Match | J4: Exposure Match | K4: Requested Value Match | L4: Watchlist Risk Rank | M4: Watchlist Offer | N4: Offer / Authority Check | O4: Ops Case Count | P4: Ops Max Severity | Q4: Ops Average Age | R4: Ops Status and Dependencies | S4: Contact Route | T4: Contact Control Check | U4: Conditional Contact Target | V4: Initial Release State | W4: Overall Reconciliation | X4: Required Supervisor Disposition | Y4: Correction / Control Note
A5: A-1001 | B5: Meridian Health Partners | C5: Approved local execution | D5: WORK NOW — CLEAR / PREPARE | E5: Pass | F5: Approved execution | G5: Approved execution | H5: Pass | I5: Pass | J5: Pass | K5: Pass | L5: 2 | M5: MG-15 | N5: Pass | O5: Pass | P5: Pass | Q5: Pass | R5: CASE-7201 Waiting on Ad Ops; CASE-7202 Open | CASE-7201: Traffic pacing confirmation; CASE-7202: Reach report reconciliation | S5: Dr. Lena Morris: Approved | T5: Pass | U5: 46220 | V5: Pending evidence — no customer contact | W5: RECONCILED — PENDING EVIDENCE | X5: Traffic pacing confirmation and makegood inventory validation attached to CASE-7201.
A6: A-1002 | B6: Larkspur Credit Union | C6: Approved local execution | D6: WORK NOW — CLEAR / PREPARE | E6: Pass | F6: Approved execution | G6: Approved execution | H6: Pass | I6: Pass | J6: Pass | K6: Pass | L6: 10 | M6: RPT-COMP | N6: Pass | O6: Pass | P6: Pass | Q6: Pass | R6: CASE-7203 Open | CASE-7203: Corrected report | S6: Tanya Wells: Approved | T6: Pass | U6: 46224 | V6: Pending evidence — no customer contact | W6: RECONCILED — PENDING EVIDENCE | X6: Corrected reach report and customer-facing reconciliation summary attached.
A7: A-1003 | B7: Cobalt Cloud Systems | C7: Approved local execution | D7: WORK NOW — CLEAR / PREPARE | E7: Pass | F7: Approved execution | G7: Approved execution | H7: Pass | I7: Pass | J7: Pass | K7: Pass | L7: 7 | M7: CR-10K | N7: Pass for CR-10K only; RH-60 excluded for Key Growth | O7: Pass | P7: Pass | Q7: Pass | R7: CASE-7204 Resolved Pending Customer; CASE-7205 Waiting on Sales | CASE-7204: Credit memo confirmation; CASE-7205: Rate hold language | S7: Rafael Soto: Approved | T7: Pass | U7: 46220 | V7: Pending evidence — no customer contact | W7: RECONCILED — PENDING EVIDENCE | X7: Verified credit memo up to $9,500 attached; any rate-hold request removed or separately escalated. | Y7: Watchlist action mixed CR-10K with an ineligible RH-60 rate hold. Package restricts local action to CR-10K and treats CASE-7204 as the controlling evidence date.
A8: A-1004 | B8: Harborview Furnishings | C8: Approved local execution | D8: WORK NOW — CLEAR / PREPARE | E8: Pass | F8: Approved execution | G8: Approved execution | H8: Pass | I8: Pass | J8: Pass | K8: Pass | L8: 11 | M8: SW-PKG | N8: Pass | O8: Pass | P8: Pass | Q8: Pass | R8: CASE-7206 Waiting on Ad Ops | CASE-7206: Creative retagging | S8: Nina Cho: Approved | T8: Pass | U8: 46220 | V8: Pending evidence — no customer contact | W8: RECONCILED — PENDING EVIDENCE | X8: Creative retagging confirmation and package-swap feasibility documented by Ad Ops.
A9: A-1005 | B9: Axion Robotics | C9: Approved local execution | D9: WORK NOW — CLEAR / PREPARE | E9: Pass | F9: Approved execution | G9: Approved execution | H9: Pass | I9: Pass | J9: Pass | K9: Pass | L9: 1 | M9: SW-PKG | N9: Pass | O9: Pass | P9: Pass | Q9: Pass | R9: CASE-7207 Open; CASE-7208 Waiting on Ad Ops | CASE-7207: Audience rebuild proof; CASE-7208: Pacing reset | S9: Mark Feld: Approved | T9: Pass | U9: 46223 | V9: Pending evidence — no customer contact | W9: RECONCILED — PENDING EVIDENCE | X9: Audience rebuild proof and package-swap feasibility confirmed by Product Support / Ad Ops.
A10: A-1006 | B10: Greenway Kitchens | C10: Approved local execution | D10: WORK NOW — CLEAR / PREPARE | E10: Pass | F10: Approved execution | G10: Approved execution | H10: Pass | I10: Pass | J10: Pass | K10: Pass | L10: 13 | M10: CR-10K | N10: Pass | O10: Pass | P10: Pass | Q10: Pass | R10: CASE-7209 Open | CASE-7209: Credit memo draft | S10: Gloria Kim: Approved | T10: Pass | U10: 46223 | V10: Pending evidence — no customer contact | W10: RECONCILED — PENDING EVIDENCE | X10: Verified credit memo up to $4,800 and corrected bill date attached.
A11: A-1007 | B11: Northline Insurance | C11: Approved local execution | D11: WORK NOW — CLEAR / PREPARE | E11: Pass | F11: Approved execution | G11: Approved execution | H11: Pass | I11: Pass | J11: Pass | K11: Pass | L11: 6 | M11: MG-15 | N11: Pass | O11: Pass | P11: Pass | Q11: Pass | R11: CASE-7210 Waiting on Ad Ops | CASE-7210: Makegood placement | S11: Samira Ahmad: Approved | T11: Pass | U11: 46223 | V11: Pending evidence — no customer contact | W11: RECONCILED — PENDING EVIDENCE | X11: Makegood placement and revised delivery dates confirmed by Ad Ops.
A12: A-1008 | B12: Veridian Charter Schools | C12: Approved local execution | D12: WORK NOW — CLEAR / PREPARE | E12: Pass | F12: Approved execution | G12: Approved execution | H12: Pass | I12: Pass | J12: Pass | K12: Pass | L12: 15 | M12: RPT-COMP | N12: Pass | O12: Pass | P12: Pass | Q12: Pass | R12: CASE-7211 Open | CASE-7211: Corrected district report | S12: Julian Pierce: Approved | T12: Pass | U12: 46224 | V12: Pending evidence — no customer contact | W12: RECONCILED — PENDING EVIDENCE | X12: Corrected district reach report and renewal summary attached.
A13: A-1009 | B13: Copper Trail Hospitality | C13: Approved local execution | D13: WORK NOW — CLEAR / PREPARE | E13: Pass | F13: Approved execution | G13: Approved execution | H13: Pass | I13: Pass | J13: Pass | K13: Pass | L13: 8 | M13: SW-PKG | N13: Pass | O13: Pass | P13: Pass | Q13: Pass | R13: CASE-7212 Waiting on Ad Ops | CASE-7212: Creative approval proof | S13: Cora Lind: Approved | T13: Pass | U13: 46220 | V13: Pending evidence — no customer contact | W13: RECONCILED — PENDING EVIDENCE | X13: Creative approval proof and equivalent package-swap feasibility confirmed by Ad Ops.
A14: A-1010 | B14: Finch Legal Group | C14: Approved local execution | D14: WORK NOW — CLEAR / PREPARE | E14: Pass | F14: Approved execution | G14: Approved execution | H14: Pass | I14: Pass | J14: Pass | K14: Pass | L14: 17 | M14: RH-60 | N14: Pass | O14: Pass | P14: Pass | Q14: Pass | R14: CASE-7213 Waiting on Sales | CASE-7213: Rate hold note | S14: Evan Finch: Approved | T14: Pass | U14: 46225 | V14: Pending evidence — no customer contact | W14: RECONCILED — PENDING EVIDENCE | X14: 60-day CPM hold language documented with no additional credit.
A15: A-1011 | B15: Solstice Energy Co-op | C15: Approved local execution | D15: WORK NOW — CLEAR / PREPARE | E15: Pass | F15: Approved execution | G15: Approved execution | H15: Pass | I15: Pass | J15: Pass | K15: Pass | L15: 12 | M15: RPT-COMP | N15: Pass | O15: Pass | P15: Pass | Q15: Pass | R15: CASE-7214 Open | CASE-7214: Corrected lift model | S15: Imani Hart: Approved | T15: Pass | U15: 46224 | V15: Pending evidence — no customer contact | W15: RECONCILED — PENDING EVIDENCE | X15: Corrected lift model and customer-facing summary attached.
A16: A-1012 | B16: Vesta Apparel Collective | C16: Approved local execution | D16: WORK NOW — CLEAR / PREPARE | E16: Pass | F16: Approved execution | G16: Approved execution | H16: Pass | I16: Pass | J16: Pass | K16: Pass | L16: 4 | M16: MG-15 | N16: Pass | O16: Pass | P16: Pass | Q16: Pass | R16: CASE-7215 Waiting on Ad Ops; CASE-7216 Open | CASE-7215: Makegood placement; CASE-7216: Invoice correction | S16: Marta Ruiz: Approved | T16: Pass | U16: 46223 | V16: Pending evidence — no customer contact | W16: RECONCILED — PENDING EVIDENCE | X16: Makegood placement validated and invoice PO correction route documented.
A17: A-1013 | B17: BrightPath Dental Alliance | C17: Controlled exception | D17: CONTROLLED — NO LOCAL COMMITMENT | E17: Pass | F17: Controlled exception | G17: Controlled exception | H17: Pass | I17: Pass | J17: Pass | K17: Pass | L17: 14 | M17: MG-15 | N17: Pass offer fit; controlled by contact permission | O17: Pass | P17: Pass | Q17: Pass | R17: CASE-7217 Open | CASE-7217: Pacing check | S17: Alice Go: Pending | T17: Controlled — final approver permission pending | V17: Controlled — no local commitment | W17: RECONCILED — CONTROLLED | X17: Obtain permission for the final approver route; operational contact may receive issue evidence only. | Y17: Offer fit alone does not clear the account; final-approver permission remains pending.
A18: A-1014 | B18: SummitBank SMB Services | C18: Controlled exception | D18: CONTROLLED — NO LOCAL COMMITMENT | E18: Pass | F18: Controlled exception | G18: Controlled exception | H18: Pass | I18: Pass | J18: Pass | K18: Pass | L18: 3 | M18: MGR-REQ | N18: Controlled manager route — not a local offer | O18: Pass | P18: Pass | Q18: Pass | R18: CASE-7218 Resolved Pending Customer | CASE-7218: Manager approval | S18: Brent Ivers: Approved | T18: Consistent with hold/exception lane | V18: Controlled — no local commitment | W18: RECONCILED — CONTROLLED | X18: Decide the $42,000 over-limit credit route; no local credit promise. | Y18: The $42,000 request exceeds local authority and remains MGR-REQ.
A19: A-1015 | B19: Mesa Tool Supply | C19: Controlled exception | D19: CONTROLLED — NO LOCAL COMMITMENT | E19: Pass | F19: Controlled exception | G19: Controlled exception | H19: Pass | I19: Pass | J19: Pass | K19: Pass | L19: 9 | M19: SW-PKG | N19: Pass offer fit; controlled by unresolved ops blocker | O19: Pass | P19: Pass | Q19: Pass | R19: CASE-7219 Waiting on Ad Ops | CASE-7219: Feed fix proof | S19: Mei Carter: Approved | T19: Consistent with hold/exception lane | V19: Controlled — no local commitment | W19: RECONCILED — CONTROLLED | X19: Clear the feed blocker and provide feasibility proof before any package-swap offer. | Y19: SW-PKG fits tier/value, but the product-feed blocker prevents local release.
A20: A-1016 | B20: Riverstone Fitness | C20: Excluded / hold | D20: EXCLUDED / HOLD | E20: Pass | F20: Excluded - closed renewal | G20: Excluded - no action | H20: Pass | I20: Pass | J20: Pass | K20: Pass | L20: 16 | M20: None | N20: Not applicable — no local offer | O20: Pass | P20: Pass | Q20: Pass | R20: No open cases | None | S20: Hannah Roy: Approved | T20: Consistent with hold/exception lane | V20: Excluded / hold — no July contact | W20: RECONCILED — EXCLUDED / HOLD | X20: No sprint action; keep closure note
A21: A-1017 | B21: Atlas BioLabs | C21: Controlled exception | D21: CONTROLLED — NO LOCAL COMMITMENT | E21: Pass | F21: Controlled exception | G21: Controlled exception | H21: Pass | I21: Pass | J21: Pass | K21: Pass | L21: 5 | M21: MGR-REQ | N21: Controlled manager route — not a local offer | O21: Pass | P21: Pass | Q21: Pass | R21: CASE-7221 Open; CASE-7222 Open | CASE-7221: Legal review; CASE-7222: Segment report | S21: Dr. Paolo Kent: Do not contact executive | T21: Controlled — executive do-not-contact / manager-legal route | V21: Controlled — no local commitment | W21: RECONCILED — CONTROLLED | X21: Draft the data-use response through the manager/legal route; no rep commitment. | Y21: Enterprise data-use terms remain with manager/legal; executive contact is prohibited.
A22: A-1018 | B22: Pinyon Outdoor Media Buyers | C22: Excluded / hold | D22: EXCLUDED / HOLD | E22: Pass | F22: Excluded - September review | G22: Excluded - no action | H22: Pass | I22: Pass | J22: Pass | K22: Pass | L22: 18 | M22: None | N22: Not applicable — no local offer | O22: Pass | P22: Pass | Q22: Pass | R22: CASE-7223 Waiting on Customer | CASE-7223: September rebrief | S22: Morgan Price: Pending | T22: Hold — customer requested September review | V22: Excluded / hold — no July contact | W22: RECONCILED — EXCLUDED / HOLD | X22: Hold for September agency review | Y22: Customer-requested September hold overrides risk priority.

Sheet Authority Reference
A1: Local Recovery Authority — Quick Reference
A2: Effective July 15–September 30, 2026. The source authority document remains controlling.
A4: Offer Code | B4: Issue Basis | C4: Eligible Tiers | D4: Authority Limit | E4: Approval | F4: Permitted Use | G4: If Evidence Is Missing
A5: MG-15 | B5: Delivery Underpacing | C5: Key Growth, Core, Emerging | D5: $25,000 | E5: Supervisor | F5: Makegood inventory up to 15% of affected booked impressions after ad-ops validation. | G5: Hold
A6: CR-10K | B6: Billing Error | C6: Key Growth, Core, Emerging | D6: $10,000 | E6: Supervisor | F6: Verified invoice credit up to $10,000 with billing case attached. | G6: Hold
A7: RH-60 | B7: Renewal Rate Objection | C7: Core, Emerging | D7: No credit | E7: Supervisor | F7: Hold current renewal CPM for 60 days when no extra credit is promised. | G7: Exception
A8: SW-PKG | B8: Creative Trafficking; Audience Mismatch; Product Feed Blocker | C8: Key Growth, Core, Emerging | D8: $18,000 | E8: Supervisor | F8: Equivalent-value package swap after operational owner confirms feasibility. | G8: Hold
A9: RPT-COMP | B9: Reporting Discrepancy | C9: Key Growth, Core, Emerging | D9: No credit | E9: Supervisor | F9: Expedited reporting reconciliation package with customer-facing summary. | G9: Hold
A10: MGR-REQ | B10: Over-limit or unsupported | C10: All | D10: No credit | E10: Manager required | F10: Controlled exception route for over-limit credits, legal terms, unsupported offers, or missing authority. | G10: Manager / functional owner

Sheet Source Control
A1: Source Lineage and Package Corrections
A2: Source dates are preserved so the supervisor can identify stale evidence before release.
A4: Source | B4: As-of / Effective Date | C4: Use in Package | D4: Control Note
A5: data/revenue_ops_review/escalation_watchlist_review_2026-07-14.xlsx | B5: Review 2026-07-14 | C5: Risk scores, tiers, proposed actions | D5: Global risk rank replaced by an execution-only rank plus separate exception/hold lanes.
A6: data/crm_health/escalated_account_health_export_2026-07-13.xlsx | B6: Export 2026-07-13 | C6: Account, renewal, approval, forecast context | D6: Refresh changed renewal or approval state before outreach.
A7: data/ad_ops_cases/open_ad_ops_case_queue_2026-07-13.csv | B7: Queue 2026-07-13; some updates through 2026-07-14 | C7: Case owner, dependency, expected resolution | D7: Gate clearance requires current owner evidence, not the file date alone.
A8: data/contacts/advertiser_contact_and_authority_directory_2026-07-10.xlsx | B8: Directory 2026-07-10 | C8: Approved contact route and restrictions | D8: Reconfirm any pending or restricted route.
A9: data/rep_activity/rep_touchpoints_and_commitments_2026-04-01_to_2026-07-14.csv | B9: Through 2026-07-14 | C9: Commitments, due dates, next steps | D9: Checkpoint fields in this package become the sprint record.
A10: data/commercial_options/local_recovery_offer_authority_q3_2026.docx | B10: Effective 2026-07-15 to 2026-09-30 | C10: Offer codes, caps, evidence gates, escalation rules | D10: Controlling authority source.
A11: data/approvals/recovery_sprint_scope_approval_2026-07-15.eml | B11: Approved 2026-07-15 | C11: Supervisor, execution window, account scope | D11: Controlling sprint approval source.
A12: Package correction: A-1003 | B12: Applied in this workbook | C12: Local action and guardrail | D12: Removed unsupported RH-60 language; Key Growth is not RH-60 eligible. CR-10K only unless separately approved.
